Workbook

Sheet Leia-me
A1: Tópico | B1: Conteúdo
A2: O que é este arquivo | B2: Configuração e classificação da Fase 2. Nada aqui é o indicador final. Os limiares de materialidade estão em branco para você preencher.
A3: Período | B3: 2026-01 a 2026-08. Agosto é o último mês fechado em 23/09/2026. Edite em Configuracao; os números desta geração usam esse recorte.
A4: Regime | B4: Eixo = competência (competencia_titulo, valor do item). Caixa (data_pagamento, valor pago) entra na conciliação. Os dois estão calculados.
A5: Referência 2026 | B5: Não é orçamento aprovado. Referência montada em jul/2026 a partir do realizado até ago. Aba Referencia_2026.
A6: Sócios de capital | B6: Pró-labore 8.1.03, contas nominais de sócios e distribuição de lucros ficam FORA do OPEX, na linha Remuneração de sócios de capital, abaixo do resultado operacional. Associados (8.1.01) e sócios de serviço permanecem em Pessoas.
A7: Reembolso | B7: PAGAR com departamento Conta Corrente Clientes sai do OPEX. Custas 5.6.02, 2.6.01, 2.6.01.005, 2.6.03, 5.16.06 e 5.16.07 em qualquer outro departamento ficam no OPEX, grupo Despesas Processuais, com flag.
A8: Repasse | B8: 2.6.04.000 está fora do OPEX e não teve movimento no período. O repasse efetivo está em 3.2.07.000 (REPASSE DE OUTRAS RECEITAS), também fora. A entrada correspondente no RECEBER está documentada na aba Repasse.
A9: Tributos | B9: DAS 2.2.06.002, DARF 2.2.06.001, ISS 3.3.01.000, ISSQN 2.2.06.003 e Tributos 2.2.06.000 saem do OPEX. No período essas contas estão zeradas, exceto ISS (R$ 209,13). O DAS, o parcelamento do Simples e o PGFN foram lançados na 5.14.03 e saíram do OPEX com status sugerida e flag composição pendente. Anuidade e demais linhas da 5.14.03 permanecem no OPEX, com flag para revisão.
A10: Financeiras | B10: 5.18.01, 5.18.02, 5.18.04 e 5.18.05 ficam no OPEX (Administrativo e Financeiro / Custos bancários e de cobrança). 5.18.03 multas e juros fica fora.
A11: Como editar | B11: Na aba Lancamentos, preencha override_dentro_opex ou override_recorrente. A coluna final e a Reconciliacao em fórmula acompanham o override. A classificação sugerida está na aba Classificacao_contas.
A12: Materialidade | B12: Um item só é material se o valor E o percentual sobre o OPEX de competência atingirem os dois limiares. Enquanto estiverem vazios, a coluna fica "aguardando limiar".
... A14: 13º e férias | B14: provisionar_13_ferias = sim. A aba Provisao_13_ferias mostra o lançado e uma provisão sugerida (soma do período / 8). A base não é folha individual, porque o cadastro não tem custo por pessoa.

Sheet Configuracao
A1: parametro | B1: valor | C1: opcoes_ou_nota
A2: periodo_inicio | B2: 2026-01 | C2: editável
A3: periodo_fim | B3: 2026-08 | C3: último mês fechado em 23/09/2026
A4: regime_eixo | B4: competencia | C4: competencia | caixa
A5: regime_conciliacao | B5: caixa | C5: o outro regime, para bater caixa e competência
A6: calcular_ambos | B6: sim | C6: os dois regimes estão nas colunas valor_competencia e valor_caixa
A7: receita_referencia | B7: liquida_faturada | C7: liquida_faturada (eficiência) | recebida (só leitura de caixa)
A8: tratamento_socios | B8: fora_do_opex | C8: fora_do_opex | dentro_do_opex
A9: limiar_materialidade_valor | C9: R$. Preencher. Item material só se valor E percentual passarem.
A10: limiar_materialidade_pct | C10: Percentual sobre o OPEX de competência do período. Ex.: 1 para 1%.
A11: peso_fte_estagiario | B11: 0.75 | C11: usado na aba Pessoas_fte
A12: meses_run_rate | B12: 3 | C12: parâmetro para a fase de cálculo; ainda não aplicado a um indicador
A13: provisionar_13_ferias | B13: sim | C13: ver aba Provisao_13_ferias
A14: nome_orcamento | B14: Referência 2026 | C14: não é orçamento aprovado
A15: nota_orcamento | B15: referência montada em jul/2026 a partir do realizado até ago | C15: usar este texto em qualquer saída

Sheet Exclusoes
A1: regra | B1: chave | C1: efeito | D1: destino | E1: status | F1: nota
A2: departamento | B2: Conta Corrente Clientes | C2: fora do OPEX | D2: Despesas reembolsáveis de clientes | E2: confirmada | F2: Vale para qualquer conta PAGAR nesse departamento.
A3: conta | B3: 2.6.04.000 | C3: fora do OPEX | D3: Repasse ao cliente | E3: confirmada | F3: Sem movimento em jan–ago/2026.
A4: conta | B4: 3.2.07.000 | C4: fora do OPEX | D4: Repasse ao cliente | E4: confirmada | F4: É a conta que carrega o repasse no período.
A5: conta | B5: 8.1.03.000 | C5: fora do OPEX | D5: Remuneração de sócios de capital | E5: confirmada | F5: Pró-labore = sócio de capital.
A6: conta | B6: 2.4.01.000 | C6: fora do OPEX | D6: Remuneração de sócios de capital | E6: confirmada | F6: Conta nominal Ricardo Pires.
A7: conta | B7: 2.4.02.000 | C7: fora do OPEX | D7: Remuneração de sócios de capital | E7: confirmada | F7: Conta nominal Gustavo Bismarchi.
A8: conta | B8: 7.1.01.000 | C8: fora do OPEX | D8: Remuneração de sócios de capital | E8: confirmada | F8: Distribuição de lucros.
A9: conta | B9: 7.1.02.000 | C9: fora do OPEX | D9: Remuneração de sócios de capital | E9: confirmada | F9: Dividendos parcelas fixas.
A10: prefixo | B10: 10. | C10: fora do OPEX | D10: Investimento / CAPEX | E10: confirmada
A11: prefixo | B11: 3.4 | C11: fora do OPEX | D11: Deduções da receita | E11: confirmada | F11: Devolução de honorários.
A12: conta | B12: 2.2.06.002 | C12: fora do OPEX | D12: Deduções / tributos sobre faturamento | E12: confirmada | F12: DAS. Flag composição pendente.
A13: conta | B13: 2.2.06.001 | C13: fora do OPEX | D13: Deduções / tributos sobre faturamento | E13: confirmada | F13: DARF. Flag composição pendente.
A14: conta | B14: 3.3.01.000 | C14: fora do OPEX | D14: Deduções / tributos sobre faturamento | E14: confirmada | F14: ISS. Flag composição pendente.
A15: conta | B15: 2.2.06.003 | C15: fora do OPEX | D15: Deduções / tributos sobre faturamento | E15: confirmada | F15: ISSQN. Flag composição pendente.
A16: conta | B16: 2.2.06.000 | C16: fora do OPEX | D16: Deduções / tributos sobre faturamento | E16: confirmada | F16: Tributos da sede. Flag composição pendente. Sem movimento no período.
A17: descrição na conta de impostos | B17: DAS, DARF, ISSQN, Simples Nacional, parcelamento PGFN | C17: fora do OPEX | D17: Deduções / tributos sobre faturamento | E17: sugerida | F17: No período isso está na 5.14.03, não nas contas 2.2.06. Anuidade da mesma conta permanece no OPEX.
A18: conta | B18: 5.18.03.000 | C18: fora do OPEX | D18: Multas e juros | E18: confirmada
A19: prefixo | B19: 1.1.02 / 1.1.03 / 1.1.08 | C19: fora do OPEX | D19: Adiantamento ou transferência | E19: sugerida | F19: Não é despesa operacional. Entra na reconciliação como excluído.
A20: conta | B20: 5.6.02 / 2.6.01 / 2.6.01.005 / 2.6.03 / 5.16.06 / 5.16.07 | C20: dentro do OPEX | D20: Despesas Processuais | E20: confirmada | F20: Só quando o departamento NÃO é Conta Corrente Clientes. Flag processual_possivelmente_reembolsavel.
A21: conta | B21: 4.1.01 / 4.1.02 / 2.3.07 | C21: dentro do OPEX | D21: Comissões | E21: confirmada | F21: Natureza variável.
A22: conta | B22: 5.18.01 / 5.18.02 / 5.18.04 / 5.18.05 | C22: dentro do OPEX | D22: Administrativo e Financeiro | E22: confirmada | F22: Subgrupo Custos bancários e de cobrança. 5.18.05 = tarifas de boleto.
A23: receita | B23: RECEBER + Conta Corrente Clientes + REEMBOLSO DE DESPESAS | C23: fora da receita | D23: Reembolso de despesas | E23: confirmada | F23: Não entra na receita de referência.

Sheet Classificacao_contas
A1: conta_numero | B1: plano_contas | C1: grupo_conta | D1: dentro_opex | E1: status_perimetro | F1: motivo_perimetro | G1: grupo_gerencial | H1: subgrupo | I1: natureza | J1: controlabilidade | K1: tipo | L1: potencial_eficiencia | M1: status_classificacao | N1: flag | O1: qtd_lancamentos | P1: valor_competencia | Q1: valor_caixa | R1: pct_opex_competencia
A2: 8.1.01.000 | B2: HONORÁRIOS ASSOCIADOS | C2: REMUNERAÇãO FIXA | D2: sim | E2: confirmada | G2: Pessoas | H2: Associados | I2: fixa | J2: contratual | K2: despesa | L2: médio | M2: sugerida | O2: 394 | P2: 2275610.7 | Q2: 2540065 | R2: 0.51271007
A3: 7.1.01.000 | B3: DISTRIBUIÇãO DE LUCROS | C3: DISTRIBUIÇãO DE LUCROS | D3: não | E3: confirmada | F3: Remuneração de sócios de capital | G3: Remuneração de sócios de capital | H3: Remuneração de sócios de capital | I3: — | J3: — | K3: exclusão | L3: não avaliado | M3: confirmada | N3: abaixo_do_resultado_operacional | O3: 274 | P3: 1782959.5 | Q3: 1783854.4 | R3: 0
A4: 8.1.03.000 | B4: PRÓ-LABORE | C4: REMUNERAÇãO FIXA | D4: não | E4: confirmada | F4: Remuneração de sócios de capital | G4: Remuneração de sócios de capital | H4: Remuneração de sócios de capital | I4: — | J4: — | K4: exclusão | L4: não avaliado | M4: confirmada | N4: abaixo_do_resultado_operacional | O4: 39 | P4: 942000 | Q4: 942000 | R4: 0
A5: 3.2.07.000 | B5: REPASSE DE OUTRAS RECEITAS | C5: OUTRAS RECEITAS OPERACIONAIS | D5: não | E5: confirmada | F5: Repasse ao cliente (3.2.07 REPASSE DE OUTRAS RECEITAS; 2.6.04 sem movimento no período) | G5: Repasse ao cliente | H5: Repasse ao cliente (3.2.07 REPASSE DE OUTRAS RECEITAS; 2.6.04 sem movimento no período) | I5: — | J5: — | K5: exclusão | L5: não avaliado | M5: confirmada | N5: repasse | O5: 53 | P5: 835346.5 | Q5: 856695.8 | R5: 0
A6: 5.14.03.000 | B6: IMPOSTOS E TAXAS | C6: IMPOSTOS, TAXAS E SEGUROS | D6: não | E6: sugerida | F6: Deduções / tributos sobre faturamento | G6: Deduções / tributos sobre faturamento | H6: Deduções / tributos sobre faturamento | I6: — | J6: — | K6: exclusão | L6: não avaliado | M6: sugerida | N6: composicao_pendente;lancado_em_5.14.03.000_descricao_DAS_parcelamento | O6: 24 | P6: 543014.18 | Q6: 543014.18 | R6: 0
A7: 5.8.20.000 | B7: CONSULTORIA | C7: DESPESAS COM SERVIÇOS DE TERCEIROS | D7: sim | E7: confirmada | G7: Serviços Terceirizados | H7: Serviços de terceiros | I7: semivariável | J7: contratual | K7: despesa | L7: alto | M7: sugerida | O7: 52 | P7: 252652.93 | Q7: 252324.42 | R7: 0.056924368
A8: 3.2.07.000 | B8: REPASSE DE OUTRAS RECEITAS | C8: OUTRAS RECEITAS OPERACIONAIS | D8: não | E8: confirmada | F8: Despesas reembolsáveis de clientes | G8: Despesas reembolsáveis de clientes | H8: Despesas reembolsáveis de clientes | I8: — | J8: — | K8: exclusão | L8: não avaliado | M8: confirmada | N8: departamento_conta_corrente_clientes | O8: 3 | P8: 233028.81 | Q8: 233028.81 | R8: 0
A9: 5.13.01.000 | B9: ALUGUEL DE IMÓVEL | C9: ALUGUÉIS | D9: sim | E9: confirmada | G9: Ocupação/Facilities | H9: Aluguel | I9: fixa | J9: contratual | K9: despesa | L9: baixo | M9: sugerida | O9: 8 | P9: 214683.01 | Q9: 214683.01 | R9: 0.048369495
A10: 4.1.02.000 | B10: COMISSÕES INTERNAS | C10: COMISSÕES SOBRE VENDAS | D10: sim | E10: confirmada | G10: Comissões | H10: Comissões | I10: variável | J10: decisão interna | K10: despesa | L10: médio | M10: confirmada | O10: 203 | P10: 186194.49 | Q10: 186194.49 | R10: 0.041950844
A11: 9.1.05.000 | B11: SISTEMAS DE GESTÃO E OPERAÇãO | C11: TECNOLOGIA E SISTEMAS | D11: sim | E11: confirmada | G11: Tecnologia e Sistemas | H11: Sistemas e informática | I11: fixa | J11: contratual | K11: despesa | L11: médio | M11: sugerida | O11: 138 | P11: 175058.93 | Q11: 174758.93 | R11: 0.039441929
A12: 8.1.02.000 | B12: SALÁRIOS | C12: REMUNERAÇãO FIXA | D12: sim | E12: confirmada | G12: Pessoas | H12: CLT | I12: fixa | J12: contratual | K12: despesa | L12: médio | M12: sugerida | O12: 42 | P12: 131038.27 | Q12: 144306.91 | R12: 0.029523785
A13: 8.3.02.000 | B13: INSS | C13: ENCARGOS SOCIAIS | D13: sim | E13: confirmada | G13: Pessoas | H13: Encargos | I13: fixa | J13: obrigação legal | K13: despesa | L13: baixo | M13: sugerida | O13: 69 | P13: 130481.44 | Q13: 130481.44 | R13: 0.029398327
A14: 4.1.01.000 | B14: COMISSÕES PARCEIROS | C14: COMISSÕES SOBRE VENDAS | D14: sim | E14: confirmada | G14: Comissões | H14: Comissões | I14: variável | J14: decisão interna | K14: despesa | L14: médio | M14: confirmada | O14: 168 | P14: 116219.95 | Q14: 102231.71 | R14: 0.02618512
A15: 8.3.03.000 | B15: IRRF | C15: ENCARGOS SOCIAIS | D15: sim | E15: confirmada | G15: Pessoas | H15: Encargos | I15: fixa | J15: obrigação legal | K15: despesa | L15: baixo | M15: sugerida | O15: 20 | P15: 99529.22 | Q15: 99529.22 | R15: 0.022424588
A16: 8.2.01.000 | B16: BÔNUS | C16: REMUNERAÇãO VARIÁVEL | D16: sim | E16: confirmada | G16: Pessoas | H16: Bônus | I16: variável | J16: decisão interna | K16: despesa | L16: médio | M16: sugerida | O16: 40 | P16: 86908.01 | Q16: 90908.01 | R16: 0.019580947
A17: 5.15.05.000 | B17: PATROCÍNIOS | C17: PROPAGANDA E MARKETING | D17: sim | E17: confirmada | G17: Marketing e Desenvolvimento de Negócios | H17: Marketing | I17: variável | J17: decisão interna | K17: despesa | L17: alto | M17: sugerida | O17: 10 | P17: 75626.66 | Q17: 75626.66 | R17: 0.017039184
A18: 8.5.04.000 | B18: EVENTOS | C18: TREINAMENTO/DESENVOLVIMENTO/CULTURA | D18: sim | E18: confirmada | G18: Pessoas | H18: Treinamento | I18: variável | J18: decisão interna | K18: despesa | L18: alto | M18: sugerida | O18: 50 | P18: 63534.2 | Q18: 53534.2 | R18: 0.014314673
A19: 7.1.02.000 | B19: DIVIDENDOS PARCELAS FIXAS | C19: DISTRIBUIÇãO DE LUCROS | D19: não | E19: confirmada | F19: Remuneração de sócios de capital | G19: Remuneração de sócios de capital | H19: Remuneração de sócios de capital | I19: — | J19: — | K19: exclusão | L19: não avaliado | M19: confirmada | N19: abaixo_do_resultado_operacional | O19: 15 | P19: 44000 | Q19: 44000 | R19: 0
A20: 8.4.03.000 | B20: ASSISTÊNCIA MÉDICA E ODONTOLÓGICA | C20: BENEFÍCIOS | D20: sim | E20: confirmada | G20: Pessoas | H20: Benefícios | I20: fixa | J20: contratual | K20: despesa | L20: médio | M20: sugerida | O20: 27 | P20: 37079.71 | Q20: 37079.71 | R20: 0.0083543027
A21: 8.7.04.000 | B21: SALDO REMUNERAÇãO ASSOCIADOS | C21: DESLIGAMENTOS | D21: sim | E21: confirmada | G21: Pessoas | H21: Desligamentos | I21: variável | J21: obrigação legal | K21: despesa | L21: baixo | M21: sugerida | O21: 12 | P21: 29808.02 | Q21: 29808.02 | R21: 0.0067159431
A22: 9.1.03.000 | B22: MARKETING E COMERCIAL | C22: TECNOLOGIA E SISTEMAS | D22: sim | E22: confirmada | G22: Marketing e Desenvolvimento de Negócios | H22: Marketing | I22: variável | J22: decisão interna | K22: despesa | L22: alto | M22: sugerida | O22: 22 | P22: 29746.04 | Q22: 29746.04 | R22: 0.0067019786
A23: 8.4.01.000 | B23: VALE REFEIÇãO/VALE ALIMENTAÇãO | C23: BENEFÍCIOS | D23: sim | E23: confirmada | G23: Pessoas | H23: Benefícios | I23: fixa | J23: contratual | K23: despesa | L23: médio | M23: sugerida | O23: 27 | P23: 29502 | Q23: 29502 | R23: 0.0066469947
A24: 5.14.03.000 | B24: IMPOSTOS E TAXAS | C24: IMPOSTOS, TAXAS E SEGUROS | D24: sim | E24: confirmada | G24: Ocupação/Facilities | H24: Taxas e seguros do escritório | I24: fixa | J24: obrigação legal | K24: despesa | L24: baixo | M24: sugerida | N24: revisar_se_e_tributo_sobre_faturamento | O24: 35 | P24: 28496.41 | Q24: 26994.69 | R24: 0.0064204287
A25: 5.8.19.000 | B25: HONORÁRIOS CONTÁBEIS | C25: DESPESAS COM SERVIÇOS DE TERCEIROS | D25: sim | E25: confirmada | G25: Serviços Terceirizados | H25: Serviços de terceiros | I25: semivariável | J25: contratual | K25: despesa | L25: alto | M25: sugerida | O25: 13 | P25: 27753.2 | Q25: 27753.2 | R25: 0.0062529786
A26: 5.16.06.000 | B26: OUTRAS DESPESAS REEMBOLSÁVEIS | C26: OUTRAS DESPESAS | D26: não | E26: confirmada | F26: Despesas reembolsáveis de clientes | G26: Despesas reembolsáveis de clientes | H26: Despesas reembolsáveis de clientes | I26: — | J26: — | K26: exclusão | L26: não avaliado | M26: confirmada | N26: departamento_conta_corrente_clientes | O26: 70 | P26: 26902.35 | Q26: 26902.35 | R26: 0
A27: 8.4.06.000 | B27: ESTACIONAMENTO | C27: BENEFÍCIOS | D27: sim | E27: confirmada | G27: Pessoas | H27: Benefícios | I27: fixa | J27: contratual | K27: despesa | L27: médio | M27: sugerida | O27: 45 | P27: 26400 | Q27: 24359.99 | R27: 0.0059480937
A28: 5.8.02.000 | B28: SERVIÇOS DE INFORMÁTICA | C28: DESPESAS COM SERVIÇOS DE TERCEIROS | D28: sim | E28: confirmada | G28: Tecnologia e Sistemas | H28: Sistemas e informática | I28: fixa | J28: contratual | K28: despesa | L28: médio | M28: sugerida | O28: 13 | P28: 25368.56 | Q28: 25368.56 | R28: 0.0057157035
A29: 1.1.02.000 | B29: ADIANTAMENTOS | C29: SAÍDAS - EMPRÉSTIMOS APL. E DEVOLUÇÕES | D29: não | E29: confirmada | F29: Despesas reembolsáveis de clientes | G29: Despesas reembolsáveis de clientes | H29: Despesas reembolsáveis de clientes | I29: — | J29: — | K29: exclusão | L29: não avaliado | M29: confirmada | N29: departamento_conta_corrente_clientes | O29: 9 | P29: 25024.67 | Q29: 25024.67 | R29: 0
A30: 8.7.06.000 | B30: SALDO DE FÉRIAS ASSOCIADOS | C30: DESLIGAMENTOS | D30: sim | E30: confirmada | G30: Pessoas | H30: 13º e férias | I30: semivariável | J30: obrigação legal | K30: despesa | L30: baixo | M30: sugerida | O30: 3 | P30: 22135.82 | Q30: 22135.82 | R30: 0.0049873459
A31: 5.8.07.000 | B31: GRÁFICA | C31: DESPESAS COM SERVIÇOS DE TERCEIROS | D31: sim | E31: confirmada | G31: Serviços Terceirizados | H31: Serviços de terceiros | I31: semivariável | J31: contratual | K31: despesa | L31: alto | M31: sugerida | O31: 15 | P31: 21084.99 | Q31: 17155 | R31: 0.004750587
A32: 8.4.05.000 | B32: AUXÍLIO EDUCACIONAL | C32: BENEFÍCIOS | D32: sim | E32: confirmada | G32: Pessoas | H32: Benefícios | I32: fixa | J32: contratual | K32: despesa | L32: médio | M32: sugerida | O32: 28 | P32: 21048.28 | Q32: 21048.28 | R32: 0.004742316
A33: 5.15.06.000 | B33: SERVIÇOS FOTOGRÁFICOS / FILMAGEM | C33: PROPAGANDA E MARKETING | D33: sim | E33: confirmada | G33: Marketing e Desenvolvimento de Negócios | H33: Marketing | I33: variável | J33: decisão interna | K33: despesa | L33: alto | M33: sugerida | O33: 8 | P33: 20000 | Q33: 20000 | R33: 0.0045061316
A34: 8.5.05.000 | B34: DATAS COMEMORATIVAS | C34: TREINAMENTO/DESENVOLVIMENTO/CULTURA | D34: sim | E34: confirmada | G34: Pessoas | H34: Treinamento | I34: variável | J34: decisão interna | K34: despesa | L34: alto | M34: sugerida | O34: 25 | P34: 19584.27 | Q34: 19584.27 | R34: 0.0044124649
A35: 5.9.03.000 | B35: MANUTENÇãO PREDIAL | C35: DESPESAS DE MANUTENÇãO | D35: sim | E35: confirmada | G35: Ocupação/Facilities | H35: Manutenção | I35: semivariável | J35: decisão interna | K35: despesa | L35: médio | M35: sugerida | O35: 41 | P35: 19189.04 | Q35: 19039.04 | R35: 0.004323417
A36: 5.6.02.000 | B36: CUSTAS JUDICIAIS | C36: ASSOCIAÇÕES E CUSTAS JUDICIAIS | D36: sim | E36: confirmada | G36: Despesas Processuais | H36: Custas e despesas processuais | I36: variável | J36: obrigação legal | K36: despesa | L36: baixo | M36: confirmada | N36: processual_possivelmente_reembolsavel | O36: 51 | P36: 19024.49 | Q36: 19024.49 | R36: 0.0042863428
A37: 1.1.08.000 | B37: DEVOLUÇãO DE ADIANTAMENTOS DE CLIENTES | C37: SAÍDAS - EMPRÉSTIMOS APL. E DEVOLUÇÕES | D37: não | E37: confirmada | F37: Despesas reembolsáveis de clientes | G37: Despesas reembolsáveis de clientes | H37: Despesas reembolsáveis de clientes | I37: — | J37: — | K37: exclusão | L37: não avaliado | M37: confirmada | N37: departamento_conta_corrente_clientes | O37: 2 | P37: 18024.88 | Q37: 18024.88 | R37: 0
A38: 5.16.09.000 | B38: PERMUTAS | C38: OUTRAS DESPESAS | D38: sim | E38: confirmada | G38: Administrativo Geral | H38: PERMUTAS | I38: semivariável | J38: decisão interna | K38: despesa | L38: médio | M38: sugerida | O38: 1 | P38: 18000 | Q38: 18000 | R38: 0.0040555185
A39: 5.10.01.000 | B39: MATERIAL DE HIGIENE E LIMPEZA | C39: MATERIAL DE CONSUMO, LIMPEZA E SEGURANÇA | D39: sim | E39: confirmada | G39: Ocupação/Facilities | H39: Copa, limpeza e consumo | I39: semivariável | J39: decisão interna | K39: despesa | L39: médio | M39: sugerida | O39: 58 | P39: 15368.78 | Q39: 13767.41 | R39: 0.0034626873
A40: 8.3.01.000 | B40: FGTS | C40: ENCARGOS SOCIAIS | D40: sim | E40: confirmada | G40: Pessoas | H40: Encargos | I40: fixa | J40: obrigação legal | K40: despesa | L40: baixo | M40: sugerida | O40: 27 | P40: 14872.08 | Q40: 14872.08 | R40: 0.0033507775
A41: 5.9.07.000 | B41: PAISAGISMO | C41: DESPESAS DE MANUTENÇãO | D41: sim | E41: confirmada | G41: Ocupação/Facilities | H41: Manutenção | I41: semivariável | J41: decisão interna | K41: despesa | L41: médio | M41: sugerida | O41: 8 | P41: 13615.5 | Q41: 13615.5 | R41: 0.0030676617
A42: 5.12.02.000 | B42: ENERGIA ELÉTRICA | C42: DESPESAS DE INFRAESTRUTURA | D42: sim | E42: confirmada | G42: Ocupação/Facilities | H42: Infraestrutura | I42: fixa | J42: contratual | K42: despesa | L42: baixo | M42: sugerida | O42: 8 | P42: 13531.49 | Q42: 13531.49 | R42: 0.0030487337
A43: 5.8.31.000 | B43: DIARISTA | C43: DESPESAS COM SERVIÇOS DE TERCEIROS | D43: sim | E43: confirmada | G43: Ocupação/Facilities | H43: Copa, limpeza e consumo | I43: semivariável | J43: decisão interna | K43: despesa | L43: médio | M43: sugerida | O43: 43 | P43: 12610 | Q43: 12610 | R43: 0.002841116
A44: 5.6.02.000 | B44: CUSTAS JUDICIAIS | C44: ASSOCIAÇÕES E CUSTAS JUDICIAIS | D44: não | E44: confirmada | F44: Despesas reembolsáveis de clientes | G44: Despesas reembolsáveis de clientes | H44: Despesas reembolsáveis de clientes | I44: — | J44: — | K44: exclusão | L44: não avaliado | M44: confirmada | N44: departamento_conta_corrente_clientes | O44: 77 | P44: 12167.08 | Q44: 12167.08 | R44: 0
A45: 8.4.02.000 | B45: VALE TRANSPORTE | C45: BENEFÍCIOS | D45: sim | E45: confirmada | G45: Pessoas | H45: Benefícios | I45: fixa | J45: contratual | K45: despesa | L45: médio | M45: sugerida | O45: 24 | P45: 12000 | Q45: 12000 | R45: 0.002703679
A46: 5.12.03.000 | B46: INTERNET | C46: DESPESAS DE INFRAESTRUTURA | D46: sim | E46: confirmada | G46: Ocupação/Facilities | H46: Infraestrutura | I46: fixa | J46: contratual | K46: despesa | L46: baixo | M46: sugerida | O46: 20 | P46: 11975.46 | Q46: 12581.77 | R46: 0.0026981499
A47: 5.16.04.000 | B47: OUTRAS DESPESAS DE OPERAÇãO | C47: OUTRAS DESPESAS | D47: sim | E47: confirmada | G47: Administrativo Geral | H47: OUTRAS DESPESAS DE OPERACAO | I47: semivariável | J47: decisão interna | K47: despesa | L47: médio | M47: sugerida | O47: 52 | P47: 11589.38 | Q47: 11589.38 | R47: 0.0026111636
A48: 5.14.05.000 | B48: SEGUROS | C48: IMPOSTOS, TAXAS E SEGUROS | D48: sim | E48: confirmada | G48: Ocupação/Facilities | H48: Taxas e seguros do escritório | I48: fixa | J48: obrigação legal | K48: despesa | L48: baixo | M48: sugerida | O48: 8 | P48: 11491.2 | Q48: 11491.2 | R48: 0.002589043
A49: 9.1.01.000 | B49: AUTOMAÇãO, DADOS E IA | C49: TECNOLOGIA E SISTEMAS | D49: sim | E49: confirmada | G49: Tecnologia e Sistemas | H49: Sistemas e informática | I49: fixa | J49: contratual | K49: despesa | L49: médio | M49: sugerida | O49: 52 | P49: 11263.41 | Q49: 11263.41 | R49: 0.0025377204
A50: 5.11.02.000 | B50: COPA E COZINHA | C50: DESPESAS DE COPA E COZINHA | D50: sim | E50: confirmada | G50: Ocupação/Facilities | H50: Copa, limpeza e consumo | I50: semivariável | J50: decisão interna | K50: despesa | L50: médio | M50: sugerida | O50: 59 | P50: 11095.5 | Q50: 10479.83 | R50: 0.0024998892
A51: 5.12.01.000 | B51: ÁGUA E ESGOTO | C51: DESPESAS DE INFRAESTRUTURA | D51: sim | E51: confirmada | G51: Ocupação/Facilities | H51: Infraestrutura | I51: fixa | J51: contratual | K51: despesa | L51: baixo | M51: sugerida | O51: 8 | P51: 9619.03 | Q51: 9619.03 | R51: 0.0021672308
A52: 10.1.03.000 | B52: EQUIPAMENTOS DE INFORMÁTICA | C52: INVESTIMENTOS | D52: não | E52: confirmada | F52: Investimento / CAPEX | G52: Investimento / CAPEX | H52: Investimento / CAPEX | I52: — | J52: — | K52: investimento | L52: não avaliado | M52: confirmada | O52: 16 | P52: 8971.18 | Q52: 8751.3 | R52: 0
A53: 5.18.01.000 | B53: DESPESAS BANCÁRIAS | C53: DESPESAS FINANCEIRAS | D53: sim | E53: confirmada | G53: Administrativo e Financeiro | H53: Custos bancários e de cobrança | I53: semivariável | J53: contratual | K53: despesa | L53: baixo | M53: confirmada | O53: 67 | P53: 7651.85 | Q53: 7571.95 | R53: 0.0017240122
A54: 1.1.08.000 | B54: DEVOLUÇãO DE ADIANTAMENTOS DE CLIENTES | C54: SAÍDAS - EMPRÉSTIMOS APL. E DEVOLUÇÕES | D54: não | E54: sugerida | F54: Adiantamento ou transferência (não é despesa operacional) | G54: Fora do OPEX | H54: Adiantamento ou transferência (não é despesa operacional) | I54: — | J54: — | K54: exclusão | L54: não avaliado | M54: sugerida | O54: 1 | P54: 7600 | Q54: 7600 | R54: 0
A55: 8.8.02.000 | B55: ONBOARDING | C55: OUTROS CUSTOS COM PESSOAS | D55: sim | E55: confirmada | G55: Pessoas | H55: Recrutamento e reconhecimento | I55: variável | J55: decisão interna | K55: despesa | L55: alto | M55: sugerida | O55: 8 | P55: 6933.49 | Q55: 6933.49 | R55: 0.0015621609
A56: 5.9.05.000 | B56: MANUTENÇãO AR CONDICIONADO | C56: DESPESAS DE MANUTENÇãO | D56: sim | E56: confirmada | G56: Ocupação/Facilities | H56: Manutenção | I56: semivariável | J56: decisão interna | K56: despesa | L56: médio | M56: sugerida | O56: 9 | P56: 6400 | Q56: 6400 | R56: 0.0014419621
A57: 8.5.03.000 | B57: SAÚDE E BEM-ESTAR | C57: TREINAMENTO/DESENVOLVIMENTO/CULTURA | D57: sim | E57: confirmada | G57: Pessoas | H57: Treinamento | I57: variável | J57: decisão interna | K57: despesa | L57: alto | M57: sugerida | O57: 8 | P57: 5632 | Q57: 5632 | R57: 0.0012689267
A58: 5.9.04.000 | B58: MANUTENÇãO EQUIPAMENTOS DE INFORMÁTICA | C58: DESPESAS DE MANUTENÇãO | D58: sim | E58: confirmada | G58: Ocupação/Facilities | H58: Manutenção | I58: semivariável | J58: decisão interna | K58: despesa | L58: médio | M58: sugerida | O58: 16 | P58: 5322.47 | Q58: 5322.47 | R58: 0.0011991875
A59: 5.7.05.000 | B59: PASSAGEM AÉREA | C59: DESPESAS DE VIAGEM E LOCOMOÇãO | D59: sim | E59: confirmada | G59: Viagens e Deslocamentos | H59: Viagens | I59: variável | J59: decisão interna | K59: despesa | L59: alto | M59: sugerida | O59: 6 | P59: 4996.2 | Q59: 4996.2 | R59: 0.0011256767
A60: 8.2.04.000 | B60: FÉRIAS | C60: REMUNERAÇãO VARIÁVEL | D60: sim | E60: confirmada | G60: Pessoas | H60: 13º e férias | I60: semivariável | J60: obrigação legal | K60: despesa | L60: baixo | M60: sugerida | O60: 3 | P60: 4622.97 | Q60: 4622.97 | R60: 0.0010415856
A61: 5.11.01.000 | B61: UTENSÍLIOS E ACESSÓRIOS | C61: DESPESAS DE COPA E COZINHA | D61: sim | E61: confirmada | G61: Ocupação/Facilities | H61: Copa, limpeza e consumo | I61: semivariável | J61: decisão interna | K61: despesa | L61: médio | M61: sugerida | O61: 24 | P61: 4521.09 | Q61: 4521.09 | R61: 0.0010186313
A62: 8.3.04.000 | B62: CONSIGNADO | C62: ENCARGOS SOCIAIS | D62: sim | E62: confirmada | G62: Pessoas | H62: Encargos | I62: fixa | J62: obrigação legal | K62: despesa | L62: baixo | M62: sugerida | O62: 8 | P62: 4383.38 | Q62: 4383.38 | R62: 0.00098760436
A63: 8.7.05.000 | B63: INDENIZAÇãO ASSOCIADOS | C63: DESLIGAMENTOS | D63: sim | E63: confirmada | G63: Pessoas | H63: Desligamentos | I63: variável | J63: obrigação legal | K63: despesa | L63: baixo | M63: sugerida | O63: 1 | P63: 3750 | Q63: 3750 | R63: 0.00084489968
A64: 8.8.03.000 | B64: RECONHECIMENTO | C64: OUTROS CUSTOS COM PESSOAS | D64: sim | E64: confirmada | G64: Pessoas | H64: Recrutamento e reconhecimento | I64: variável | J64: decisão interna | K64: despesa | L64: alto | M64: sugerida | O64: 36 | P64: 3555.57 | Q64: 3555.57 | R64: 0.00080109332
A65: 5.15.04.000 | B65: FEIRAS E EVENTOS | C65: PROPAGANDA E MARKETING | D65: sim | E65: confirmada | G65: Marketing e Desenvolvimento de Negócios | H65: Marketing | I65: variável | J65: decisão interna | K65: despesa | L65: alto | M65: sugerida | O65: 5 | P65: 2811.42 | Q65: 2811.42 | R65: 0.00063343143
A66: 5.7.04.000 | B66: HOSPEDAGEM | C66: DESPESAS DE VIAGEM E LOCOMOÇãO | D66: sim | E66: confirmada | G66: Viagens e Deslocamentos | H66: Viagens | I66: variável | J66: decisão interna | K66: despesa | L66: alto | M66: sugerida | O66: 2 | P66: 2530.5 | Q66: 2530.5 | R66: 0.0005701383
... A70: 9.1.04.000 | B70: SEGURANÇA DA INFORMAÇãO | C70: TECNOLOGIA E SISTEMAS | D70: sim | E70: confirmada | G70: Tecnologia e Sistemas | H70: Sistemas e informática | I70: fixa | J70: contratual | K70: despesa | L70: médio | M70: sugerida | O70: 1 | P70: 2077.08 | Q70: 2077.08 | R70: 0.00046797979
A71: 3.4.01.000 | B71: DEVOLUÇãO HONORÁRIOS / DESPESAS | C71: DEDUÇÕES DA RECEITA | D71: não | E71: confirmada | F71: Dedução da receita | G71: Deduções da receita | H71: Dedução da receita | I71: — | J71: — | K71: exclusão | L71: não avaliado | M71: confirmada | O71: 1 | P71: 2000 | Q71: 2000 | R71: 0
A72: 5.9.08.000 | B72: MANUTENÇãO PURIFICADORES DE ÁGUA | C72: DESPESAS DE MANUTENÇãO | D72: sim | E72: confirmada | G72: Ocupação/Facilities | H72: Manutenção | I72: semivariável | J72: decisão interna | K72: despesa | L72: médio | M72: sugerida | O72: 8 | P72: 1877.12 | Q72: 1877.12 | R72: 0.00042292749
A73: 5.12.06.000 | B73: ALARME E MONITORAMENTO | C73: DESPESAS DE INFRAESTRUTURA | D73: sim | E73: confirmada | G73: Ocupação/Facilities | H73: Infraestrutura | I73: fixa | J73: contratual | K73: despesa | L73: baixo | M73: sugerida | O73: 8 | P73: 1741.92 | Q73: 1741.92 | R73: 0.00039246604
A74: 5.12.07.000 | B74: TELEFONIA MÓVEL | C74: DESPESAS DE INFRAESTRUTURA | D74: sim | E74: confirmada | G74: Ocupação/Facilities | H74: Infraestrutura | I74: fixa | J74: contratual | K74: despesa | L74: baixo | M74: sugerida | O74: 24 | P74: 1625.24 | Q74: 1625.24 | R74: 0.00036617727
A75: 5.10.03.000 | B75: MATERIAL DE INFORMÁTICA | C75: MATERIAL DE CONSUMO, LIMPEZA E SEGURANÇA | D75: sim | E75: confirmada | G75: Tecnologia e Sistemas | H75: Sistemas e informática | I75: fixa | J75: contratual | K75: despesa | L75: médio | M75: sugerida | O75: 10 | P75: 1405.1 | Q75: 1405.1 | R75: 0.00031657828
A76: 5.18.02.000 | B76: IOF | C76: DESPESAS FINANCEIRAS | D76: sim | E76: confirmada | G76: Administrativo e Financeiro | H76: Custos bancários e de cobrança | I76: semivariável | J76: contratual | K76: despesa | L76: baixo | M76: confirmada | O76: 41 | P76: 1320.76 | Q76: 1320.76 | R76: 0.00029757592
A77: 5.12.04.000 | B77: TELEFONIA FIXA | C77: DESPESAS DE INFRAESTRUTURA | D77: sim | E77: confirmada | G77: Ocupação/Facilities | H77: Infraestrutura | I77: fixa | J77: contratual | K77: despesa | L77: baixo | M77: sugerida | O77: 10 | P77: 1222.16 | Q77: 1393.07 | R77: 0.00027536069
A78: 8.5.01.000 | B78: CURSOS/WORKSHOPS/PALESTRAS | C78: TREINAMENTO/DESENVOLVIMENTO/CULTURA | D78: sim | E78: confirmada | G78: Pessoas | H78: Treinamento | I78: variável | J78: decisão interna | K78: despesa | L78: alto | M78: sugerida | O78: 20 | P78: 1094.5 | Q78: 1094.5 | R78: 0.00024659805
A79: 5.8.03.000 | B79: MOTOBOY | C79: DESPESAS COM SERVIÇOS DE TERCEIROS | D79: sim | E79: confirmada | G79: Serviços Terceirizados | H79: Serviços de terceiros | I79: semivariável | J79: contratual | K79: despesa | L79: alto | M79: sugerida | O79: 22 | P79: 1060 | Q79: 1060 | R79: 0.00023882498
A80: 5.8.05.000 | B80: CORREIOS | C80: DESPESAS COM SERVIÇOS DE TERCEIROS | D80: sim | E80: confirmada | G80: Serviços Terceirizados | H80: Serviços de terceiros | I80: semivariável | J80: contratual | K80: despesa | L80: alto | M80: sugerida | O80: 9 | P80: 961.15 | Q80: 961.15 | R80: 0.00021655342
A81: 5.18.04.000 | B81: TARIFAS DE CARTÕES | C81: DESPESAS FINANCEIRAS | D81: sim | E81: confirmada | G81: Administrativo e Financeiro | H81: Custos bancários e de cobrança | I81: semivariável | J81: contratual | K81: despesa | L81: baixo | M81: confirmada | O81: 9 | P81: 824.76 | Q81: 824.76 | R81: 0.00018582386
A82: 5.18.05.000 | B82: OUTRAS DESPESAS FINANCEIRAS | C82: DESPESAS FINANCEIRAS | D82: sim | E82: confirmada | G82: Administrativo e Financeiro | H82: Custos bancários e de cobrança | I82: semivariável | J82: contratual | K82: despesa | L82: baixo | M82: confirmada | O82: 99 | P82: 587.48 | Q82: 587.48 | R82: 0.00013236311
A83: 10.1.01.000 | B83: MÓVEIS E EQUIPAMENTOS | C83: INVESTIMENTOS | D83: não | E83: confirmada | F83: Investimento / CAPEX | G83: Investimento / CAPEX | H83: Investimento / CAPEX | I83: — | J83: — | K83: investimento | L83: não avaliado | M83: confirmada | O83: 2 | P83: 567.43 | Q83: 567.43 | R83: 0
A84: 5.16.03.000 | B84: CARTÃO DE CRÉDITO | C84: OUTRAS DESPESAS | D84: sim | E84: confirmada | G84: Administrativo Geral | H84: CARTAO DE CREDITO | I84: semivariável | J84: decisão interna | K84: despesa | L84: médio | M84: sugerida | O84: 18 | P84: 479.75 | Q84: 479.75 | R84: 0.00010809083
A85: 8.4.04.000 | B85: SEGURO DE VIDA | C85: BENEFÍCIOS | D85: sim | E85: confirmada | G85: Pessoas | H85: Benefícios | I85: fixa | J85: contratual | K85: despesa | L85: médio | M85: sugerida | O85: 6 | P85: 463.92 | Q85: 467.58 | R85: 0.00010452423
A86: 9.1.02.000 | B86: DOMÍNIOS E HOSPEDAGEM | C86: TECNOLOGIA E SISTEMAS | D86: sim | E86: confirmada | G86: Tecnologia e Sistemas | H86: Sistemas e informática | I86: fixa | J86: contratual | K86: despesa | L86: médio | M86: sugerida | O86: 8 | P86: 369.81 | Q86: 369.81 | R86: 8.3320627e-05
A87: 5.8.13.000 | B87: CERTIFICADO DIGITAL | C87: DESPESAS COM SERVIÇOS DE TERCEIROS | D87: sim | E87: confirmada | G87: Serviços Terceirizados | H87: Serviços de terceiros | I87: semivariável | J87: contratual | K87: despesa | L87: alto | M87: sugerida | O87: 2 | P87: 278 | Q87: 278 | R87: 6.2635229e-05
A88: 3.3.01.000 | B88: IMPOSTOS SOBRE SERVIÇOS - ISS | C88: IMPOSTOS SOBRE SERVIÇOS | D88: não | E88: confirmada | F88: Deduções / tributos sobre faturamento | G88: Deduções / tributos sobre faturamento | H88: Deduções / tributos sobre faturamento | I88: — | J88: — | K88: exclusão | L88: não avaliado | M88: confirmada | N88: composicao_pendente | O88: 8 | P88: 209.13 | Q88: 209.13 | R88: 0
A89: 10.1.11.000 | B89: EQUIPAMENTOS DE COMUNICAÇãO | C89: INVESTIMENTOS | D89: não | E89: confirmada | F89: Investimento / CAPEX | G89: Investimento / CAPEX | H89: Investimento / CAPEX | I89: — | J89: — | K89: investimento | L89: não avaliado | M89: confirmada | O89: 1 | P89: 189 | Q89: 189 | R89: 0
A90: 8.6.02.000 | B90: MEDICINA OCUPACIONAL | C90: RECRUTAMENTO E SELEÇãO | D90: sim | E90: confirmada | G90: Pessoas | H90: Recrutamento e reconhecimento | I90: variável | J90: decisão interna | K90: despesa | L90: alto | M90: sugerida | O90: 1 | P90: 55 | Q90: 55 | R90: 1.2391862e-05

Sheet Lancamentos
A1: ci_item | B1: nro_titulo | C1: descricao | D1: fornecedor | E1: departamento | F1: grupo_conta | G1: plano_contas | H1: conta_numero | I1: mes_competencia | J1: mes_pagamento | K1: valor_competencia | L1: valor_caixa | M1: dentro_opex_regra | N1: status_perimetro | O1: motivo_perimetro | P1: flag | Q1: grupo_gerencial | R1: subgrupo | S1: natureza | T1: controlabilidade | U1: tipo | V1: potencial_eficiencia | W1: status_classificacao | X1: recorrente_sugerido | Y1: motivo_recorrencia | Z1: status_recorrencia | AA1: override_dentro_opex | AB1: override_recorrente | AC1: dentro_opex_final | AD1: recorrente_final | AE1: material
A2: 15960 | C2: DEVOLUÇÃO ADIANTAMENTO | D2: Nigro Aluminio Ltda | E2: Conta Corrente Clientes | F2: SAÍDAS - EMPRÉSTIMOS APL. E DEVOLUÇÕES | G2: ADIANTAMENTOS | H2: 1.1.02.000 | I2: 2026-03 | J2: 2026-03 | K2: 2.55 | L2: 2.55 | M2: não | N2: confirmada | O2: Despesas reembolsáveis de clientes | P2: departamento_conta_corrente_clientes | Q2: Despesas reembolsáveis de clientes | R2: Despesas reembolsáveis de clientes | S2: — | T2: — | U2: exclusão | V2: não avaliado | W2: confirmada | X2: sim | Z2: sem sinal | AC2: =IF(AA2="",M2,AA2) -> não | AD2: =IF(AB2="",X2,AB2) -> sim | AE2: =IF(OR(Configuracao!B9="",Configuracao!B10=""),"aguardando limiar",IF(AND(K2>=Configuracao!B9,K2/MAX(Reconciliacao!C2,1)>=Configuracao!B10/100),"sim","não")) -> aguardando limiar
A3: 12930 | C3: CUSTAS NIGRO | D3: Caio Augusto de Alcantara Cesar Silva | E3: Conta Corrente Clientes | F3: SAÍDAS - EMPRÉSTIMOS APL. E DEVOLUÇÕES | G3: ADIANTAMENTOS | H3: 1.1.02.000 | I3: 2026-02 | J3: 2026-02 | K3: 40 | L3: 40 | M3: não | N3: confirmada | O3: Despesas reembolsáveis de clientes | P3: departamento_conta_corrente_clientes | Q3: Despesas reembolsáveis de clientes | R3: Despesas reembolsáveis de clientes | S3: — | T3: — | U3: exclusão | V3: não avaliado | W3: confirmada | X3: sim | Z3: sem sinal | AC3: =IF(AA3="",M3,AA3) -> não | AD3: =IF(AB3="",X3,AB3) -> sim | AE3: =IF(OR(Configuracao!B9="",Configuracao!B10=""),"aguardando limiar",IF(AND(K3>=Configuracao!B9,K3/MAX(Reconciliacao!C2,1)>=Configuracao!B10/100),"sim","não")) -> aguardando limiar
A4: 15959 | C4: DEVOLUÇÃO ADIANTAMENTO | D4: Carvalho Assessoria Empreendimentos Imobiliarios Ltda | E4: Conta Corrente Clientes | F4: SAÍDAS - EMPRÉSTIMOS APL. E DEVOLUÇÕES | G4: ADIANTAMENTOS | H4: 1.1.02.000 | I4: 2026-03 | J4: 2026-03 | K4: 44 | L4: 44 | M4: não | N4: confirmada | O4: Despesas reembolsáveis de clientes | P4: departamento_conta_corrente_clientes | Q4: Despesas reembolsáveis de clientes | R4: Despesas reembolsáveis de clientes | S4: — | T4: — | U4: exclusão | V4: não avaliado | W4: confirmada | X4: sim | Z4: sem sinal | AC4: =IF(AA4="",M4,AA4) -> não | AD4: =IF(AB4="",X4,AB4) -> sim | AE4: =IF(OR(Configuracao!B9="",Configuracao!B10=""),"aguardando limiar",IF(AND(K4>=Configuracao!B9,K4/MAX(Reconciliacao!C2,1)>=Configuracao!B10/100),"sim","não")) -> aguardando limiar
A5: 13040 | C5: CUSTAS CARVALHO | D5: Caio Augusto de Alcantara Cesar Silva | E5: Conta Corrente Clientes | F5: SAÍDAS - EMPRÉSTIMOS APL. E DEVOLUÇÕES | G5: ADIANTAMENTOS | H5: 1.1.02.000 | I5: 2026-02 | J5: 2026-02 | K5: 56.75 | L5: 56.75 | M5: não | N5: confirmada | O5: Despesas reembolsáveis de clientes | P5: departamento_conta_corrente_clientes | Q5: Despesas reembolsáveis de clientes | R5: Despesas reembolsáveis de clientes | S5: — | T5: — | U5: exclusão | V5: não avaliado | W5: confirmada | X5: sim | Z5: sem sinal | AC5: =IF(AA5="",M5,AA5) -> não | AD5: =IF(AB5="",X5,AB5) -> sim | AE5: =IF(OR(Configuracao!B9="",Configuracao!B10=""),"aguardando limiar",IF(AND(K5>=Configuracao!B9,K5/MAX(Reconciliacao!C2,1)>=Configuracao!B10/100),"sim","não")) -> aguardando limiar
A6: 13360 | C6: DEVOLUÇÃO ADIANTAMENTO CUSTAS | D6: Spel Embalagens Ltda | E6: Conta Corrente Clientes | F6: SAÍDAS - EMPRÉSTIMOS APL. E DEVOLUÇÕES | G6: ADIANTAMENTOS | H6: 1.1.02.000 | I6: 2026-03 | J6: 2026-03 | K6: 166 | L6: 166 | M6: não | N6: confirmada | O6: Despesas reembolsáveis de clientes | P6: departamento_conta_corrente_clientes | Q6: Despesas reembolsáveis de clientes | R6: Despesas reembolsáveis de clientes | S6: — | T6: — | U6: exclusão | V6: não avaliado | W6: confirmada | X6: sim | Z6: sem sinal | AC6: =IF(AA6="",M6,AA6) -> não | AD6: =IF(AB6="",X6,AB6) -> sim | AE6: =IF(OR(Configuracao!B9="",Configuracao!B10=""),"aguardando limiar",IF(AND(K6>=Configuracao!B9,K6/MAX(Reconciliacao!C2,1)>=Configuracao!B10/100),"sim","não")) -> aguardando limiar
A7: 12782 | C7: CUSTAS SUSTENTARE | D7: Fernanda Andrade Camolesi | E7: Conta Corrente Clientes | F7: SAÍDAS - EMPRÉSTIMOS APL. E DEVOLUÇÕES | G7: ADIANTAMENTOS | H7: 1.1.02.000 | I7: 2026-03 | J7: 2026-03 | K7: 250 | L7: 250 | M7: não | N7: confirmada | O7: Despesas reembolsáveis de clientes | P7: departamento_conta_corrente_clientes | Q7: Despesas reembolsáveis de clientes | R7: Despesas reembolsáveis de clientes | S7: — | T7: — | U7: exclusão | V7: não avaliado | W7: confirmada | X7: sim | Z7: sem sinal | AC7: =IF(AA7="",M7,AA7) -> não | AD7: =IF(AB7="",X7,AB7) -> sim | AE7: =IF(OR(Configuracao!B9="",Configuracao!B10=""),"aguardando limiar",IF(AND(K7>=Configuracao!B9,K7/MAX(Reconciliacao!C2,1)>=Configuracao!B10/100),"sim","não")) -> aguardando limiar
A8: 12899 | C8: CORREIOS SPEL | D8: Laura Puente Ferreira Gomes | E8: Conta Corrente Clientes | F8: SAÍDAS - EMPRÉSTIMOS APL. E DEVOLUÇÕES | G8: ADIANTAMENTOS | H8: 1.1.02.000 | I8: 2026-03 | J8: 2026-03 | K8: 2294.95 | L8: 2294.95 | M8: não | N8: confirmada | O8: Despesas reembolsáveis de clientes | P8: departamento_conta_corrente_clientes | Q8: Despesas reembolsáveis de clientes | R8: Despesas reembolsáveis de clientes | S8: — | T8: — | U8: exclusão | V8: não avaliado | W8: confirmada | X8: não | Y8: fornecedor sem outra ocorrência na conta em 12 meses; valor atípico (acima de 3x a mediana da conta em 12 meses, mediana 166) | Z8: sugerido | AC8: =IF(AA8="",M8,AA8) -> não | AD8: =IF(AB8="",X8,AB8) -> não | AE8: =IF(OR(Configuracao!B9="",Configuracao!B10=""),"aguardando limiar",IF(AND(K8>=Configuracao!B9,K8/MAX(Reconciliacao!C2,1)>=Configuracao!B10/100),"sim","não")) -> aguardando limiar
A9: 13049 | C9: IPVA 2026 (CARRO GUSTAVO QUE FICA COM A IRMÃ. ADIANTOU O VALOR INTEGRAL E PAGAMOS NO MESMO DIA) | D9: SECRETARIA DE ESTADO DA FAZENDA | E9: Conta Corrente Clientes | F9: SAÍDAS - EMPRÉSTIMOS APL. E DEVOLUÇÕES | G9: ADIANTAMENTOS | H9: 1.1.02.000 | I9: 2026-02 | J9: 2026-02 | K9: 2348.73 | L9: 2348.73 | M9: não | N9: confirmada | O9: Despesas reembolsáveis de clientes | P9: departamento_conta_corrente_clientes | Q9: Despesas reembolsáveis de clientes | R9: Despesas reembolsáveis de clientes | S9: — | T9: — | U9: exclusão | V9: não avaliado | W9: confirmada | X9: não | Y9: fornecedor sem outra ocorrência na conta em 12 meses; valor atípico (acima de 3x a mediana da conta em 12 meses, mediana 166) | Z9: sugerido | AC9: =IF(AA9="",M9,AA9) -> não | AD9: =IF(AB9="",X9,AB9) -> não | AE9: =IF(OR(Configuracao!B9="",Configuracao!B10=""),"aguardando limiar",IF(AND(K9>=Configuracao!B9,K9/MAX(Reconciliacao!C2,1)>=Configuracao!B10/100),"sim","não")) -> aguardando limiar
A10: 17980 | C10: VALOR REF. REMUNERAÇÃO PAGO INDEVIDAMENTE - VALOR DEVOLVIDO NO DIA SEGUINTE | D10: Michel Donizeti de Medeiros Malaquias | E10: Conta Corrente Clientes | F10: SAÍDAS - EMPRÉSTIMOS APL. E DEVOLUÇÕES | G10: ADIANTAMENTOS | H10: 1.1.02.000 | I10: 2026-07 | J10: 2026-07 | K10: 19821.69 | L10: 19821.69 | M10: não | N10: confirmada | O10: Despesas reembolsáveis de clientes | P10: departamento_conta_corrente_clientes | Q10: Despesas reembolsáveis de clientes | R10: Despesas reembolsáveis de clientes | S10: — | T10: — | U10: exclusão | V10: não avaliado | W10: confirmada | X10: não | Y10: fornecedor sem outra ocorrência na conta em 12 meses; valor atípico (acima de 3x a mediana da conta em 12 meses, mediana 166) | Z10: sugerido | AC10: =IF(AA10="",M10,AA10) -> não | AD10: =IF(AB10="",X10,AB10) -> não | AE10: =IF(OR(Configuracao!B9="",Configuracao!B10=""),"aguardando limiar",IF(AND(K10>=Configuracao!B9,K10/MAX(Reconciliacao!C2,1)>=Configuracao!B10/100),"sim","não")) -> aguardando limiar
A11: 17696 | C11: DEVOLUÇÃO VALOR PAGO INDEVIDAMENTE JUNTO COM ND | D11: Macan Logistica e Transportes Ltda | E11: Conta Corrente Clientes | F11: SAÍDAS - EMPRÉSTIMOS APL. E DEVOLUÇÕES | G11: DEVOLUÇãO DE ADIANTAMENTOS DE CLIENTES | H11: 1.1.08.000 | I11: 2026-06 | J11: 2026-06 | K11: 24.88 | L11: 24.88 | M11: não | N11: confirmada | O11: Despesas reembolsáveis de clientes | P11: departamento_conta_corrente_clientes | Q11: Despesas reembolsáveis de clientes | R11: Despesas reembolsáveis de clientes | S11: — | T11: — | U11: exclusão | V11: não avaliado | W11: confirmada | X11: sim | Z11: sem sinal | AC11: =IF(AA11="",M11,AA11) -> não | AD11: =IF(AB11="",X11,AB11) -> sim | AE11: =IF(OR(Configuracao!B9="",Configuracao!B10=""),"aguardando limiar",IF(AND(K11>=Configuracao!B9,K11/MAX(Reconciliacao!C2,1)>=Configuracao!B10/100),"sim","não")) -> aguardando limiar
A12: 12932 | C12: DEVOLUÇÃO HONORÁRIO PAGO INDEVIDAMENTE (DEZ/25 E JAN/26) | D12: Primi & Appoloni Arquitetura Ltda. | E12: Trabalhista | F12: SAÍDAS - EMPRÉSTIMOS APL. E DEVOLUÇÕES | G12: DEVOLUÇãO DE ADIANTAMENTOS DE CLIENTES | H12: 1.1.08.000 | I12: 2026-02 | J12: 2026-02 | K12: 7600 | L12: 7600 | M12: não | N12: sugerida | O12: Adiantamento ou transferência (não é despesa operacional) | Q12: Fora do OPEX | R12: Adiantamento ou transferência (não é despesa operacional) | S12: — | T12: — | U12: exclusão | V12: não avaliado | W12: sugerida | X12: não | Y12: fornecedor sem outra ocorrência na conta em 12 meses; valor atípico (acima de 3x a mediana da conta em 12 meses, mediana 28.05) | Z12: sugerido | AC12: =IF(AA12="",M12,AA12) -> não | AD12: =IF(AB12="",X12,AB12) -> não | AE12: =IF(OR(Configuracao!B9="",Configuracao!B10=""),"aguardando limiar",IF(AND(K12>=Configuracao!B9,K12/MAX(Reconciliacao!C2,1)>=Configuracao!B10/100),"sim","não")) -> aguardando limiar
A13: 11995 | C13: DEVOLUÇÃO VALOR RECEBIDO EQUIVOCADAMENTE | D13: Bárbara Stefany Minosso Menezes | E13: Conta Corrente Clientes | F13: SAÍDAS - EMPRÉSTIMOS APL. E DEVOLUÇÕES | G13: DEVOLUÇãO DE ADIANTAMENTOS DE CLIENTES | H13: 1.1.08.000 | I13: 2026-01 | J13: 2026-01 | K13: 18000 | L13: 18000 | M13: não | N13: confirmada | O13: Despesas reembolsáveis de clientes | P13: departamento_conta_corrente_clientes | Q13: Despesas reembolsáveis de clientes | R13: Despesas reembolsáveis de clientes | S13: — | T13: — | U13: exclusão | V13: não avaliado | W13: confirmada | X13: não | Y13: fornecedor sem outra ocorrência na conta em 12 meses; valor atípico (acima de 3x a mediana da conta em 12 meses, mediana 28.05) | Z13: sugerido | AC13: =IF(AA13="",M13,AA13) -> não | AD13: =IF(AB13="",X13,AB13) -> não | AE13: =IF(OR(Configuracao!B9="",Configuracao!B10=""),"aguardando limiar",IF(AND(K13>=Configuracao!B9,K13/MAX(Reconciliacao!C2,1)>=Configuracao!B10/100),"sim","não")) -> aguardando limiar
A14: 12135 | C14: CAIXA DE SOM PORTÁTIL | D14: Mercado Livre | E14: Facilities | F14: INVESTIMENTOS | G14: MÓVEIS E EQUIPAMENTOS | H14: 10.1.01.000 | I14: 2026-02 | J14: 2026-02 | K14: 112.66 | L14: 112.66 | M14: não | N14: confirmada | O14: Investimento / CAPEX | Q14: Investimento / CAPEX | R14: Investimento / CAPEX | S14: — | T14: — | U14: investimento | V14: não avaliado | W14: confirmada | X14: sim | Z14: sem sinal | AC14: =IF(AA14="",M14,AA14) -> não | AD14: =IF(AB14="",X14,AB14) -> sim | AE14: =IF(OR(Configuracao!B9="",Configuracao!B10=""),"aguardando limiar",IF(AND(K14>=Configuracao!B9,K14/MAX(Reconciliacao!C2,1)>=Configuracao!B10/100),"sim","não")) -> aguardando limiar
A15: 15817 | C15: MÁQUINA DOLCE GUSTO | D15: NESTLE BRASIL LTDA. | E15: Facilities | F15: INVESTIMENTOS | G15: MÓVEIS E EQUIPAMENTOS | H15: 10.1.01.000 | I15: 2026-04 | J15: 2026-04 | K15: 454.77 | L15: 454.77 | M15: não | N15: confirmada | O15: Investimento / CAPEX | Q15: Investimento / CAPEX | R15: Investimento / CAPEX | S15: — | T15: — | U15: investimento | V15: não avaliado | W15: confirmada | X15: sim | Z15: sem sinal | AC15: =IF(AA15="",M15,AA15) -> não | AD15: =IF(AB15="",X15,AB15) -> sim | AE15: =IF(OR(Configuracao!B9="",Configuracao!B10=""),"aguardando limiar",IF(AND(K15>=Configuracao!B9,K15/MAX(Reconciliacao!C2,1)>=Configuracao!B10/100),"sim","não")) -> aguardando limiar
A16: 18519 | C16: MONITOR - VALENTINA | D16: Magazine Luiza Marketplace | E16: Marketing | F16: INVESTIMENTOS | G16: EQUIPAMENTOS DE INFORMÁTICA | H16: 10.1.03.000 | I16: 2026-07 | J16: 2026-07 | K16: 209.14 | L16: 209.14 | M16: não | N16: confirmada | O16: Investimento / CAPEX | Q16: Investimento / CAPEX | R16: Investimento / CAPEX | S16: — | T16: — | U16: investimento | V16: não avaliado | W16: confirmada | X16: sim | Z16: sem sinal | AC16: =IF(AA16="",M16,AA16) -> não | AD16: =IF(AB16="",X16,AB16) -> sim | AE16: =IF(OR(Configuracao!B9="",Configuracao!B10=""),"aguardando limiar",IF(AND(K16>=Configuracao!B9,K16/MAX(Reconciliacao!C2,1)>=Configuracao!B10/100),"sim","não")) -> aguardando limiar
A17: 19029 | C17: MONITOR - CATHARINA CARDOSO | D17: Magazine Luiza Marketplace | E17: R.H. | F17: INVESTIMENTOS | G17: EQUIPAMENTOS DE INFORMÁTICA | H17: 10.1.03.000 | I17: 2026-08 | J17: 2026-09 | K17: 219.88 | L17: 0 | M17: não | N17: confirmada | O17: Investimento / CAPEX | Q17: Investimento / CAPEX | R17: Investimento / CAPEX | S17: — | T17: — | U17: investimento | V17: não avaliado | W17: confirmada | X17: sim | Z17: sem sinal | AC17: =IF(AA17="",M17,AA17) -> não | AD17: =IF(AB17="",X17,AB17) -> sim | AE17: =IF(OR(Configuracao!B9="",Configuracao!B10=""),"aguardando limiar",IF(AND(K17>=Configuracao!B9,K17/MAX(Reconciliacao!C2,1)>=Configuracao!B10/100),"sim","não")) -> aguardando limiar
A18: 12071 | C18: TABLET PARA PONTO ELETRÔNICO | D18: Mercado Livre | E18: Facilities | F18: INVESTIMENTOS | G18: EQUIPAMENTOS DE INFORMÁTICA | H18: 10.1.03.000 | I18: 2026-04 | J18: 2026-04 | K18: 326.66 | L18: 326.66 | M18: não | N18: confirmada | O18: Investimento / CAPEX | Q18: Investimento / CAPEX | R18: Investimento / CAPEX | S18: — | T18: — | U18: investimento | V18: não avaliado | W18: confirmada | X18: sim | Z18: sem sinal | AC18: =IF(AA18="",M18,AA18) -> não | AD18: =IF(AB18="",X18,AB18) -> sim | AE18: =IF(OR(Configuracao!B9="",Configuracao!B10=""),"aguardando limiar",IF(AND(K18>=Configuracao!B9,K18/MAX(Reconciliacao!C2,1)>=Configuracao!B10/100),"sim","não")) -> aguardando limiar
A19: 12072 | C19: TABLET PARA PONTO ELETRÔNICO | D19: Mercado Livre | E19: Facilities | F19: INVESTIMENTOS | G19: EQUIPAMENTOS DE INFORMÁTICA | H19: 10.1.03.000 | I19: 2026-05 | J19: 2026-05 | K19: 326.66 | L19: 326.66 | M19: não | N19: confirmada | O19: Investimento / CAPEX | Q19: Investimento / CAPEX | R19: Investimento / CAPEX | S19: — | T19: — | U19: investimento | V19: não avaliado | W19: confirmada | X19: sim | Z19: sem sinal | AC19: =IF(AA19="",M19,AA19) -> não | AD19: =IF(AB19="",X19,AB19) -> sim | AE19: =IF(OR(Configuracao!B9="",Configuracao!B10=""),"aguardando limiar",IF(AND(K19>=Configuracao!B9,K19/MAX(Reconciliacao!C2,1)>=Configuracao!B10/100),"sim","não")) -> aguardando limiar
A20: 12070 | C20: TABLET PARA PONTO ELETRÔNICO | D20: Mercado Livre | E20: Facilities | F20: INVESTIMENTOS | G20: EQUIPAMENTOS DE INFORMÁTICA | H20: 10.1.03.000 | I20: 2026-03 | J20: 2026-03 | K20: 326.68 | L20: 326.68 | M20: não | N20: confirmada | O20: Investimento / CAPEX | Q20: Investimento / CAPEX | R20: Investimento / CAPEX | S20: — | T20: — | U20: investimento | V20: não avaliado | W20: confirmada | X20: sim | Z20: sem sinal | AC20: =IF(AA20="",M20,AA20) -> não | AD20: =IF(AB20="",X20,AB20) -> sim | AE20: =IF(OR(Configuracao!B9="",Configuracao!B10=""),"aguardando limiar",IF(AND(K20>=Configuracao!B9,K20/MAX(Reconciliacao!C2,1)>=Configuracao!B10/100),"sim","não")) -> aguardando limiar
A21: 12832 | C21: NOTEBOOK - LEONARDO MARQUES | D21: Amazon Servicos | E21: Marketing | F21: INVESTIMENTOS | G21: EQUIPAMENTOS DE INFORMÁTICA | H21: 10.1.03.000 | I21: 2026-04 | J21: 2026-04 | K21: 555.9 | L21: 555.9 | M21: não | N21: confirmada | O21: Investimento / CAPEX | Q21: Investimento / CAPEX | R21: Investimento / CAPEX | S21: — | T21: — | U21: investimento | V21: não avaliado | W21: confirmada | X21: sim | Z21: sem sinal | AC21: =IF(AA21="",M21,AA21) -> não | AD21: =IF(AB21="",X21,AB21) -> sim | AE21: =IF(OR(Configuracao!B9="",Configuracao!B10=""),"aguardando limiar",IF(AND(K21>=Configuracao!B9,K21/MAX(Reconciliacao!C2,1)>=Configuracao!B10/100),"sim","não")) -> aguardando limiar
A22: 12833 | C22: NOTEBOOK - LEONARDO MARQUES | D22: Amazon Servicos | E22: Marketing | F22: INVESTIMENTOS | G22: EQUIPAMENTOS DE INFORMÁTICA | H22: 10.1.03.000 | I22: 2026-05 | J22: 2026-05 | K22: 555.9 | L22: 555.9 | M22: não | N22: confirmada | O22: Investimento / CAPEX | Q22: Investimento / CAPEX | R22: Investimento / CAPEX | S22: — | T22: — | U22: investimento | V22: não avaliado | W22: confirmada | X22: sim | Z22: sem sinal | AC22: =IF(AA22="",M22,AA22) -> não | AD22: =IF(AB22="",X22,AB22) -> sim | AE22: =IF(OR(Configuracao!B9="",Configuracao!B10=""),"aguardando limiar",IF(AND(K22>=Configuracao!B9,K22/MAX(Reconciliacao!C2,1)>=Configuracao!B10/100),"sim","não")) -> aguardando limiar
A23: 12834 | C23: NOTEBOOK - LEONARDO MARQUES | D23: Amazon Servicos | E23: Marketing | F23: INVESTIMENTOS | G23: EQUIPAMENTOS DE INFORMÁTICA | H23: 10.1.03.000 | I23: 2026-06 | J23: 2026-06 | K23: 555.9 | L23: 555.9 | M23: não | N23: confirmada | O23: Investimento / CAPEX | Q23: Investimento / CAPEX | R23: Investimento / CAPEX | S23: — | T23: — | U23: investimento | V23: não avaliado | W23: confirmada | X23: sim | Z23: sem sinal | AC23: =IF(AA23="",M23,AA23) -> não | AD23: =IF(AB23="",X23,AB23) -> sim | AE23: =IF(OR(Configuracao!B9="",Configuracao!B10=""),"aguardando limiar",IF(AND(K23>=Configuracao!B9,K23/MAX(Reconciliacao!C2,1)>=Configuracao!B10/100),"sim","não")) -> aguardando limiar
A24: 12835 | C24: NOTEBOOK - LEONARDO MARQUES | D24: Amazon Servicos | E24: Marketing | F24: INVESTIMENTOS | G24: EQUIPAMENTOS DE INFORMÁTICA | H24: 10.1.03.000 | I24: 2026-07 | J24: 2026-07 | K24: 555.9 | L24: 555.9 | M24: não | N24: confirmada | O24: Investimento / CAPEX | Q24: Investimento / CAPEX | R24: Investimento / CAPEX | S24: — | T24: — | U24: investimento | V24: não avaliado | W24: confirmada | X24: sim | Z24: sem sinal | AC24: =IF(AA24="",M24,AA24) -> não | AD24: =IF(AB24="",X24,AB24) -> sim | AE24: =IF(OR(Configuracao!B9="",Configuracao!B10=""),"aguardando limiar",IF(AND(K24>=Configuracao!B9,K24/MAX(Reconciliacao!C2,1)>=Configuracao!B10/100),"sim","não")) -> aguardando limiar
A25: 12836 | C25: NOTEBOOK - LEONARDO MARQUES | D25: Amazon Servicos | E25: Marketing | F25: INVESTIMENTOS | G25: EQUIPAMENTOS DE INFORMÁTICA | H25: 10.1.03.000 | I25: 2026-08 | J25: 2026-08 | K25: 555.9 | L25: 555.9 | M25: não | N25: confirmada | O25: Investimento / CAPEX | Q25: Investimento / CAPEX | R25: Investimento / CAPEX | S25: — | T25: — | U25: investimento | V25: não avaliado | W25: confirmada | X25: sim | Z25: sem sinal | AC25: =IF(AA25="",M25,AA25) -> não | AD25: =IF(AB25="",X25,AB25) -> sim | AE25: =IF(OR(Configuracao!B9="",Configuracao!B10=""),"aguardando limiar",IF(AND(K25>=Configuracao!B9,K25/MAX(Reconciliacao!C2,1)>=Configuracao!B10/100),"sim","não")) -> aguardando limiar
A26: 17621 | C26: NOTEBOOK VINICIUS SCHMOCKEL | D26: Magazine Luiza Marketplace | E26: Operações Legais | F26: INVESTIMENTOS | G26: EQUIPAMENTOS DE INFORMÁTICA | H26: 10.1.03.000 | I26: 2026-06 | J26: 2026-06 | K26: 649.9 | L26: 649.9 | M26: não | N26: confirmada | O26: Investimento / CAPEX | Q26: Investimento / CAPEX | R26: Investimento / CAPEX | S26: — | T26: — | U26: investimento | V26: não avaliado | W26: confirmada | X26: sim | Z26: sem sinal | AC26: =IF(AA26="",M26,AA26) -> não | AD26: =IF(AB26="",X26,AB26) -> sim | AE26: =IF(OR(Configuracao!B9="",Configuracao!B10=""),"aguardando limiar",IF(AND(K26>=Configuracao!B9,K26/MAX(Reconciliacao!C2,1)>=Configuracao!B10/100),"sim","não")) -> aguardando limiar
A27: 17622 | C27: NOTEBOOK VINICIUS SCHMOCKEL | D27: Magazine Luiza Marketplace | E27: Operações Legais | F27: INVESTIMENTOS | G27: EQUIPAMENTOS DE INFORMÁTICA | H27: 10.1.03.000 | I27: 2026-07 | J27: 2026-07 | K27: 649.9 | L27: 649.9 | M27: não | N27: confirmada | O27: Investimento / CAPEX | Q27: Investimento / CAPEX | R27: Investimento / CAPEX | S27: — | T27: — | U27: investimento | V27: não avaliado | W27: confirmada | X27: sim | Z27: sem sinal | AC27: =IF(AA27="",M27,AA27) -> não | AD27: =IF(AB27="",X27,AB27) -> sim | AE27: =IF(OR(Configuracao!B9="",Configuracao!B10=""),"aguardando limiar",IF(AND(K27>=Configuracao!B9,K27/MAX(Reconciliacao!C2,1)>=Configuracao!B10/100),"sim","não")) -> aguardando limiar
A28: 17623 | C28: NOTEBOOK VINICIUS SCHMOCKEL | D28: Magazine Luiza Marketplace | E28: Operações Legais | F28: INVESTIMENTOS | G28: EQUIPAMENTOS DE INFORMÁTICA | H28: 10.1.03.000 | I28: 2026-08 | J28: 2026-08 | K28: 649.9 | L28: 649.9 | M28: não | N28: confirmada | O28: Investimento / CAPEX | Q28: Investimento / CAPEX | R28: Investimento / CAPEX | S28: — | T28: — | U28: investimento | V28: não avaliado | W28: confirmada | X28: sim | Z28: sem sinal | AC28: =IF(AA28="",M28,AA28) -> não | AD28: =IF(AB28="",X28,AB28) -> sim | AE28: =IF(OR(Configuracao!B9="",Configuracao!B10=""),"aguardando limiar",IF(AND(K28>=Configuracao!B9,K28/MAX(Reconciliacao!C2,1)>=Configuracao!B10/100),"sim","não")) -> aguardando limiar
A29: 9284 | C29: PARCELA 05/06 | D29: Magazine Luiza Marketplace | E29: Insolvência | F29: INVESTIMENTOS | G29: EQUIPAMENTOS DE INFORMÁTICA | H29: 10.1.03.000 | I29: 2026-01 | J29: 2026-01 | K29: 666.48 | L29: 666.48 | M29: não | N29: confirmada | O29: Investimento / CAPEX | Q29: Investimento / CAPEX | R29: Investimento / CAPEX | S29: — | T29: — | U29: investimento | V29: não avaliado | W29: confirmada | X29: sim | Z29: sem sinal | AC29: =IF(AA29="",M29,AA29) -> não | AD29: =IF(AB29="",X29,AB29) -> sim | AE29: =IF(OR(Configuracao!B9="",Configuracao!B10=""),"aguardando limiar",IF(AND(K29>=Configuracao!B9,K29/MAX(Reconciliacao!C2,1)>=Configuracao!B10/100),"sim","não")) -> aguardando limiar
A30: 9285 | C30: PARCELA 06/06 | D30: Magazine Luiza Marketplace | E30: Insolvência | F30: INVESTIMENTOS | G30: EQUIPAMENTOS DE INFORMÁTICA | H30: 10.1.03.000 | I30: 2026-02 | J30: 2026-02 | K30: 666.48 | L30: 666.48 | M30: não | N30: confirmada | O30: Investimento / CAPEX | Q30: Investimento / CAPEX | R30: Investimento / CAPEX | S30: — | T30: — | U30: investimento | V30: não avaliado | W30: confirmada | X30: sim | Z30: sem sinal | AC30: =IF(AA30="",M30,AA30) -> não | AD30: =IF(AB30="",X30,AB30) -> sim | AE30: =IF(OR(Configuracao!B9="",Configuracao!B10=""),"aguardando limiar",IF(AND(K30>=Configuracao!B9,K30/MAX(Reconciliacao!C2,1)>=Configuracao!B10/100),"sim","não")) -> aguardando limiar
A31: 11646 | C31: COMPRA NOTEBOOK QUE ESTAVA COM PAGAMENTO PENDENTE PELO RICARDO.NÃO HÁ RASTREIO SOBRE QUAL ÁREA UTILIZA O RESPECTIVO EQUIPAMENTO. | D31: Fabricio Fais Ferreira | E31: Ricardo Viscardi Pires | F31: INVESTIMENTOS | G31: EQUIPAMENTOS DE INFORMÁTICA | H31: 10.1.03.000 | I31: 2026-01 | J31: 2026-01 | K31: 1500 | L31: 1500 | M31: não | N31: confirmada | O31: Investimento / CAPEX | Q31: Investimento / CAPEX | R31: Investimento / CAPEX | S31: — | T31: — | U31: investimento | V31: não avaliado | W31: confirmada | X31: não | Y31: fornecedor sem outra ocorrência na conta em 12 meses | Z31: sugerido | AC31: =IF(AA31="",M31,AA31) -> não | AD31: =IF(AB31="",X31,AB31) -> não | AE31: =IF(OR(Configuracao!B9="",Configuracao!B10=""),"aguardando limiar",IF(AND(K31>=Configuracao!B9,K31/MAX(Reconciliacao!C2,1)>=Configuracao!B10/100),"sim","não")) -> aguardando limiar
A32: 12139 | C32: TELEFONE SALA GUSTAVO | D32: Amazon Servicos | E32: Gustavo Bismarchi Motta | F32: INVESTIMENTOS | G32: EQUIPAMENTOS DE COMUNICAÇãO | H32: 10.1.11.000 | I32: 2026-02 | J32: 2026-02 | K32: 189 | L32: 189 | M32: não | N32: confirmada | O32: Investimento / CAPEX | Q32: Investimento / CAPEX | R32: Investimento / CAPEX | S32: — | T32: — | U32: investimento | V32: não avaliado | W32: confirmada | X32: sim | Z32: sem sinal | AC32: =IF(AA32="",M32,AA32) -> não | AD32: =IF(AB32="",X32,AB32) -> sim | AE32: =IF(OR(Configuracao!B9="",Configuracao!B10=""),"aguardando limiar",IF(AND(K32>=Configuracao!B9,K32/MAX(Reconciliacao!C2,1)>=Configuracao!B10/100),"sim","não")) -> aguardando limiar
A33: 6001 | C33: REPASSE ACORDO CONSTRURBAN - PARCELA 15/15 | D33: Alexandre Fantazzini Rigi | E33: Distressed Deals | F33: OUTRAS RECEITAS OPERACIONAIS | G33: REPASSE DE OUTRAS RECEITAS | H33: 3.2.07.000 | I33: 2025-11 | J33: 2026-01 | K33: 0 | L33: 21349.3 | M33: não | N33: confirmada | O33: Repasse ao cliente (3.2.07 REPASSE DE OUTRAS RECEITAS; 2.6.04 sem movimento no período) | P33: repasse | Q33: Repasse ao cliente | R33: Repasse ao cliente (3.2.07 REPASSE DE OUTRAS RECEITAS; 2.6.04 sem movimento no período) | S33: — | T33: — | U33: exclusão | V33: não avaliado | W33: confirmada | X33: sim | Z33: sem sinal | AC33: =IF(AA33="",M33,AA33) -> não | AD33: =IF(AB33="",X33,AB33) -> sim | AE33: =IF(OR(Configuracao!B9="",Configuracao!B10=""),"aguardando limiar",IF(AND(K33>=Configuracao!B9,K33/MAX(Reconciliacao!C2,1)>=Configuracao!B10/100),"sim","não")) -> aguardando limiar
A34: 17019 | C34: REPASSE ACORDO CONSTRURBAN | D34: Alexandre Fantazzini Rigi | E34: Insolvência | F34: OUTRAS RECEITAS OPERACIONAIS | G34: REPASSE DE OUTRAS RECEITAS | H34: 3.2.07.000 | I34: 2026-06 | J34: 2026-06 | K34: 191.7 | L34: 191.7 | M34: não | N34: confirmada | O34: Repasse ao cliente (3.2.07 REPASSE DE OUTRAS RECEITAS; 2.6.04 sem movimento no período) | P34: repasse | Q34: Repasse ao cliente | R34: Repasse ao cliente (3.2.07 REPASSE DE OUTRAS RECEITAS; 2.6.04 sem movimento no período) | S34: — | T34: — | U34: exclusão | V34: não avaliado | W34: confirmada | X34: sim | Z34: sem sinal | AC34: =IF(AA34="",M34,AA34) -> não | AD34: =IF(AB34="",X34,AB34) -> sim | AE34: =IF(OR(Configuracao!B9="",Configuracao!B10=""),"aguardando limiar",IF(AND(K34>=Configuracao!B9,K34/MAX(Reconciliacao!C2,1)>=Configuracao!B10/100),"sim","não")) -> aguardando limiar
A35: 17833 | C35: REPASSE ACORDO CONSTRURBAN | D35: Alexandre Fantazzini Rigi | E35: Insolvência | F35: OUTRAS RECEITAS OPERACIONAIS | G35: REPASSE DE OUTRAS RECEITAS | H35: 3.2.07.000 | I35: 2026-07 | J35: 2026-07 | K35: 191.99 | L35: 191.99 | M35: não | N35: confirmada | O35: Repasse ao cliente (3.2.07 REPASSE DE OUTRAS RECEITAS; 2.6.04 sem movimento no período) | P35: repasse | Q35: Repasse ao cliente | R35: Repasse ao cliente (3.2.07 REPASSE DE OUTRAS RECEITAS; 2.6.04 sem movimento no período) | S35: — | T35: — | U35: exclusão | V35: não avaliado | W35: confirmada | X35: sim | Z35: sem sinal | AC35: =IF(AA35="",M35,AA35) -> não | AD35: =IF(AB35="",X35,AB35) -> sim | AE35: =IF(OR(Configuracao!B9="",Configuracao!B10=""),"aguardando limiar",IF(AND(K35>=Configuracao!B9,K35/MAX(Reconciliacao!C2,1)>=Configuracao!B10/100),"sim","não")) -> aguardando limiar
A36: 18691 | C36: REPASSE ACORDO CONSTRURBAN | D36: Alexandre Fantazzini Rigi | E36: Insolvência | F36: OUTRAS RECEITAS OPERACIONAIS | G36: REPASSE DE OUTRAS RECEITAS | H36: 3.2.07.000 | I36: 2026-08 | J36: 2026-08 | K36: 192.27 | L36: 192.27 | M36: não | N36: confirmada | O36: Repasse ao cliente (3.2.07 REPASSE DE OUTRAS RECEITAS; 2.6.04 sem movimento no período) | P36: repasse | Q36: Repasse ao cliente | R36: Repasse ao cliente (3.2.07 REPASSE DE OUTRAS RECEITAS; 2.6.04 sem movimento no período) | S36: — | T36: — | U36: exclusão | V36: não avaliado | W36: confirmada | X36: sim | Z36: sem sinal | AC36: =IF(AA36="",M36,AA36) -> não | AD36: =IF(AB36="",X36,AB36) -> sim | AE36: =IF(OR(Configuracao!B9="",Configuracao!B10=""),"aguardando limiar",IF(AND(K36>=Configuracao!B9,K36/MAX(Reconciliacao!C2,1)>=Configuracao!B10/100),"sim","não")) -> aguardando limiar
A37: 13358 | C37: REPASSE ACORDO DECORWATTS X PENA CONSTRUÇÕES | D37: Decorwatts Eletrica e Iluminacao Ltda | E37: Distressed Deals | F37: OUTRAS RECEITAS OPERACIONAIS | G37: REPASSE DE OUTRAS RECEITAS | H37: 3.2.07.000 | I37: 2026-03 | J37: 2026-03 | K37: 302.49 | L37: 302.49 | M37: não | N37: confirmada | O37: Repasse ao cliente (3.2.07 REPASSE DE OUTRAS RECEITAS; 2.6.04 sem movimento no período) | P37: repasse | Q37: Repasse ao cliente | R37: Repasse ao cliente (3.2.07 REPASSE DE OUTRAS RECEITAS; 2.6.04 sem movimento no período) | S37: — | T37: — | U37: exclusão | V37: não avaliado | W37: confirmada | X37: sim | Z37: sem sinal | AC37: =IF(AA37="",M37,AA37) -> não | AD37: =IF(AB37="",X37,AB37) -> sim | AE37: =IF(OR(Configuracao!B9="",Configuracao!B10=""),"aguardando limiar",IF(AND(K37>=Configuracao!B9,K37/MAX(Reconciliacao!C2,1)>=Configuracao!B10/100),"sim","não")) -> aguardando limiar
A38: 13359 | C38: REPASSE ACORDO DECORWATTS X KM 18 | D38: Decorwatts Eletrica e Iluminacao Ltda | E38: Distressed Deals | F38: OUTRAS RECEITAS OPERACIONAIS | G38: REPASSE DE OUTRAS RECEITAS | H38: 3.2.07.000 | I38: 2026-03 | J38: 2026-03 | K38: 312.41 | L38: 312.41 | M38: não | N38: confirmada | O38: Repasse ao cliente (3.2.07 REPASSE DE OUTRAS RECEITAS; 2.6.04 sem movimento no período) | P38: repasse | Q38: Repasse ao cliente | R38: Repasse ao cliente (3.2.07 REPASSE DE OUTRAS RECEITAS; 2.6.04 sem movimento no período) | S38: — | T38: — | U38: exclusão | V38: não avaliado | W38: confirmada | X38: sim | Z38: sem sinal | AC38: =IF(AA38="",M38,AA38) -> não | AD38: =IF(AB38="",X38,AB38) -> sim | AE38: =IF(OR(Configuracao!B9="",Configuracao!B10=""),"aguardando limiar",IF(AND(K38>=Configuracao!B9,K38/MAX(Reconciliacao!C2,1)>=Configuracao!B10/100),"sim","não")) -> aguardando limiar
A39: 12238 | C39: MLE PROCESSO 1000140-12.2020.8.26.0650 | D39: Perfilix Industria e Comercio de Perfis Eireli | E39: Conta Corrente Clientes | F39: OUTRAS RECEITAS OPERACIONAIS | G39: REPASSE DE OUTRAS RECEITAS | H39: 3.2.07.000 | I39: 2026-02 | J39: 2026-02 | K39: 314.01 | L39: 314.01 | M39: não | N39: confirmada | O39: Despesas reembolsáveis de clientes | P39: departamento_conta_corrente_clientes | Q39: Despesas reembolsáveis de clientes | R39: Despesas reembolsáveis de clientes | S39: — | T39: — | U39: exclusão | V39: não avaliado | W39: confirmada | X39: sim | Z39: sem sinal | AC39: =IF(AA39="",M39,AA39) -> não | AD39: =IF(AB39="",X39,AB39) -> sim | AE39: =IF(OR(Configuracao!B9="",Configuracao!B10=""),"aguardando limiar",IF(AND(K39>=Configuracao!B9,K39/MAX(Reconciliacao!C2,1)>=Configuracao!B10/100),"sim","não")) -> aguardando limiar
A40: 17330 | C40: REPASSE LIBERAÇÃO JUDICIAL PROC. 000306587020258160014REJANE COSTA - R$ 7.917,00EUNICE RENNA - R$ 16.000,00FATIMA SAMÕES - R$ 10.500,00FELIPE RODRIGUES - R$ 516,92FELIPE RODRIGUES - R$ 1.000,00LILIAN VIEIRA - R$ 2.000,00 | D40: Decorwatts Eletrica e Iluminacao Ltda | E40: Recuperação de Crédito | F40: OUTRAS RECEITAS OPERACIONAIS | G40: REPASSE DE OUTRAS RECEITAS | H40: 3.2.07.000 | I40: 2026-06 | J40: 2026-06 | K40: 516.92 | L40: 516.92 | M40: não | N40: confirmada | O40: Repasse ao cliente (3.2.07 REPASSE DE OUTRAS RECEITAS; 2.6.04 sem movimento no período) | P40: repasse | Q40: Repasse ao cliente | R40: Repasse ao cliente (3.2.07 REPASSE DE OUTRAS RECEITAS; 2.6.04 sem movimento no período) | S40: — | T40: — | U40: exclusão | V40: não avaliado | W40: confirmada | X40: sim | Z40: sem sinal | AC40: =IF(AA40="",M40,AA40) -> não | AD40: =IF(AB40="",X40,AB40) -> sim | AE40: =IF(OR(Configuracao!B9="",Configuracao!B10=""),"aguardando limiar",IF(AND(K40>=Configuracao!B9,K40/MAX(Reconciliacao!C2,1)>=Configuracao!B10/100),"sim","não")) -> aguardando limiar
A41: 18480 | C41: REPASSE ACORDO FÁBIO IORGULO | D41: Perfilix Industria e Comercio de Perfis Eireli | E41: Recuperação de Crédito | F41: OUTRAS RECEITAS OPERACIONAIS | G41: REPASSE DE OUTRAS RECEITAS | H41: 3.2.07.000 | I41: 2026-07 | J41: 2026-07 | K41: 686.63 | L41: 686.63 | M41: não | N41: confirmada | O41: Repasse ao cliente (3.2.07 REPASSE DE OUTRAS RECEITAS; 2.6.04 sem movimento no período) | P41: repasse | Q41: Repasse ao cliente | R41: Repasse ao cliente (3.2.07 REPASSE DE OUTRAS RECEITAS; 2.6.04 sem movimento no período) | S41: — | T41: — | U41: exclusão | V41: não avaliado | W41: confirmada | X41: sim | Z41: sem sinal | AC41: =IF(AA41="",M41,AA41) -> não | AD41: =IF(AB41="",X41,AB41) -> sim | AE41: =IF(OR(Configuracao!B9="",Configuracao!B10=""),"aguardando limiar",IF(AND(K41>=Configuracao!B9,K41/MAX(Reconciliacao!C2,1)>=Configuracao!B10/100),"sim","não")) -> aguardando limiar
A42: 19041 | C42: REPASSE ACORDO FÁBIO IORGULO | D42: Perfilix Industria e Comercio de Perfis Eireli | E42: Recuperação de Crédito | F42: OUTRAS RECEITAS OPERACIONAIS | G42: REPASSE DE OUTRAS RECEITAS | H42: 3.2.07.000 | I42: 2026-08 | J42: 2026-08 | K42: 686.63 | L42: 686.63 | M42: não | N42: confirmada | O42: Repasse ao cliente (3.2.07 REPASSE DE OUTRAS RECEITAS; 2.6.04 sem movimento no período) | P42: repasse | Q42: Repasse ao cliente | R42: Repasse ao cliente (3.2.07 REPASSE DE OUTRAS RECEITAS; 2.6.04 sem movimento no período) | S42: — | T42: — | U42: exclusão | V42: não avaliado | W42: confirmada | X42: sim | Z42: sem sinal | AC42: =IF(AA42="",M42,AA42) -> não | AD42: =IF(AB42="",X42,AB42) -> sim | AE42: =IF(OR(Configuracao!B9="",Configuracao!B10=""),"aguardando limiar",IF(AND(K42>=Configuracao!B9,K42/MAX(Reconciliacao!C2,1)>=Configuracao!B10/100),"sim","não")) -> aguardando limiar
A43: 12900 | C43: REPASSE ACORDO SBV SOLUÇÕES AMBIENTAIS | D43: Inovageo Geossinteticos Ltda | E43: Distressed Deals | F43: OUTRAS RECEITAS OPERACIONAIS | G43: REPASSE DE OUTRAS RECEITAS | H43: 3.2.07.000 | I43: 2026-03 | J43: 2026-03 | K43: 699.5 | L43: 699.5 | M43: não | N43: confirmada | O43: Repasse ao cliente (3.2.07 REPASSE DE OUTRAS RECEITAS; 2.6.04 sem movimento no período) | P43: repasse | Q43: Repasse ao cliente | R43: Repasse ao cliente (3.2.07 REPASSE DE OUTRAS RECEITAS; 2.6.04 sem movimento no período) | S43: — | T43: — | U43: exclusão | V43: não avaliado | W43: confirmada | X43: sim | Z43: sem sinal | AC43: =IF(AA43="",M43,AA43) -> não | AD43: =IF(AB43="",X43,AB43) -> sim | AE43: =IF(OR(Configuracao!B9="",Configuracao!B10=""),"aguardando limiar",IF(AND(K43>=Configuracao!B9,K43/MAX(Reconciliacao!C2,1)>=Configuracao!B10/100),"sim","não")) -> aguardando limiar
A44: 16657 | C44: REPASSE ACORDO CONSTRURBAN - JANEIRO A ABRIL/2026 | D44: Alexandre Fantazzini Rigi | E44: Insolvência | F44: OUTRAS RECEITAS OPERACIONAIS | G44: REPASSE DE OUTRAS RECEITAS | H44: 3.2.07.000 | I44: 2026-05 | J44: 2026-05 | K44: 764 | L44: 764 | M44: não | N44: confirmada | O44: Repasse ao cliente (3.2.07 REPASSE DE OUTRAS RECEITAS; 2.6.04 sem movimento no período) | P44: repasse | Q44: Repasse ao cliente | R44: Repasse ao cliente (3.2.07 REPASSE DE OUTRAS RECEITAS; 2.6.04 sem movimento no período) | S44: — | T44: — | U44: exclusão | V44: não avaliado | W44: confirmada | X44: sim | Z44: sem sinal | AC44: =IF(AA44="",M44,AA44) -> não | AD44: =IF(AB44="",X44,AB44) -> sim | AE44: =IF(OR(Configuracao!B9="",Configuracao!B10=""),"aguardando limiar",IF(AND(K44>=Configuracao!B9,K44/MAX(Reconciliacao!C2,1)>=Configuracao!B10/100),"sim","não")) -> aguardando limiar
A45: 13085 | C45: REPASSE PROCESSO 00029099420208260428 | D45: Antonio Paulino Inglez | E45: Insolvência | F45: OUTRAS RECEITAS OPERACIONAIS | G45: REPASSE DE OUTRAS RECEITAS | H45: 3.2.07.000 | I45: 2026-02 | J45: 2026-02 | K45: 864.12 | L45: 864.12 | M45: não | N45: confirmada | O45: Repasse ao cliente (3.2.07 REPASSE DE OUTRAS RECEITAS; 2.6.04 sem movimento no período) | P45: repasse | Q45: Repasse ao cliente | R45: Repasse ao cliente (3.2.07 REPASSE DE OUTRAS RECEITAS; 2.6.04 sem movimento no período) | S45: — | T45: — | U45: exclusão | V45: não avaliado | W45: confirmada | X45: sim | Z45: sem sinal | AC45: =IF(AA45="",M45,AA45) -> não | AD45: =IF(AB45="",X45,AB45) -> sim | AE45: =IF(OR(Configuracao!B9="",Configuracao!B10=""),"aguardando limiar",IF(AND(K45>=Configuracao!B9,K45/MAX(Reconciliacao!C2,1)>=Configuracao!B10/100),"sim","não")) -> aguardando limiar
A46: 17332 | C46: REPASSE LIBERAÇÃO JUDICIAL PROC. 000306587020258160014REJANE COSTA - R$ 7.917,00EUNICE RENNA - R$ 16.000,00FATIMA SAMÕES - R$ 10.500,00FELIPE RODRIGUES - R$ 516,92FELIPE RODRIGUES - R$ 1.000,00LILIAN VIEIRA - R$ 2.000,00 | D46: Decorwatts Eletrica e Iluminacao Ltda | E46: Recuperação de Crédito | F46: OUTRAS RECEITAS OPERACIONAIS | G46: REPASSE DE OUTRAS RECEITAS | H46: 3.2.07.000 | I46: 2026-06 | J46: 2026-06 | K46: 1000 | L46: 1000 | M46: não | N46: confirmada | O46: Repasse ao cliente (3.2.07 REPASSE DE OUTRAS RECEITAS; 2.6.04 sem movimento no período) | P46: repasse | Q46: Repasse ao cliente | R46: Repasse ao cliente (3.2.07 REPASSE DE OUTRAS RECEITAS; 2.6.04 sem movimento no período) | S46: — | T46: — | U46: exclusão | V46: não avaliado | W46: confirmada | X46: sim | Z46: sem sinal | AC46: =IF(AA46="",M46,AA46) -> não | AD46: =IF(AB46="",X46,AB46) -> sim | AE46: =IF(OR(Configuracao!B9="",Configuracao!B10=""),"aguardando limiar",IF(AND(K46>=Configuracao!B9,K46/MAX(Reconciliacao!C2,1)>=Configuracao!B10/100),"sim","não")) -> aguardando limiar
A47: 11643 | C47: REPASSE PROCESSO 10035085620188260114 - APOSENTADORIA | D47: Kazuo Nishiwaki | E47: Insolvência | F47: OUTRAS RECEITAS OPERACIONAIS | G47: REPASSE DE OUTRAS RECEITAS | H47: 3.2.07.000 | I47: 2026-01 | J47: 2026-01 | K47: 1107.98 | L47: 1107.98 | M47: não | N47: confirmada | O47: Repasse ao cliente (3.2.07 REPASSE DE OUTRAS RECEITAS; 2.6.04 sem movimento no período) | P47: repasse | Q47: Repasse ao cliente | R47: Repasse ao cliente (3.2.07 REPASSE DE OUTRAS RECEITAS; 2.6.04 sem movimento no período) | S47: — | T47: — | U47: exclusão | V47: não avaliado | W47: confirmada | X47: não | Y47: fornecedor sem outra ocorrência na conta em 12 meses | Z47: sugerido | AC47: =IF(AA47="",M47,AA47) -> não | AD47: =IF(AB47="",X47,AB47) -> não | AE47: =IF(OR(Configuracao!B9="",Configuracao!B10=""),"aguardando limiar",IF(AND(K47>=Configuracao!B9,K47/MAX(Reconciliacao!C2,1)>=Configuracao!B10/100),"sim","não")) -> aguardando limiar
A48: 17995 | C48: REPASSE LIBERAÇÃO JUDICIAL - PROC. 1020087-64.2023.8.26.0224 | D48: Perfilix Industria e Comercio de Perfis Eireli | E48: Recuperação de Crédito | F48: OUTRAS RECEITAS OPERACIONAIS | G48: REPASSE DE OUTRAS RECEITAS | H48: 3.2.07.000 | I48: 2026-07 | J48: 2026-07 | K48: 1147.45 | L48: 1147.45 | M48: não | N48: confirmada | O48: Repasse ao cliente (3.2.07 REPASSE DE OUTRAS RECEITAS; 2.6.04 sem movimento no período) | P48: repasse | Q48: Repasse ao cliente | R48: Repasse ao cliente (3.2.07 REPASSE DE OUTRAS RECEITAS; 2.6.04 sem movimento no período) | S48: — | T48: — | U48: exclusão | V48: não avaliado | W48: confirmada | X48: sim | Z48: sem sinal | AC48: =IF(AA48="",M48,AA48) -> não | AD48: =IF(AB48="",X48,AB48) -> sim | AE48: =IF(OR(Configuracao!B9="",Configuracao!B10=""),"aguardando limiar",IF(AND(K48>=Configuracao!B9,K48/MAX(Reconciliacao!C2,1)>=Configuracao!B10/100),"sim","não")) -> aguardando limiar
A49: 17378 | C49: REPASSE LIBERAÇÃO JUDICIAL PROC. 1000860-98.2025.5.02.0204 | D49: Rafael Tecchio Vigolo | E49: Trabalhista | F49: OUTRAS RECEITAS OPERACIONAIS | G49: REPASSE DE OUTRAS RECEITAS | H49: 3.2.07.000 | I49: 2026-06 | J49: 2026-06 | K49: 1439.42 | L49: 1439.42 | M49: não | N49: confirmada | O49: Repasse ao cliente (3.2.07 REPASSE DE OUTRAS RECEITAS; 2.6.04 sem movimento no período) | P49: repasse | Q49: Repasse ao cliente | R49: Repasse ao cliente (3.2.07 REPASSE DE OUTRAS RECEITAS; 2.6.04 sem movimento no período) | S49: — | T49: — | U49: exclusão | V49: não avaliado | W49: confirmada | X49: não | Y49: fornecedor sem outra ocorrência na conta em 12 meses | Z49: sugerido | AC49: =IF(AA49="",M49,AA49) -> não | AD49: =IF(AB49="",X49,AB49) -> não | AE49: =IF(OR(Configuracao!B9="",Configuracao!B10=""),"aguardando limiar",IF(AND(K49>=Configuracao!B9,K49/MAX(Reconciliacao!C2,1)>=Configuracao!B10/100),"sim","não")) -> aguardando limiar
A50: 18870 | C50: REPASSE ACORDO DENARDI | D50: Inovageo Geossinteticos Ltda | E50: Recuperação de Crédito | F50: OUTRAS RECEITAS OPERACIONAIS | G50: REPASSE DE OUTRAS RECEITAS | H50: 3.2.07.000 | I50: 2026-08 | J50: 2026-08 | K50: 1512.21 | L50: 1512.21 | M50: não | N50: confirmada | O50: Repasse ao cliente (3.2.07 REPASSE DE OUTRAS RECEITAS; 2.6.04 sem movimento no período) | P50: repasse | Q50: Repasse ao cliente | R50: Repasse ao cliente (3.2.07 REPASSE DE OUTRAS RECEITAS; 2.6.04 sem movimento no período) | S50: — | T50: — | U50: exclusão | V50: não avaliado | W50: confirmada | X50: sim | Z50: sem sinal | AC50: =IF(AA50="",M50,AA50) -> não | AD50: =IF(AB50="",X50,AB50) -> sim | AE50: =IF(OR(Configuracao!B9="",Configuracao!B10=""),"aguardando limiar",IF(AND(K50>=Configuracao!B9,K50/MAX(Reconciliacao!C2,1)>=Configuracao!B10/100),"sim","não")) -> aguardando limiar
A51: 11829 | C51: REPASSE ACORDO GS INDUSTRIAL | D51: Covolan Industria Textil Ltda Em Recuperacao Judicial | E51: Distressed Deals | F51: OUTRAS RECEITAS OPERACIONAIS | G51: REPASSE DE OUTRAS RECEITAS | H51: 3.2.07.000 | I51: 2026-01 | J51: 2026-01 | K51: 1875 | L51: 1875 | M51: não | N51: confirmada | O51: Repasse ao cliente (3.2.07 REPASSE DE OUTRAS RECEITAS; 2.6.04 sem movimento no período) | P51: repasse | Q51: Repasse ao cliente | R51: Repasse ao cliente (3.2.07 REPASSE DE OUTRAS RECEITAS; 2.6.04 sem movimento no período) | S51: — | T51: — | U51: exclusão | V51: não avaliado | W51: confirmada | X51: sim | Z51: sem sinal | AC51: =IF(AA51="",M51,AA51) -> não | AD51: =IF(AB51="",X51,AB51) -> sim | AE51: =IF(OR(Configuracao!B9="",Configuracao!B10=""),"aguardando limiar",IF(AND(K51>=Configuracao!B9,K51/MAX(Reconciliacao!C2,1)>=Configuracao!B10/100),"sim","não")) -> aguardando limiar
A52: 13048 | C52: REPASSE ACORDO GS INDUSTRIAL | D52: Covolan Industria Textil Ltda Em Recuperacao Judicial | E52: Distressed Deals | F52: OUTRAS RECEITAS OPERACIONAIS | G52: REPASSE DE OUTRAS RECEITAS | H52: 3.2.07.000 | I52: 2026-02 | J52: 2026-02 | K52: 1875 | L52: 1875 | M52: não | N52: confirmada | O52: Repasse ao cliente (3.2.07 REPASSE DE OUTRAS RECEITAS; 2.6.04 sem movimento no período) | P52: repasse | Q52: Repasse ao cliente | R52: Repasse ao cliente (3.2.07 REPASSE DE OUTRAS RECEITAS; 2.6.04 sem movimento no período) | S52: — | T52: — | U52: exclusão | V52: não avaliado | W52: confirmada | X52: sim | Z52: sem sinal | AC52: =IF(AA52="",M52,AA52) -> não | AD52: =IF(AB52="",X52,AB52) -> sim | AE52: =IF(OR(Configuracao!B9="",Configuracao!B10=""),"aguardando limiar",IF(AND(K52>=Configuracao!B9,K52/MAX(Reconciliacao!C2,1)>=Configuracao!B10/100),"sim","não")) -> aguardando limiar
A53: 14913 | C53: REPASSE ACORDO GS INDUSTRIAL | D53: Covolan Industria Textil Ltda Em Recuperacao Judicial | E53: Recuperação de Crédito | F53: OUTRAS RECEITAS OPERACIONAIS | G53: REPASSE DE OUTRAS RECEITAS | H53: 3.2.07.000 | I53: 2026-04 | J53: 2026-04 | K53: 1875 | L53: 1875 | M53: não | N53: confirmada | O53: Repasse ao cliente (3.2.07 REPASSE DE OUTRAS RECEITAS; 2.6.04 sem movimento no período) | P53: repasse | Q53: Repasse ao cliente | R53: Repasse ao cliente (3.2.07 REPASSE DE OUTRAS RECEITAS; 2.6.04 sem movimento no período) | S53: — | T53: — | U53: exclusão | V53: não avaliado | W53: confirmada | X53: sim | Z53: sem sinal | AC53: =IF(AA53="",M53,AA53) -> não | AD53: =IF(AB53="",X53,AB53) -> sim | AE53: =IF(OR(Configuracao!B9="",Configuracao!B10=""),"aguardando limiar",IF(AND(K53>=Configuracao!B9,K53/MAX(Reconciliacao!C2,1)>=Configuracao!B10/100),"sim","não")) -> aguardando limiar
A54: 16656 | C54: REPASSE ACORDO GS INDUSTRIAL | D54: Covolan Industria Textil Ltda Em Recuperacao Judicial | E54: Recuperação de Crédito | F54: OUTRAS RECEITAS OPERACIONAIS | G54: REPASSE DE OUTRAS RECEITAS | H54: 3.2.07.000 | I54: 2026-05 | J54: 2026-05 | K54: 1875 | L54: 1875 | M54: não | N54: confirmada | O54: Repasse ao cliente (3.2.07 REPASSE DE OUTRAS RECEITAS; 2.6.04 sem movimento no período) | P54: repasse | Q54: Repasse ao cliente | R54: Repasse ao cliente (3.2.07 REPASSE DE OUTRAS RECEITAS; 2.6.04 sem movimento no período) | S54: — | T54: — | U54: exclusão | V54: não avaliado | W54: confirmada | X54: sim | Z54: sem sinal | AC54: =IF(AA54="",M54,AA54) -> não | AD54: =IF(AB54="",X54,AB54) -> sim | AE54: =IF(OR(Configuracao!B9="",Configuracao!B10=""),"aguardando limiar",IF(AND(K54>=Configuracao!B9,K54/MAX(Reconciliacao!C2,1)>=Configuracao!B10/100),"sim","não")) -> aguardando limiar
A55: 17401 | C55: REPASSE ACORDO GS INDUSTRIAL | D55: Covolan Industria Textil Ltda Em Recuperacao Judicial | E55: Recuperação de Crédito | F55: OUTRAS RECEITAS OPERACIONAIS | G55: REPASSE DE OUTRAS RECEITAS | H55: 3.2.07.000 | I55: 2026-06 | J55: 2026-06 | K55: 1875 | L55: 1875 | M55: não | N55: confirmada | O55: Repasse ao cliente (3.2.07 REPASSE DE OUTRAS RECEITAS; 2.6.04 sem movimento no período) | P55: repasse | Q55: Repasse ao cliente | R55: Repasse ao cliente (3.2.07 REPASSE DE OUTRAS RECEITAS; 2.6.04 sem movimento no período) | S55: — | T55: — | U55: exclusão | V55: não avaliado | W55: confirmada | X55: sim | Z55: sem sinal | AC55: =IF(AA55="",M55,AA55) -> não | AD55: =IF(AB55="",X55,AB55) -> sim | AE55: =IF(OR(Configuracao!B9="",Configuracao!B10=""),"aguardando limiar",IF(AND(K55>=Configuracao!B9,K55/MAX(Reconciliacao!C2,1)>=Configuracao!B10/100),"sim","não")) -> aguardando limiar
A56: 17996 | C56: REPASSE ACORDO GS INDUSTRIAL | D56: Covolan Industria Textil Ltda Em Recuperacao Judicial | E56: Recuperação de Crédito | F56: OUTRAS RECEITAS OPERACIONAIS | G56: REPASSE DE OUTRAS RECEITAS | H56: 3.2.07.000 | I56: 2026-07 | J56: 2026-07 | K56: 1875 | L56: 1875 | M56: não | N56: confirmada | O56: Repasse ao cliente (3.2.07 REPASSE DE OUTRAS RECEITAS; 2.6.04 sem movimento no período) | P56: repasse | Q56: Repasse ao cliente | R56: Repasse ao cliente (3.2.07 REPASSE DE OUTRAS RECEITAS; 2.6.04 sem movimento no período) | S56: — | T56: — | U56: exclusão | V56: não avaliado | W56: confirmada | X56: sim | Z56: sem sinal | AC56: =IF(AA56="",M56,AA56) -> não | AD56: =IF(AB56="",X56,AB56) -> sim | AE56: =IF(OR(Configuracao!B9="",Configuracao!B10=""),"aguardando limiar",IF(AND(K56>=Configuracao!B9,K56/MAX(Reconciliacao!C2,1)>=Configuracao!B10/100),"sim","não")) -> aguardando limiar
A57: 18869 | C57: REPASSE ACORDO GS INDUSTRIAL | D57: Covolan Industria Textil Ltda Em Recuperacao Judicial | E57: Recuperação de Crédito | F57: OUTRAS RECEITAS OPERACIONAIS | G57: REPASSE DE OUTRAS RECEITAS | H57: 3.2.07.000 | I57: 2026-08 | J57: 2026-08 | K57: 1875 | L57: 1875 | M57: não | N57: confirmada | O57: Repasse ao cliente (3.2.07 REPASSE DE OUTRAS RECEITAS; 2.6.04 sem movimento no período) | P57: repasse | Q57: Repasse ao cliente | R57: Repasse ao cliente (3.2.07 REPASSE DE OUTRAS RECEITAS; 2.6.04 sem movimento no período) | S57: — | T57: — | U57: exclusão | V57: não avaliado | W57: confirmada | X57: sim | Z57: sem sinal | AC57: =IF(AA57="",M57,AA57) -> não | AD57: =IF(AB57="",X57,AB57) -> sim | AE57: =IF(OR(Configuracao!B9="",Configuracao!B10=""),"aguardando limiar",IF(AND(K57>=Configuracao!B9,K57/MAX(Reconciliacao!C2,1)>=Configuracao!B10/100),"sim","não")) -> aguardando limiar
A58: 17331 | C58: REPASSE LIBERAÇÃO JUDICIAL PROC. 000306587020258160014REJANE COSTA - R$ 7.917,00EUNICE RENNA - R$ 16.000,00FATIMA SAMÕES - R$ 10.500,00FELIPE RODRIGUES - R$ 516,92FELIPE RODRIGUES - R$ 1.000,00LILIAN VIEIRA - R$ 2.000,00 | D58: Decorwatts Eletrica e Iluminacao Ltda | E58: Recuperação de Crédito | F58: OUTRAS RECEITAS OPERACIONAIS | G58: REPASSE DE OUTRAS RECEITAS | H58: 3.2.07.000 | I58: 2026-06 | J58: 2026-06 | K58: 2000 | L58: 2000 | M58: não | N58: confirmada | O58: Repasse ao cliente (3.2.07 REPASSE DE OUTRAS RECEITAS; 2.6.04 sem movimento no período) | P58: repasse | Q58: Repasse ao cliente | R58: Repasse ao cliente (3.2.07 REPASSE DE OUTRAS RECEITAS; 2.6.04 sem movimento no período) | S58: — | T58: — | U58: exclusão | V58: não avaliado | W58: confirmada | X58: sim | Z58: sem sinal | AC58: =IF(AA58="",M58,AA58) -> não | AD58: =IF(AB58="",X58,AB58) -> sim | AE58: =IF(OR(Configuracao!B9="",Configuracao!B10=""),"aguardando limiar",IF(AND(K58>=Configuracao!B9,K58/MAX(Reconciliacao!C2,1)>=Configuracao!B10/100),"sim","não")) -> aguardando limiar
A59: 18187 | C59: REPASSE ACORDO DENARDI | D59: Inovageo Geossinteticos Ltda | E59: Recuperação de Crédito | F59: OUTRAS RECEITAS OPERACIONAIS | G59: REPASSE DE OUTRAS RECEITAS | H59: 3.2.07.000 | I59: 2026-07 | J59: 2026-07 | K59: 2442.25 | L59: 2442.25 | M59: não | N59: confirmada | O59: Repasse ao cliente (3.2.07 REPASSE DE OUTRAS RECEITAS; 2.6.04 sem movimento no período) | P59: repasse | Q59: Repasse ao cliente | R59: Repasse ao cliente (3.2.07 REPASSE DE OUTRAS RECEITAS; 2.6.04 sem movimento no período) | S59: — | T59: — | U59: exclusão | V59: não avaliado | W59: confirmada | X59: sim | Z59: sem sinal | AC59: =IF(AA59="",M59,AA59) -> não | AD59: =IF(AB59="",X59,AB59) -> sim | AE59: =IF(OR(Configuracao!B9="",Configuracao!B10=""),"aguardando limiar",IF(AND(K59>=Configuracao!B9,K59/MAX(Reconciliacao!C2,1)>=Configuracao!B10/100),"sim","não")) -> aguardando limiar
A60: 17358 | C60: REPASSE LIBERAÇÃO JUDICIAL PROC. 000306587020258160014REJANE COSTA - R$ 7.917,00EUNICE RENNA - R$ 16.000,00FATIMA SAMÕES - R$ 10.500,00FELIPE RODRIGUES - R$ 516,92FELIPE RODRIGUES - R$ 1.000,00LILIAN VIEIRA - R$ 2.000,00 | D60: Decorwatts Eletrica e Iluminacao Ltda | E60: Recuperação de Crédito | F60: OUTRAS RECEITAS OPERACIONAIS | G60: REPASSE DE OUTRAS RECEITAS | H60: 3.2.07.000 | I60: 2026-06 | J60: 2026-06 | K60: 2939.44 | L60: 2939.44 | M60: não | N60: confirmada | O60: Repasse ao cliente (3.2.07 REPASSE DE OUTRAS RECEITAS; 2.6.04 sem movimento no período) | P60: repasse | Q60: Repasse ao cliente | R60: Repasse ao cliente (3.2.07 REPASSE DE OUTRAS RECEITAS; 2.6.04 sem movimento no período) | S60: — | T60: — | U60: exclusão | V60: não avaliado | W60: confirmada | X60: sim | Z60: sem sinal | AC60: =IF(AA60="",M60,AA60) -> não | AD60: =IF(AB60="",X60,AB60) -> sim | AE60: =IF(OR(Configuracao!B9="",Configuracao!B10=""),"aguardando limiar",IF(AND(K60>=Configuracao!B9,K60/MAX(Reconciliacao!C2,1)>=Configuracao!B10/100),"sim","não")) -> aguardando limiar
A61: 12433 | C61: REPASSE ACORDO CONSÓRCIO SANTA BARBARA | D61: Inovageo Geossinteticos Ltda | E61: Distressed Deals | F61: OUTRAS RECEITAS OPERACIONAIS | G61: REPASSE DE OUTRAS RECEITAS | H61: 3.2.07.000 | I61: 2026-02 | J61: 2026-02 | K61: 4050.65 | L61: 4050.65 | M61: não | N61: confirmada | O61: Repasse ao cliente (3.2.07 REPASSE DE OUTRAS RECEITAS; 2.6.04 sem movimento no período) | P61: repasse | Q61: Repasse ao cliente | R61: Repasse ao cliente (3.2.07 REPASSE DE OUTRAS RECEITAS; 2.6.04 sem movimento no período) | S61: — | T61: — | U61: exclusão | V61: não avaliado | W61: confirmada | X61: sim | Z61: sem sinal | AC61: =IF(AA61="",M61,AA61) -> não | AD61: =IF(AB61="",X61,AB61) -> sim | AE61: =IF(OR(Configuracao!B9="",Configuracao!B10=""),"aguardando limiar",IF(AND(K61>=Configuracao!B9,K61/MAX(Reconciliacao!C2,1)>=Configuracao!B10/100),"sim","não")) -> aguardando limiar
A62: 16093 | C62: REPASSE ACORDO GUARA EMPREENDIMENTOS | D62: Inovageo Geossinteticos Ltda | E62: Distressed Deals | F62: OUTRAS RECEITAS OPERACIONAIS | G62: REPASSE DE OUTRAS RECEITAS | H62: 3.2.07.000 | I62: 2026-03 | J62: 2026-03 | K62: 7615.77 | L62: 7615.77 | M62: não | N62: confirmada | O62: Repasse ao cliente (3.2.07 REPASSE DE OUTRAS RECEITAS; 2.6.04 sem movimento no período) | P62: repasse | Q62: Repasse ao cliente | R62: Repasse ao cliente (3.2.07 REPASSE DE OUTRAS RECEITAS; 2.6.04 sem movimento no período) | S62: — | T62: — | U62: exclusão | V62: não avaliado | W62: confirmada | X62: sim | Z62: sem sinal | AC62: =IF(AA62="",M62,AA62) -> não | AD62: =IF(AB62="",X62,AB62) -> sim | AE62: =IF(OR(Configuracao!B9="",Configuracao!B10=""),"aguardando limiar",IF(AND(K62>=Configuracao!B9,K62/MAX(Reconciliacao!C2,1)>=Configuracao!B10/100),"sim","não")) -> aguardando limiar
A63: 11833 | C63: REPASSE PROC. 1061459-77.2023.8.26.0002 - DECORWATTS X SOBROSA | D63: Decorwatts Eletrica e Iluminacao Ltda | E63: Distressed Deals | F63: OUTRAS RECEITAS OPERACIONAIS | G63: REPASSE DE OUTRAS RECEITAS | H63: 3.2.07.000 | I63: 2026-01 | J63: 2026-01 | K63: 7670.57 | L63: 7670.57 | M63: não | N63: confirmada | O63: Repasse ao cliente (3.2.07 REPASSE DE OUTRAS RECEITAS; 2.6.04 sem movimento no período) | P63: repasse | Q63: Repasse ao cliente | R63: Repasse ao cliente (3.2.07 REPASSE DE OUTRAS RECEITAS; 2.6.04 sem movimento no período) | S63: — | T63: — | U63: exclusão | V63: não avaliado | W63: confirmada | X63: sim | Z63: sem sinal | AC63: =IF(AA63="",M63,AA63) -> não | AD63: =IF(AB63="",X63,AB63) -> sim | AE63: =IF(OR(Configuracao!B9="",Configuracao!B10=""),"aguardando limiar",IF(AND(K63>=Configuracao!B9,K63/MAX(Reconciliacao!C2,1)>=Configuracao!B10/100),"sim","não")) -> aguardando limiar
A64: 17355 | C64: REPASSE LIBERAÇÃO JUDICIAL PROC. 000306587020258160014REJANE COSTA - R$ 7.917,00EUNICE RENNA - R$ 16.000,00FATIMA SAMÕES - R$ 10.500,00FELIPE RODRIGUES - R$ 516,92FELIPE RODRIGUES - R$ 1.000,00LILIAN VIEIRA - R$ 2.000,00 | D64: Decorwatts Eletrica e Iluminacao Ltda | E64: Recuperação de Crédito | F64: OUTRAS RECEITAS OPERACIONAIS | G64: REPASSE DE OUTRAS RECEITAS | H64: 3.2.07.000 | I64: 2026-06 | J64: 2026-06 | K64: 7917 | L64: 7917 | M64: não | N64: confirmada | O64: Repasse ao cliente (3.2.07 REPASSE DE OUTRAS RECEITAS; 2.6.04 sem movimento no período) | P64: repasse | Q64: Repasse ao cliente | R64: Repasse ao cliente (3.2.07 REPASSE DE OUTRAS RECEITAS; 2.6.04 sem movimento no período) | S64: — | T64: — | U64: exclusão | V64: não avaliado | W64: confirmada | X64: sim | Z64: sem sinal | AC64: =IF(AA64="",M64,AA64) -> não | AD64: =IF(AB64="",X64,AB64) -> sim | AE64: =IF(OR(Configuracao!B9="",Configuracao!B10=""),"aguardando limiar",IF(AND(K64>=Configuracao!B9,K64/MAX(Reconciliacao!C2,1)>=Configuracao!B10/100),"sim","não")) -> aguardando limiar
A65: 18591 | C65: REPASSE PROC. 0011542-17.2025.5.15.0092 - PAULO X BRADESCO | D65: Paulo Joaquim da Silva Junior | E65: Trabalhista | F65: OUTRAS RECEITAS OPERACIONAIS | G65: REPASSE DE OUTRAS RECEITAS | H65: 3.2.07.000 | I65: 2026-08 | J65: 2026-08 | K65: 8061.71 | L65: 8061.71 | M65: não | N65: confirmada | O65: Repasse ao cliente (3.2.07 REPASSE DE OUTRAS RECEITAS; 2.6.04 sem movimento no período) | P65: repasse | Q65: Repasse ao cliente | R65: Repasse ao cliente (3.2.07 REPASSE DE OUTRAS RECEITAS; 2.6.04 sem movimento no período) | S65: — | T65: — | U65: exclusão | V65: não avaliado | W65: confirmada | X65: não | Y65: fornecedor sem outra ocorrência na conta em 12 meses | Z65: sugerido | AC65: =IF(AA65="",M65,AA65) -> não | AD65: =IF(AB65="",X65,AB65) -> não | AE65: =IF(OR(Configuracao!B9="",Configuracao!B10=""),"aguardando limiar",IF(AND(K65>=Configuracao!B9,K65/MAX(Reconciliacao!C2,1)>=Configuracao!B10/100),"sim","não")) -> aguardando limiar
A66: 18481 | C66: REPASSE LIBERAÇÃO JUDICIAL - PROC. 02520-91.2025.8.26.0248 | D66: Artevento Acoes Promocionais e Servicos Ltda | E66: Recuperação de Crédito | F66: OUTRAS RECEITAS OPERACIONAIS | G66: REPASSE DE OUTRAS RECEITAS | H66: 3.2.07.000 | I66: 2026-07 | J66: 2026-07 | K66: 8365.24 | L66: 8365.24 | M66: não | N66: confirmada | O66: Repasse ao cliente (3.2.07 REPASSE DE OUTRAS RECEITAS; 2.6.04 sem movimento no período) | P66: repasse | Q66: Repasse ao cliente | R66: Repasse ao cliente (3.2.07 REPASSE DE OUTRAS RECEITAS; 2.6.04 sem movimento no período) | S66: — | T66: — | U66: exclusão | V66: não avaliado | W66: confirmada | X66: não | Y66: fornecedor sem outra ocorrência na conta em 12 meses | Z66: sugerido | AC66: =IF(AA66="",M66,AA66) -> não | AD66: =IF(AB66="",X66,AB66) -> não | AE66: =IF(OR(Configuracao!B9="",Configuracao!B10=""),"aguardando limiar",IF(AND(K66>=Configuracao!B9,K66/MAX(Reconciliacao!C2,1)>=Configuracao!B10/100),"sim","não")) -> aguardando limiar
A67: 11377 | C67: REPASSE ACORDO ENCALSO | D67: Inovageo Geossinteticos Ltda | E67: Distressed Deals | F67: OUTRAS RECEITAS OPERACIONAIS | G67: REPASSE DE OUTRAS RECEITAS | H67: 3.2.07.000 | I67: 2026-01 | J67: 2026-01 | K67: 8645.97 | L67: 8645.97 | M67: não | N67: confirmada | O67: Repasse ao cliente (3.2.07 REPASSE DE OUTRAS RECEITAS; 2.6.04 sem movimento no período) | P67: repasse | Q67: Repasse ao cliente | R67: Repasse ao cliente (3.2.07 REPASSE DE OUTRAS RECEITAS; 2.6.04 sem movimento no período) | S67: — | T67: — | U67: exclusão | V67: não avaliado | W67: confirmada | X67: sim | Z67: sem sinal | AC67: =IF(AA67="",M67,AA67) -> não | AD67: =IF(AB67="",X67,AB67) -> sim | AE67: =IF(OR(Configuracao!B9="",Configuracao!B10=""),"aguardando limiar",IF(AND(K67>=Configuracao!B9,K67/MAX(Reconciliacao!C2,1)>=Configuracao!B10/100),"sim","não")) -> aguardando limiar
A68: 17356 | C68: REPASSE LIBERAÇÃO JUDICIAL PROC. 000306587020258160014REJANE COSTA - R$ 7.917,00EUNICE RENNA - R$ 16.000,00FATIMA SAMÕES - R$ 10.500,00FELIPE RODRIGUES - R$ 516,92FELIPE RODRIGUES - R$ 1.000,00LILIAN VIEIRA - R$ 2.000,00 | D68: Decorwatts Eletrica e Iluminacao Ltda | E68: Recuperação de Crédito | F68: OUTRAS RECEITAS OPERACIONAIS | G68: REPASSE DE OUTRAS RECEITAS | H68: 3.2.07.000 | I68: 2026-06 | J68: 2026-06 | K68: 10500 | L68: 10500 | M68: não | N68: confirmada | O68: Repasse ao cliente (3.2.07 REPASSE DE OUTRAS RECEITAS; 2.6.04 sem movimento no período) | P68: repasse | Q68: Repasse ao cliente | R68: Repasse ao cliente (3.2.07 REPASSE DE OUTRAS RECEITAS; 2.6.04 sem movimento no período) | S68: — | T68: — | U68: exclusão | V68: não avaliado | W68: confirmada | X68: sim | Z68: sem sinal | AC68: =IF(AA68="",M68,AA68) -> não | AD68: =IF(AB68="",X68,AB68) -> sim | AE68: =IF(OR(Configuracao!B9="",Configuracao!B10=""),"aguardando limiar",IF(AND(K68>=Configuracao!B9,K68/MAX(Reconciliacao!C2,1)>=Configuracao!B10/100),"sim","não")) -> aguardando limiar
A69: 14912 | C69: REPASSE ACORDO GS INDUSTRIAL | D69: Covolan Industria Textil Ltda Em Recuperacao Judicial | E69: Distressed Deals | F69: OUTRAS RECEITAS OPERACIONAIS | G69: REPASSE DE OUTRAS RECEITAS | H69: 3.2.07.000 | I69: 2026-03 | J69: 2026-03 | K69: 11250 | L69: 11250 | M69: não | N69: confirmada | O69: Repasse ao cliente (3.2.07 REPASSE DE OUTRAS RECEITAS; 2.6.04 sem movimento no período) | P69: repasse | Q69: Repasse ao cliente | R69: Repasse ao cliente (3.2.07 REPASSE DE OUTRAS RECEITAS; 2.6.04 sem movimento no período) | S69: — | T69: — | U69: exclusão | V69: não avaliado | W69: confirmada | X69: sim | Z69: sem sinal | AC69: =IF(AA69="",M69,AA69) -> não | AD69: =IF(AB69="",X69,AB69) -> sim | AE69: =IF(OR(Configuracao!B9="",Configuracao!B10=""),"aguardando limiar",IF(AND(K69>=Configuracao!B9,K69/MAX(Reconciliacao!C2,1)>=Configuracao!B10/100),"sim","não")) -> aguardando limiar
A70: 18575 | C70: GOLD LAND - SUGUITA | D70: Giancarlo Murta Zotini | E70: Cível | F70: OUTRAS RECEITAS OPERACIONAIS | G70: REPASSE DE OUTRAS RECEITAS | H70: 3.2.07.000 | I70: 2026-07 | J70: 2026-07 | K70: 11835.2 | L70: 11835.2 | M70: não | N70: confirmada | O70: Repasse ao cliente (3.2.07 REPASSE DE OUTRAS RECEITAS; 2.6.04 sem movimento no período) | P70: repasse | Q70: Repasse ao cliente | R70: Repasse ao cliente (3.2.07 REPASSE DE OUTRAS RECEITAS; 2.6.04 sem movimento no período) | S70: — | T70: — | U70: exclusão | V70: não avaliado | W70: confirmada | X70: sim | Z70: sem sinal | AC70: =IF(AA70="",M70,AA70) -> não | AD70: =IF(AB70="",X70,AB70) -> sim | AE70: =IF(OR(Configuracao!B9="",Configuracao!B10=""),"aguardando limiar",IF(AND(K70>=Configuracao!B9,K70/MAX(Reconciliacao!C2,1)>=Configuracao!B10/100),"sim","não")) -> aguardando limiar
A71: 18581 | C71: GOLD LAND - SUGUITA | D71: Giancarlo Murta Zotini | E71: Cível | F71: OUTRAS RECEITAS OPERACIONAIS | G71: REPASSE DE OUTRAS RECEITAS | H71: 3.2.07.000 | I71: 2026-07 | J71: 2026-07 | K71: 11840 | L71: 11840 | M71: não | N71: confirmada | O71: Repasse ao cliente (3.2.07 REPASSE DE OUTRAS RECEITAS; 2.6.04 sem movimento no período) | P71: repasse | Q71: Repasse ao cliente | R71: Repasse ao cliente (3.2.07 REPASSE DE OUTRAS RECEITAS; 2.6.04 sem movimento no período) | S71: — | T71: — | U71: exclusão | V71: não avaliado | W71: confirmada | X71: sim | Z71: sem sinal | AC71: =IF(AA71="",M71,AA71) -> não | AD71: =IF(AB71="",X71,AB71) -> sim | AE71: =IF(OR(Configuracao!B9="",Configuracao!B10=""),"aguardando limiar",IF(AND(K71>=Configuracao!B9,K71/MAX(Reconciliacao!C2,1)>=Configuracao!B10/100),"sim","não")) -> aguardando limiar
A72: 19343 | C72: GOLD LAND - SUGUITA | D72: Giancarlo Murta Zotini | E72: Cível | F72: OUTRAS RECEITAS OPERACIONAIS | G72: REPASSE DE OUTRAS RECEITAS | H72: 3.2.07.000 | I72: 2026-08 | J72: 2026-08 | K72: 11840 | L72: 11840 | M72: não | N72: confirmada | O72: Repasse ao cliente (3.2.07 REPASSE DE OUTRAS RECEITAS; 2.6.04 sem movimento no período) | P72: repasse | Q72: Repasse ao cliente | R72: Repasse ao cliente (3.2.07 REPASSE DE OUTRAS RECEITAS; 2.6.04 sem movimento no período) | S72: — | T72: — | U72: exclusão | V72: não avaliado | W72: confirmada | X72: sim | Z72: sem sinal | AC72: =IF(AA72="",M72,AA72) -> não | AD72: =IF(AB72="",X72,AB72) -> sim | AE72: =IF(OR(Configuracao!B9="",Configuracao!B10=""),"aguardando limiar",IF(AND(K72>=Configuracao!B9,K72/MAX(Reconciliacao!C2,1)>=Configuracao!B10/100),"sim","não")) -> aguardando limiar
A73: 11553 | C73: GOLD LAND - SUGUITA | D73: Giancarlo Murta Zotini | E73: Cível | F73: OUTRAS RECEITAS OPERACIONAIS | G73: REPASSE DE OUTRAS RECEITAS | H73: 3.2.07.000 | I73: 2026-01 | J73: 2026-01 | K73: 12000 | L73: 12000 | M73: não | N73: confirmada | O73: Repasse ao cliente (3.2.07 REPASSE DE OUTRAS RECEITAS; 2.6.04 sem movimento no período) | P73: repasse | Q73: Repasse ao cliente | R73: Repasse ao cliente (3.2.07 REPASSE DE OUTRAS RECEITAS; 2.6.04 sem movimento no período) | S73: — | T73: — | U73: exclusão | V73: não avaliado | W73: confirmada | X73: sim | Z73: sem sinal | AC73: =IF(AA73="",M73,AA73) -> não | AD73: =IF(AB73="",X73,AB73) -> sim | AE73: =IF(OR(Configuracao!B9="",Configuracao!B10=""),"aguardando limiar",IF(AND(K73>=Configuracao!B9,K73/MAX(Reconciliacao!C2,1)>=Configuracao!B10/100),"sim","não")) -> aguardando limiar
A74: 12320 | C74: GOLD LAND - SUGUITA | D74: Giancarlo Murta Zotini | E74: Cível | F74: OUTRAS RECEITAS OPERACIONAIS | G74: REPASSE DE OUTRAS RECEITAS | H74: 3.2.07.000 | I74: 2026-02 | J74: 2026-02 | K74: 12000 | L74: 12000 | M74: não | N74: confirmada | O74: Repasse ao cliente (3.2.07 REPASSE DE OUTRAS RECEITAS; 2.6.04 sem movimento no período) | P74: repasse | Q74: Repasse ao cliente | R74: Repasse ao cliente (3.2.07 REPASSE DE OUTRAS RECEITAS; 2.6.04 sem movimento no período) | S74: — | T74: — | U74: exclusão | V74: não avaliado | W74: confirmada | X74: sim | Z74: sem sinal | AC74: =IF(AA74="",M74,AA74) -> não | AD74: =IF(AB74="",X74,AB74) -> sim | AE74: =IF(OR(Configuracao!B9="",Configuracao!B10=""),"aguardando limiar",IF(AND(K74>=Configuracao!B9,K74/MAX(Reconciliacao!C2,1)>=Configuracao!B10/100),"sim","não")) -> aguardando limiar
A75: 12610 | C75: GOLD LAND - SUGUITA | D75: Giancarlo Murta Zotini | E75: Cível | F75: OUTRAS RECEITAS OPERACIONAIS | G75: REPASSE DE OUTRAS RECEITAS | H75: 3.2.07.000 | I75: 2026-03 | J75: 2026-03 | K75: 12000 | L75: 12000 | M75: não | N75: confirmada | O75: Repasse ao cliente (3.2.07 REPASSE DE OUTRAS RECEITAS; 2.6.04 sem movimento no período) | P75: repasse | Q75: Repasse ao cliente | R75: Repasse ao cliente (3.2.07 REPASSE DE OUTRAS RECEITAS; 2.6.04 sem movimento no período) | S75: — | T75: — | U75: exclusão | V75: não avaliado | W75: confirmada | X75: sim | Z75: sem sinal | AC75: =IF(AA75="",M75,AA75) -> não | AD75: =IF(AB75="",X75,AB75) -> sim | AE75: =IF(OR(Configuracao!B9="",Configuracao!B10=""),"aguardando limiar",IF(AND(K75>=Configuracao!B9,K75/MAX(Reconciliacao!C2,1)>=Configuracao!B10/100),"sim","não")) -> aguardando limiar
A76: 17314 | C76: GOLD LAND - SUGUITA | D76: Giancarlo Murta Zotini | E76: Cível | F76: OUTRAS RECEITAS OPERACIONAIS | G76: REPASSE DE OUTRAS RECEITAS | H76: 3.2.07.000 | I76: 2026-04 | J76: 2026-04 | K76: 12000 | L76: 12000 | M76: não | N76: confirmada | O76: Repasse ao cliente (3.2.07 REPASSE DE OUTRAS RECEITAS; 2.6.04 sem movimento no período) | P76: repasse | Q76: Repasse ao cliente | R76: Repasse ao cliente (3.2.07 REPASSE DE OUTRAS RECEITAS; 2.6.04 sem movimento no período) | S76: — | T76: — | U76: exclusão | V76: não avaliado | W76: confirmada | X76: sim | Z76: sem sinal | AC76: =IF(AA76="",M76,AA76) -> não | AD76: =IF(AB76="",X76,AB76) -> sim | AE76: =IF(OR(Configuracao!B9="",Configuracao!B10=""),"aguardando limiar",IF(AND(K76>=Configuracao!B9,K76/MAX(Reconciliacao!C2,1)>=Configuracao!B10/100),"sim","não")) -> aguardando limiar
A77: 17323 | C77: GOLD LAND - SUGUITA | D77: Giancarlo Murta Zotini | E77: Cível | F77: OUTRAS RECEITAS OPERACIONAIS | G77: REPASSE DE OUTRAS RECEITAS | H77: 3.2.07.000 | I77: 2026-05 | J77: 2026-05 | K77: 12000 | L77: 12000 | M77: não | N77: confirmada | O77: Repasse ao cliente (3.2.07 REPASSE DE OUTRAS RECEITAS; 2.6.04 sem movimento no período) | P77: repasse | Q77: Repasse ao cliente | R77: Repasse ao cliente (3.2.07 REPASSE DE OUTRAS RECEITAS; 2.6.04 sem movimento no período) | S77: — | T77: — | U77: exclusão | V77: não avaliado | W77: confirmada | X77: sim | Z77: sem sinal | AC77: =IF(AA77="",M77,AA77) -> não | AD77: =IF(AB77="",X77,AB77) -> sim | AE77: =IF(OR(Configuracao!B9="",Configuracao!B10=""),"aguardando limiar",IF(AND(K77>=Configuracao!B9,K77/MAX(Reconciliacao!C2,1)>=Configuracao!B10/100),"sim","não")) -> aguardando limiar
A78: 17791 | C78: GOLD LAND - SUGUITA | D78: Giancarlo Murta Zotini | E78: Cível | F78: OUTRAS RECEITAS OPERACIONAIS | G78: REPASSE DE OUTRAS RECEITAS | H78: 3.2.07.000 | I78: 2026-06 | J78: 2026-06 | K78: 12000 | L78: 12000 | M78: não | N78: confirmada | O78: Repasse ao cliente (3.2.07 REPASSE DE OUTRAS RECEITAS; 2.6.04 sem movimento no período) | P78: repasse | Q78: Repasse ao cliente | R78: Repasse ao cliente (3.2.07 REPASSE DE OUTRAS RECEITAS; 2.6.04 sem movimento no período) | S78: — | T78: — | U78: exclusão | V78: não avaliado | W78: confirmada | X78: sim | Z78: sem sinal | AC78: =IF(AA78="",M78,AA78) -> não | AD78: =IF(AB78="",X78,AB78) -> sim | AE78: =IF(OR(Configuracao!B9="",Configuracao!B10=""),"aguardando limiar",IF(AND(K78>=Configuracao!B9,K78/MAX(Reconciliacao!C2,1)>=Configuracao!B10/100),"sim","não")) -> aguardando limiar
A79: 17517 | C79: REPASSE LIBERAÇÃO JUDICIAL PROC. 000306587020258160014REJANE COSTA - R$ 7.917,00EUNICE RENNA - R$ 16.000,00FATIMA SAMÕES - R$ 10.500,00FELIPE RODRIGUES - R$ 516,92FELIPE RODRIGUES - R$ 1.000,00LILIAN VIEIRA - R$ 2.000,00 | D79: Decorwatts Eletrica e Iluminacao Ltda | E79: Recuperação de Crédito | F79: OUTRAS RECEITAS OPERACIONAIS | G79: REPASSE DE OUTRAS RECEITAS | H79: 3.2.07.000 | I79: 2026-06 | J79: 2026-06 | K79: 13060.56 | L79: 13060.56 | M79: não | N79: confirmada | O79: Repasse ao cliente (3.2.07 REPASSE DE OUTRAS RECEITAS; 2.6.04 sem movimento no período) | P79: repasse | Q79: Repasse ao cliente | R79: Repasse ao cliente (3.2.07 REPASSE DE OUTRAS RECEITAS; 2.6.04 sem movimento no período) | S79: — | T79: — | U79: exclusão | V79: não avaliado | W79: confirmada | X79: sim | Z79: sem sinal | AC79: =IF(AA79="",M79,AA79) -> não | AD79: =IF(AB79="",X79,AB79) -> sim | AE79: =IF(OR(Configuracao!B9="",Configuracao!B10=""),"aguardando limiar",IF(AND(K79>=Configuracao!B9,K79/MAX(Reconciliacao!C2,1)>=Configuracao!B10/100),"sim","não")) -> aguardando limiar
A80: 17172 | C80: REPASSE PROC. 1012237-27.2025.8.26.0114 - GPR X PROJETAR | D80: Gpr Fundo de Investimento Em Direitos Creditorios | E80: Recuperação de Crédito | F80: OUTRAS RECEITAS OPERACIONAIS | G80: REPASSE DE OUTRAS RECEITAS | H80: 3.2.07.000 | I80: 2026-06 | J80: 2026-06 | K80: 22041.31 | L80: 22041.31 | M80: não | N80: confirmada | O80: Repasse ao cliente (3.2.07 REPASSE DE OUTRAS RECEITAS; 2.6.04 sem movimento no período) | P80: repasse | Q80: Repasse ao cliente | R80: Repasse ao cliente (3.2.07 REPASSE DE OUTRAS RECEITAS; 2.6.04 sem movimento no período) | S80: — | T80: — | U80: exclusão | V80: não avaliado | W80: confirmada | X80: sim | Z80: sem sinal | AC80: =IF(AA80="",M80,AA80) -> não | AD80: =IF(AB80="",X80,AB80) -> sim | AE80: =IF(OR(Configuracao!B9="",Configuracao!B10=""),"aguardando limiar",IF(AND(K80>=Configuracao!B9,K80/MAX(Reconciliacao!C2,1)>=Configuracao!B10/100),"sim","não")) -> aguardando limiar
A81: 15855 | C81: REPASSE OKNO CAPITAL | D81: Michel Donizeti de Medeiros Malaquias | E81: Conta Corrente Clientes | F81: OUTRAS RECEITAS OPERACIONAIS | G81: REPASSE DE OUTRAS RECEITAS | H81: 3.2.07.000 | I81: 2026-04 | J81: 2026-04 | K81: 31960 | L81: 31960 | M81: não | N81: confirmada | O81: Despesas reembolsáveis de clientes | P81: departamento_conta_corrente_clientes | Q81: Despesas reembolsáveis de clientes | R81: Despesas reembolsáveis de clientes | S81: — | T81: — | U81: exclusão | V81: não avaliado | W81: confirmada | X81: não | Y81: fornecedor sem outra ocorrência na conta em 12 meses; valor atípico (acima de 3x a mediana da conta em 12 meses, mediana 8365.24) | Z81: sugerido | AC81: =IF(AA81="",M81,AA81) -> não | AD81: =IF(AB81="",X81,AB81) -> não | AE81: =IF(OR(Configuracao!B9="",Configuracao!B10=""),"aguardando limiar",IF(AND(K81>=Configuracao!B9,K81/MAX(Reconciliacao!C2,1)>=Configuracao!B10/100),"sim","não")) -> aguardando limiar
A82: 17994 | C82: REPASSE LIBERAÇÃO JUDICIAL PROC. 4011523-40.2026.8.26.0224 | D82: Gpr Fundo de Investimento Em Direitos Creditorios | E82: Recuperação de Crédito | F82: OUTRAS RECEITAS OPERACIONAIS | G82: REPASSE DE OUTRAS RECEITAS | H82: 3.2.07.000 | I82: 2026-07 | J82: 2026-07 | K82: 46790.12 | L82: 46790.12 | M82: não | N82: confirmada | O82: Repasse ao cliente (3.2.07 REPASSE DE OUTRAS RECEITAS; 2.6.04 sem movimento no período) | P82: repasse | Q82: Repasse ao cliente | R82: Repasse ao cliente (3.2.07 REPASSE DE OUTRAS RECEITAS; 2.6.04 sem movimento no período) | S82: — | T82: — | U82: exclusão | V82: não avaliado | W82: confirmada | X82: não | Y82: valor atípico (acima de 3x a mediana da conta em 12 meses, mediana 8365.24) | Z82: sugerido | AC82: =IF(AA82="",M82,AA82) -> não | AD82: =IF(AB82="",X82,AB82) -> não | AE82: =IF(OR(Configuracao!B9="",Configuracao!B10=""),"aguardando limiar",IF(AND(K82>=Configuracao!B9,K82/MAX(Reconciliacao!C2,1)>=Configuracao!B10/100),"sim","não")) -> aguardando limiar
A83: 16664 | C83: REPASSE ACORDO ECOBULK | D83: Inovageo Geossinteticos Ltda | E83: Recuperação de Crédito | F83: OUTRAS RECEITAS OPERACIONAIS | G83: REPASSE DE OUTRAS RECEITAS | H83: 3.2.07.000 | I83: 2026-05 | J83: 2026-05 | K83: 91298.03 | L83: 91298.03 | M83: não | N83: confirmada | O83: Repasse ao cliente (3.2.07 REPASSE DE OUTRAS RECEITAS; 2.6.04 sem movimento no período) | P83: repasse | Q83: Repasse ao cliente | R83: Repasse ao cliente (3.2.07 REPASSE DE OUTRAS RECEITAS; 2.6.04 sem movimento no período) | S83: — | T83: — | U83: exclusão | V83: não avaliado | W83: confirmada | X83: não | Y83: valor atípico (acima de 3x a mediana da conta em 12 meses, mediana 8365.24) | Z83: sugerido | AC83: =IF(AA83="",M83,AA83) -> não | AD83: =IF(AB83="",X83,AB83) -> não | AE83: =IF(OR(Configuracao!B9="",Configuracao!B10=""),"aguardando limiar",IF(AND(K83>=Configuracao!B9,K83/MAX(Reconciliacao!C2,1)>=Configuracao!B10/100),"sim","não")) -> aguardando limiar
A84: 17549 | C84: REPASSE ACORDO ECOBULK | D84: Inovageo Geossinteticos Ltda | E84: Recuperação de Crédito | F84: OUTRAS RECEITAS OPERACIONAIS | G84: REPASSE DE OUTRAS RECEITAS | H84: 3.2.07.000 | I84: 2026-06 | J84: 2026-06 | K84: 91298.03 | L84: 91298.03 | M84: não | N84: confirmada | O84: Repasse ao cliente (3.2.07 REPASSE DE OUTRAS RECEITAS; 2.6.04 sem movimento no período) | P84: repasse | Q84: Repasse ao cliente | R84: Repasse ao cliente (3.2.07 REPASSE DE OUTRAS RECEITAS; 2.6.04 sem movimento no período) | S84: — | T84: — | U84: exclusão | V84: não avaliado | W84: confirmada | X84: não | Y84: valor atípico (acima de 3x a mediana da conta em 12 meses, mediana 8365.24) | Z84: sugerido | AC84: =IF(AA84="",M84,AA84) -> não | AD84: =IF(AB84="",X84,AB84) -> não | AE84: =IF(OR(Configuracao!B9="",Configuracao!B10=""),"aguardando limiar",IF(AND(K84>=Configuracao!B9,K84/MAX(Reconciliacao!C2,1)>=Configuracao!B10/100),"sim","não")) -> aguardando limiar
A85: 18178 | C85: REPASSE ACORDO ECOBULK | D85: Inovageo Geossinteticos Ltda | E85: Recuperação de Crédito | F85: OUTRAS RECEITAS OPERACIONAIS | G85: REPASSE DE OUTRAS RECEITAS | H85: 3.2.07.000 | I85: 2026-07 | J85: 2026-07 | K85: 91298.03 | L85: 91298.03 | M85: não | N85: confirmada | O85: Repasse ao cliente (3.2.07 REPASSE DE OUTRAS RECEITAS; 2.6.04 sem movimento no período) | P85: repasse | Q85: Repasse ao cliente | R85: Repasse ao cliente (3.2.07 REPASSE DE OUTRAS RECEITAS; 2.6.04 sem movimento no período) | S85: — | T85: — | U85: exclusão | V85: não avaliado | W85: confirmada | X85: não | Y85: valor atípico (acima de 3x a mediana da conta em 12 meses, mediana 8365.24) | Z85: sugerido | AC85: =IF(AA85="",M85,AA85) -> não | AD85: =IF(AB85="",X85,AB85) -> não | AE85: =IF(OR(Configuracao!B9="",Configuracao!B10=""),"aguardando limiar",IF(AND(K85>=Configuracao!B9,K85/MAX(Reconciliacao!C2,1)>=Configuracao!B10/100),"sim","não")) -> aguardando limiar
A86: 18901 | C86: REPASSE ACORDO CONSORCIO CRA | D86: Inovageo Geossinteticos Ltda | E86: Recuperação de Crédito | F86: OUTRAS RECEITAS OPERACIONAIS | G86: REPASSE DE OUTRAS RECEITAS | H86: 3.2.07.000 | I86: 2026-08 | J86: 2026-08 | K86: 98445.9 | L86: 98445.9 | M86: não | N86: confirmada | O86: Repasse ao cliente (3.2.07 REPASSE DE OUTRAS RECEITAS; 2.6.04 sem movimento no período) | P86: repasse | Q86: Repasse ao cliente | R86: Repasse ao cliente (3.2.07 REPASSE DE OUTRAS RECEITAS; 2.6.04 sem movimento no período) | S86: — | T86: — | U86: exclusão | V86: não avaliado | W86: confirmada | X86: não | Y86: valor atípico (acima de 3x a mediana da conta em 12 meses, mediana 8365.24) | Z86: sugerido | AC86: =IF(AA86="",M86,AA86) -> não | AD86: =IF(AB86="",X86,AB86) -> não | AE86: =IF(OR(Configuracao!B9="",Configuracao!B10=""),"aguardando limiar",IF(AND(K86>=Configuracao!B9,K86/MAX(Reconciliacao!C2,1)>=Configuracao!B10/100),"sim","não")) -> aguardando limiar
A87: 16481 | C87: REPASSE ACORDO ECOBULK | D87: Inovageo Geossinteticos Ltda | E87: Recuperação de Crédito | F87: OUTRAS RECEITAS OPERACIONAIS | G87: REPASSE DE OUTRAS RECEITAS | H87: 3.2.07.000 | I87: 2026-04 | J87: 2026-04 | K87: 167400 | L87: 167400 | M87: não | N87: confirmada | O87: Repasse ao cliente (3.2.07 REPASSE DE OUTRAS RECEITAS; 2.6.04 sem movimento no período) | P87: repasse | Q87: Repasse ao cliente | R87: Repasse ao cliente (3.2.07 REPASSE DE OUTRAS RECEITAS; 2.6.04 sem movimento no período) | S87: — | T87: — | U87: exclusão | V87: não avaliado | W87: confirmada | X87: não | Y87: valor atípico (acima de 3x a mediana da conta em 12 meses, mediana 8365.24) | Z87: sugerido | AC87: =IF(AA87="",M87,AA87) -> não | AD87: =IF(AB87="",X87,AB87) -> não | AE87: =IF(OR(Configuracao!B9="",Configuracao!B10=""),"aguardando limiar",IF(AND(K87>=Configuracao!B9,K87/MAX(Reconciliacao!C2,1)>=Configuracao!B10/100),"sim","não")) -> aguardando limiar
A88: 14888 | C88: REPASSE PROC. 00006294220248260451 | D88: Pst Eletronica Ltda | E88: Conta Corrente Clientes | F88: OUTRAS RECEITAS OPERACIONAIS | G88: REPASSE DE OUTRAS RECEITAS | H88: 3.2.07.000 | I88: 2026-03 | J88: 2026-03 | K88: 200754.8 | L88: 200754.8 | M88: não | N88: confirmada | O88: Despesas reembolsáveis de clientes | P88: departamento_conta_corrente_clientes | Q88: Despesas reembolsáveis de clientes | R88: Despesas reembolsáveis de clientes | S88: — | T88: — | U88: exclusão | V88: não avaliado | W88: confirmada | X88: não | Y88: valor atípico (acima de 3x a mediana da conta em 12 meses, mediana 8365.24) | Z88: sugerido | AC88: =IF(AA88="",M88,AA88) -> não | AD88: =IF(AB88="",X88,AB88) -> não | AE88: =IF(OR(Configuracao!B9="",Configuracao!B10=""),"aguardando limiar",IF(AND(K88>=Configuracao!B9,K88/MAX(Reconciliacao!C2,1)>=Configuracao!B10/100),"sim","não")) -> aguardando limiar
A89: 6930 | D89: MUNICIPIO DE CAMPINAS | E89: Facilities | F89: IMPOSTOS SOBRE SERVIÇOS | G89: IMPOSTOS SOBRE SERVIÇOS - ISS | H89: 3.3.01.000 | I89: 2026-03 | J89: 2026-03 | K89: 9.59 | L89: 9.59 | M89: não | N89: confirmada | O89: Deduções / tributos sobre faturamento | P89: composicao_pendente | Q89: Deduções / tributos sobre faturamento | R89: Deduções / tributos sobre faturamento | S89: — | T89: — | U89: exclusão | V89: não avaliado | W89: confirmada | X89: sim | Z89: sem sinal | AC89: =IF(AA89="",M89,AA89) -> não | AD89: =IF(AB89="",X89,AB89) -> sim | AE89: =IF(OR(Configuracao!B9="",Configuracao!B10=""),"aguardando limiar",IF(AND(K89>=Configuracao!B9,K89/MAX(Reconciliacao!C2,1)>=Configuracao!B10/100),"sim","não")) -> aguardando limiar
A90: 6931 | D90: MUNICIPIO DE CAMPINAS | E90: Facilities | F90: IMPOSTOS SOBRE SERVIÇOS | G90: IMPOSTOS SOBRE SERVIÇOS - ISS | H90: 3.3.01.000 | I90: 2026-04 | J90: 2026-04 | K90: 9.59 | L90: 9.59 | M90: não | N90: confirmada | O90: Deduções / tributos sobre faturamento | P90: composicao_pendente | Q90: Deduções / tributos sobre faturamento | R90: Deduções / tributos sobre faturamento | S90: — | T90: — | U90: exclusão | V90: não avaliado | W90: confirmada | X90: sim | Z90: sem sinal | AC90: =IF(AA90="",M90,AA90) -> não | AD90: =IF(AB90="",X90,AB90) -> sim | AE90: =IF(OR(Configuracao!B9="",Configuracao!B10=""),"aguardando limiar",IF(AND(K90>=Configuracao!B9,K90/MAX(Reconciliacao!C2,1)>=Configuracao!B10/100),"sim","não")) -> aguardando limiar
A91: 6932 | D91: MUNICIPIO DE CAMPINAS | E91: Facilities | F91: IMPOSTOS SOBRE SERVIÇOS | G91: IMPOSTOS SOBRE SERVIÇOS - ISS | H91: 3.3.01.000 | I91: 2026-05 | J91: 2026-05 | K91: 9.59 | L91: 9.59 | M91: não | N91: confirmada | O91: Deduções / tributos sobre faturamento | P91: composicao_pendente | Q91: Deduções / tributos sobre faturamento | R91: Deduções / tributos sobre faturamento | S91: — | T91: — | U91: exclusão | V91: não avaliado | W91: confirmada | X91: sim | Z91: sem sinal | AC91: =IF(AA91="",M91,AA91) -> não | AD91: =IF(AB91="",X91,AB91) -> sim | AE91: =IF(OR(Configuracao!B9="",Configuracao!B10=""),"aguardando limiar",IF(AND(K91>=Configuracao!B9,K91/MAX(Reconciliacao!C2,1)>=Configuracao!B10/100),"sim","não")) -> aguardando limiar
A92: 6935 | D92: MUNICIPIO DE CAMPINAS | E92: Facilities | F92: IMPOSTOS SOBRE SERVIÇOS | G92: IMPOSTOS SOBRE SERVIÇOS - ISS | H92: 3.3.01.000 | I92: 2026-08 | J92: 2026-08 | K92: 9.59 | L92: 9.59 | M92: não | N92: confirmada | O92: Deduções / tributos sobre faturamento | P92: composicao_pendente | Q92: Deduções / tributos sobre faturamento | R92: Deduções / tributos sobre faturamento | S92: — | T92: — | U92: exclusão | V92: não avaliado | W92: confirmada | X92: sim | Z92: sem sinal | AC92: =IF(AA92="",M92,AA92) -> não | AD92: =IF(AB92="",X92,AB92) -> sim | AE92: =IF(OR(Configuracao!B9="",Configuracao!B10=""),"aguardando limiar",IF(AND(K92>=Configuracao!B9,K92/MAX(Reconciliacao!C2,1)>=Configuracao!B10/100),"sim","não")) -> aguardando limiar
A93: 6933 | D93: MUNICIPIO DE CAMPINAS | E93: Facilities | F93: IMPOSTOS SOBRE SERVIÇOS | G93: IMPOSTOS SOBRE SERVIÇOS - ISS | H93: 3.3.01.000 | I93: 2026-06 | J93: 2026-06 | K93: 28.12 | L93: 28.12 | M93: não | N93: confirmada | O93: Deduções / tributos sobre faturamento | P93: composicao_pendente | Q93: Deduções / tributos sobre faturamento | R93: Deduções / tributos sobre faturamento | S93: — | T93: — | U93: exclusão | V93: não avaliado | W93: confirmada | X93: sim | Z93: sem sinal | AC93: =IF(AA93="",M93,AA93) -> não | AD93: =IF(AB93="",X93,AB93) -> sim | AE93: =IF(OR(Configuracao!B9="",Configuracao!B10=""),"aguardando limiar",IF(AND(K93>=Configuracao!B9,K93/MAX(Reconciliacao!C2,1)>=Configuracao!B10/100),"sim","não")) -> aguardando limiar
A94: 6928 | D94: MUNICIPIO DE CAMPINAS | E94: Facilities | F94: IMPOSTOS SOBRE SERVIÇOS | G94: IMPOSTOS SOBRE SERVIÇOS - ISS | H94: 3.3.01.000 | I94: 2026-01 | J94: 2026-01 | K94: 31.7 | L94: 31.7 | M94: não | N94: confirmada | O94: Deduções / tributos sobre faturamento | P94: composicao_pendente | Q94: Deduções / tributos sobre faturamento | R94: Deduções / tributos sobre faturamento | S94: — | T94: — | U94: exclusão | V94: não avaliado | W94: confirmada | X94: sim | Z94: sem sinal | AC94: =IF(AA94="",M94,AA94) -> não | AD94: =IF(AB94="",X94,AB94) -> sim | AE94: =IF(OR(Configuracao!B9="",Configuracao!B10=""),"aguardando limiar",IF(AND(K94>=Configuracao!B9,K94/MAX(Reconciliacao!C2,1)>=Configuracao!B10/100),"sim","não")) -> aguardando limiar
A95: 6929 | D95: MUNICIPIO DE CAMPINAS | E95: Facilities | F95: IMPOSTOS SOBRE SERVIÇOS | G95: IMPOSTOS SOBRE SERVIÇOS - ISS | H95: 3.3.01.000 | I95: 2026-02 | J95: 2026-02 | K95: 37.25 | L95: 37.25 | M95: não | N95: confirmada | O95: Deduções / tributos sobre faturamento | P95: composicao_pendente | Q95: Deduções / tributos sobre faturamento | R95: Deduções / tributos sobre faturamento | S95: — | T95: — | U95: exclusão | V95: não avaliado | W95: confirmada | X95: sim | Z95: sem sinal | AC95: =IF(AA95="",M95,AA95) -> não | AD95: =IF(AB95="",X95,AB95) -> sim | AE95: =IF(OR(Configuracao!B9="",Configuracao!B10=""),"aguardando limiar",IF(AND(K95>=Configuracao!B9,K95/MAX(Reconciliacao!C2,1)>=Configuracao!B10/100),"sim","não")) -> aguardando limiar
A96: 6934 | D96: MUNICIPIO DE CAMPINAS | E96: Facilities | F96: IMPOSTOS SOBRE SERVIÇOS | G96: IMPOSTOS SOBRE SERVIÇOS - ISS | H96: 3.3.01.000 | I96: 2026-07 | J96: 2026-07 | K96: 73.7 | L96: 73.7 | M96: não | N96: confirmada | O96: Deduções / tributos sobre faturamento | P96: composicao_pendente | Q96: Deduções / tributos sobre faturamento | R96: Deduções / tributos sobre faturamento | S96: — | T96: — | U96: exclusão | V96: não avaliado | W96: confirmada | X96: sim | Z96: sem sinal | AC96: =IF(AA96="",M96,AA96) -> não | AD96: =IF(AB96="",X96,AB96) -> sim | AE96: =IF(OR(Configuracao!B9="",Configuracao!B10=""),"aguardando limiar",IF(AND(K96>=Configuracao!B9,K96/MAX(Reconciliacao!C2,1)>=Configuracao!B10/100),"sim","não")) -> aguardando limiar
A97: 17737 | C97: DEVOLUÇÃO HONORÁRIOS DE MANUTENÇÃO PAGOS INDEVIDAMENTE | D97: Edital Agenciamento de Transportes Ltda | E97: Contratos | F97: DEDUÇÕES DA RECEITA | G97: DEVOLUÇãO HONORÁRIOS / DESPESAS | H97: 3.4.01.000 | I97: 2026-07 | J97: 2026-07 | K97: 2000 | L97: 2000 | M97: não | N97: confirmada | O97: Dedução da receita | Q97: Deduções da receita | R97: Dedução da receita | S97: — | T97: — | U97: exclusão | V97: não avaliado | W97: confirmada | X97: não | Y97: fornecedor sem outra ocorrência na conta em 12 meses | Z97: sugerido | AC97: =IF(AA97="",M97,AA97) -> não | AD97: =IF(AB97="",X97,AB97) -> não | AE97: =IF(OR(Configuracao!B9="",Configuracao!B10=""),"aguardando limiar",IF(AND(K97>=Configuracao!B9,K97/MAX(Reconciliacao!C2,1)>=Configuracao!B10/100),"sim","não")) -> aguardando limiar
A98: 16484 | C98: COMISSÃO FELICITA - R$ 159,80 | D98: P2 Mr Adm (Pivato) | E98: Trabalhista | F98: COMISSÕES SOBRE VENDAS | G98: COMISSÕES PARCEIROS | H98: 4.1.01.000 | I98: 2026-04 | J98: 2026-04 | K98: 7.94 | L98: 7.94 | M98: sim | N98: confirmada | Q98: Comissões | R98: Comissões | S98: variável | T98: decisão interna | U98: despesa | V98: médio | W98: confirmada | X98: sim | Z98: sem sinal | AC98: =IF(AA98="",M98,AA98) -> sim | AD98: =IF(AB98="",X98,AB98) -> sim | AE98: =IF(OR(Configuracao!B9="",Configuracao!B10=""),"aguardando limiar",IF(AND(K98>=Configuracao!B9,K98/MAX(Reconciliacao!C2,1)>=Configuracao!B10/100),"sim","não")) -> aguardando limiar
A99: 14175 | C99: COMISSÃO FELICITA - R$ 167,00 | D99: P2 Mr Adm (Pivato) | E99: Trabalhista | F99: COMISSÕES SOBRE VENDAS | G99: COMISSÕES PARCEIROS | H99: 4.1.01.000 | I99: 2026-04 | J99: 2026-04 | K99: 8.35 | L99: 8.35 | M99: sim | N99: confirmada | Q99: Comissões | R99: Comissões | S99: variável | T99: decisão interna | U99: despesa | V99: médio | W99: confirmada | X99: sim | Z99: sem sinal | AC99: =IF(AA99="",M99,AA99) -> sim | AD99: =IF(AB99="",X99,AB99) -> sim | AE99: =IF(OR(Configuracao!B9="",Configuracao!B10=""),"aguardando limiar",IF(AND(K99>=Configuracao!B9,K99/MAX(Reconciliacao!C2,1)>=Configuracao!B10/100),"sim","não")) -> aguardando limiar
A100: 12766 | C100: COMISSÃO FELICITA | D100: P2 Mr Adm (Pivato) | E100: Trabalhista | F100: COMISSÕES SOBRE VENDAS | G100: COMISSÕES PARCEIROS | H100: 4.1.01.000 | I100: 2026-03 | J100: 2026-03 | K100: 12.52 | L100: 12.52 | M100: sim | N100: confirmada | Q100: Comissões | R100: Comissões | S100: variável | T100: decisão interna | U100: despesa | V100: médio | W100: confirmada | X100: sim | Z100: sem sinal | AC100: =IF(AA100="",M100,AA100) -> sim | AD100: =IF(AB100="",X100,AB100) -> sim | AE100: =IF(OR(Configuracao!B9="",Configuracao!B10=""),"aguardando limiar",IF(AND(K100>=Configuracao!B9,K100/MAX(Reconciliacao!C2,1)>=Configuracao!B10/100),"sim","não")) -> aguardando limiar
...

Sheet Reconciliacao
A1: mes | B1: regime | C1: total_saidas | D1: opex | E1: excluidos | F1: opex_mais_excluidos | G1: diferenca | H1: bate
A2: 2026-01 a 2026-08 | B2: competencia_total_opex | C2: 4438396.8
A3: 2026-01 | B3: competencia | C3: =SUMIFS(Lancamentos!K$2:K$3028,Lancamentos!I$2:I$3028,A3) -> 652200.32 | D3: =SUMIFS(Lancamentos!K$2:K$3028,Lancamentos!I$2:I$3028,A3,Lancamentos!AC$2:AC$3028,"sim") -> 320693.36 | E3: =C3-D3 -> 331506.96 | F3: =D3+E3 -> 652200.32 | G3: =F3-C3 -> 0 | H3: =IF(ABS(G3)<0.05,"sim","não") -> sim
A4: 2026-01 | B4: caixa | C4: =SUMIFS(Lancamentos!L$2:L$3028,Lancamentos!J$2:J$3028,A4) -> 938756.48 | D4: =SUMIFS(Lancamentos!L$2:L$3028,Lancamentos!J$2:J$3028,A4,Lancamentos!AC$2:AC$3028,"sim") -> 585282.33 | E4: =C4-D4 -> 353474.15 | F4: =D4+E4 -> 938756.48 | G4: =F4-C4 -> 0 | H4: =IF(ABS(G4)<0.05,"sim","não") -> sim
A5: 2026-02 | B5: competencia | C5: =SUMIFS(Lancamentos!K$2:K$3028,Lancamentos!I$2:I$3028,A5) -> 1163641.2 | D5: =SUMIFS(Lancamentos!K$2:K$3028,Lancamentos!I$2:I$3028,A5,Lancamentos!AC$2:AC$3028,"sim") -> 810278.94 | E5: =C5-D5 -> 353362.31 | F5: =D5+E5 -> 1163641.2 | G5: =F5-C5 -> 0 | H5: =IF(ABS(G5)<0.05,"sim","não") -> sim
A6: 2026-02 | B6: caixa | C6: =SUMIFS(Lancamentos!L$2:L$3028,Lancamentos!J$2:J$3028,A6) -> 862622.25 | D6: =SUMIFS(Lancamentos!L$2:L$3028,Lancamentos!J$2:J$3028,A6,Lancamentos!AC$2:AC$3028,"sim") -> 509697.87 | E6: =C6-D6 -> 352924.38 | F6: =D6+E6 -> 862622.25 | G6: =F6-C6 -> 0 | H6: =IF(ABS(G6)<0.05,"sim","não") -> sim
A7: 2026-03 | B7: competencia | C7: =SUMIFS(Lancamentos!K$2:K$3028,Lancamentos!I$2:I$3028,A7) -> 1243292.8 | D7: =SUMIFS(Lancamentos!K$2:K$3028,Lancamentos!I$2:I$3028,A7,Lancamentos!AC$2:AC$3028,"sim") -> 610109.78 | E7: =C7-D7 -> 633183 | F7: =D7+E7 -> 1243292.8 | G7: =F7-C7 -> 0 | H7: =IF(ABS(G7)<0.05,"sim","não") -> sim
A8: 2026-03 | B8: caixa | C8: =SUMIFS(Lancamentos!L$2:L$3028,Lancamentos!J$2:J$3028,A8) -> 1201756.6 | D8: =SUMIFS(Lancamentos!L$2:L$3028,Lancamentos!J$2:J$3028,A8,Lancamentos!AC$2:AC$3028,"sim") -> 568135.69 | E8: =C8-D8 -> 633620.93 | F8: =D8+E8 -> 1201756.6 | G8: =F8-C8 -> 0 | H8: =IF(ABS(G8)<0.05,"sim","não") -> sim
A9: 2026-04 | B9: competencia | C9: =SUMIFS(Lancamentos!K$2:K$3028,Lancamentos!I$2:I$3028,A9) -> 1281104.5 | D9: =SUMIFS(Lancamentos!K$2:K$3028,Lancamentos!I$2:I$3028,A9,Lancamentos!AC$2:AC$3028,"sim") -> 598072.55 | E9: =C9-D9 -> 683031.97 | F9: =D9+E9 -> 1281104.5 | G9: =F9-C9 -> 0 | H9: =IF(ABS(G9)<0.05,"sim","não") -> sim
A10: 2026-04 | B10: caixa | C10: =SUMIFS(Lancamentos!L$2:L$3028,Lancamentos!J$2:J$3028,A10) -> 1280718.1 | D10: =SUMIFS(Lancamentos!L$2:L$3028,Lancamentos!J$2:J$3028,A10,Lancamentos!AC$2:AC$3028,"sim") -> 597686.18 | E10: =C10-D10 -> 683031.97 | F10: =D10+E10 -> 1280718.1 | G10: =F10-C10 -> 0 | H10: =IF(ABS(G10)<0.05,"sim","não") -> sim
A11: 2026-05 | B11: competencia | C11: =SUMIFS(Lancamentos!K$2:K$3028,Lancamentos!I$2:I$3028,A11) -> 1181725.4 | D11: =SUMIFS(Lancamentos!K$2:K$3028,Lancamentos!I$2:I$3028,A11,Lancamentos!AC$2:AC$3028,"sim") -> 592766.37 | E11: =C11-D11 -> 588959 | F11: =D11+E11 -> 1181725.4 | G11: =F11-C11 -> 0 | H11: =IF(ABS(G11)<0.05,"sim","não") -> sim
A12: 2026-05 | B12: caixa | C12: =SUMIFS(Lancamentos!L$2:L$3028,Lancamentos!J$2:J$3028,A12) -> 1170175.3 | D12: =SUMIFS(Lancamentos!L$2:L$3028,Lancamentos!J$2:J$3028,A12,Lancamentos!AC$2:AC$3028,"sim") -> 581216.3 | E12: =C12-D12 -> 588959 | F12: =D12+E12 -> 1170175.3 | G12: =F12-C12 -> 0 | H12: =IF(ABS(G12)<0.05,"sim","não") -> sim
A13: 2026-06 | B13: competencia | C13: =SUMIFS(Lancamentos!K$2:K$3028,Lancamentos!I$2:I$3028,A13) -> 1206702.6 | D13: =SUMIFS(Lancamentos!K$2:K$3028,Lancamentos!I$2:I$3028,A13,Lancamentos!AC$2:AC$3028,"sim") -> 594221.63 | E13: =C13-D13 -> 612480.92 | F13: =D13+E13 -> 1206702.6 | G13: =F13-C13 -> 0 | H13: =IF(ABS(G13)<0.05,"sim","não") -> sim
A14: 2026-06 | B14: caixa | C14: =SUMIFS(Lancamentos!L$2:L$3028,Lancamentos!J$2:J$3028,A14) -> 1215671.9 | D14: =SUMIFS(Lancamentos!L$2:L$3028,Lancamentos!J$2:J$3028,A14,Lancamentos!AC$2:AC$3028,"sim") -> 598643.97 | E14: =C14-D14 -> 617027.96 | F14: =D14+E14 -> 1215671.9 | G14: =F14-C14 -> 0 | H14: =IF(ABS(G14)<0.05,"sim","não") -> sim
A15: 2026-07 | B15: competencia | C15: =SUMIFS(Lancamentos!K$2:K$3028,Lancamentos!I$2:I$3028,A15) -> 1269958.4 | D15: =SUMIFS(Lancamentos!K$2:K$3028,Lancamentos!I$2:I$3028,A15,Lancamentos!AC$2:AC$3028,"sim") -> 610906.05 | E15: =C15-D15 -> 659052.37 | F15: =D15+E15 -> 1269958.4 | G15: =F15-C15 -> 0 | H15: =IF(ABS(G15)<0.05,"sim","não") -> sim
A16: 2026-07 | B16: caixa | C16: =SUMIFS(Lancamentos!L$2:L$3028,Lancamentos!J$2:J$3028,A16) -> 1267063.9 | D16: =SUMIFS(Lancamentos!L$2:L$3028,Lancamentos!J$2:J$3028,A16,Lancamentos!AC$2:AC$3028,"sim") -> 612228.57 | E16: =C16-D16 -> 654835.38 | F16: =D16+E16 -> 1267063.9 | G16: =F16-C16 -> 0 | H16: =IF(ABS(G16)<0.05,"sim","não") -> sim
A17: 2026-08 | B17: competencia | C17: =SUMIFS(Lancamentos!K$2:K$3028,Lancamentos!I$2:I$3028,A17) -> 921776.25 | D17: =SUMIFS(Lancamentos!K$2:K$3028,Lancamentos!I$2:I$3028,A17,Lancamentos!AC$2:AC$3028,"sim") -> 301348.09 | E17: =C17-D17 -> 620428.16 | F17: =D17+E17 -> 921776.25 | G17: =F17-C17 -> 0 | H17: =IF(ABS(G17)<0.05,"sim","não") -> sim
A18: 2026-08 | B18: caixa | C18: =SUMIFS(Lancamentos!L$2:L$3028,Lancamentos!J$2:J$3028,A18) -> 1253629.5 | D18: =SUMIFS(Lancamentos!L$2:L$3028,Lancamentos!J$2:J$3028,A18,Lancamentos!AC$2:AC$3028,"sim") -> 633474.23 | E18: =C18-D18 -> 620155.24 | F18: =D18+E18 -> 1253629.5 | G18: =F18-C18 -> 0 | H18: =IF(ABS(G18)<0.05,"sim","não") -> sim

Sheet Excluidos_por_motivo
A1: motivo | B1: valor_competencia | C1: pct_das_saidas
A2: Remuneração de sócios de capital | B2: 2768959.5 | C2: 0.3104075
A3: Repasse ao cliente (3.2.07 REPASSE DE OUTRAS RECEITAS; 2.6.04 sem movimento no período) | B3: 835346.5 | C3: 0.093644496
A4: Deduções / tributos sobre faturamento | B4: 543223.31 | C4: 0.060896733
A5: Despesas reembolsáveis de clientes | B5: 315147.79 | C5: 0.03532888
A6: Investimento / CAPEX | B6: 9727.61 | C6: 0.0010904902
A7: Adiantamento ou transferência (não é despesa operacional) | B7: 7600 | C7: 0.00085197959
A8: Dedução da receita | B8: 2000 | C8: 0.00022420516
A9: TOTAL EXCLUÍDO | B9: 4482004.7 | C9: 0.50244428
A10: OPEX | B10: 4438396.8 | C10: 0.49755572
A11: OPEX + EXCLUÍDOS | B11: 8920401.5 | C11: 1

Sheet Reembolsaveis_por_depto
A1: conta_numero | B1: plano_contas | C1: departamento | D1: qtd | E1: valor_competencia | F1: valor_caixa | G1: tratamento
A2: 5.16.06.000 | B2: OUTRAS DESPESAS REEMBOLSÁVEIS | C2: Conta Corrente Clientes | D2: 70 | E2: 26902.35 | F2: 26902.35 | G2: FORA do OPEX — reembolsável de cliente
A3: 5.6.02.000 | B3: CUSTAS JUDICIAIS | C3: Conta Corrente Clientes | D3: 77 | E3: 12167.08 | F3: 12167.08 | G3: FORA do OPEX — reembolsável de cliente
A4: 5.6.02.000 | B4: CUSTAS JUDICIAIS | C4: Cível | D4: 4 | E4: 8920.22 | F4: 8920.22 | G4: DENTRO do OPEX — Despesas Processuais, com flag
A5: 5.6.02.000 | B5: CUSTAS JUDICIAIS | C5: Insolvência | D5: 8 | E5: 5500.15 | F5: 5500.15 | G5: DENTRO do OPEX — Despesas Processuais, com flag
A6: 5.6.02.000 | B6: CUSTAS JUDICIAIS | C6: Recuperação de Crédito | D6: 22 | E6: 2584.03 | F6: 2584.03 | G6: DENTRO do OPEX — Despesas Processuais, com flag
A7: 5.6.02.000 | B7: CUSTAS JUDICIAIS | C7: Distressed Deals | D7: 16 | E7: 1827.99 | F7: 1827.99 | G7: DENTRO do OPEX — Despesas Processuais, com flag
A8: 5.6.02.000 | B8: CUSTAS JUDICIAIS | C8: Gustavo Bismarchi Motta | D8: 1 | E8: 192.1 | F8: 192.1 | G8: DENTRO do OPEX — Despesas Processuais, com flag
A9: 2.6.01.000 | B9: Custas | C9: — | D9: 0 | E9: 0 | F9: 0 | G9: sem lançamento no período
A10: 2.6.01.005 | B10: Correios jurídicos | C10: — | D10: 0 | E10: 0 | F10: 0 | G10: sem lançamento no período
A11: 2.6.03.000 | B11: Diligência | C11: — | D11: 0 | E11: 0 | F11: 0 | G11: sem lançamento no período
A12: 5.16.07.000 | B12: DESPESAS REEMBOLSÁVEIS - GUIAS | C12: — | D12: 0 | E12: 0 | F12: 0 | G12: sem lançamento no período

Sheet Controle_reembolso
A1: mes | B1: reembolsaveis_pagas_competencia | C1: reembolsos_recebidos_competencia | D1: saldo_competencia | E1: acumulado_competencia | F1: reembolsaveis_pagas_caixa | G1: reembolsos_recebidos_caixa | H1: saldo_caixa | I1: acumulado_caixa
A2: Critério | B2: PAGAR departamento Conta Corrente Clientes menos RECEBER mesmo departamento e plano REEMBOLSO DE DESPESAS. Fora do OPEX e fora da receita.
A3: 2026-01 | B3: 20315.58 | C3: 7842.48 | D3: 12473.1 | E3: 12473.1 | F3: 20315.58 | G3: 7842.68 | H3: 12472.9 | I3: 12472.9
A4: 2026-02 | B4: 7281.76 | C4: 3979.98 | D4: 3301.78 | E4: 15774.88 | F4: 7281.76 | G4: 2673.55 | H4: 4608.21 | I4: 17081.11
A5: 2026-03 | B5: 207232.2 | C5: 2751.02 | D5: 204481.18 | E5: 220256.06 | F5: 207232.2 | G5: 3912.39 | H5: 203319.81 | I5: 220400.92
A6: 2026-04 | B6: 34637.08 | C6: 2604.31 | D6: 32032.77 | E6: 252288.83 | F6: 34637.08 | G6: 1715.94 | H6: 32921.14 | I6: 253322.06
A7: 2026-05 | B7: 5791.45 | C7: 3514.47 | D7: 2276.98 | E7: 254565.81 | F7: 5791.45 | G7: 2419.44 | H7: 3372.01 | I7: 256694.07
A8: 2026-06 | B8: 10213.58 | C8: 7658.32 | D8: 2555.26 | E8: 257121.07 | F8: 10213.58 | G8: 7797.52 | H8: 2416.06 | I8: 259110.13
A9: 2026-07 | B9: 25748.93 | C9: 3025.83 | D9: 22723.1 | E9: 279844.17 | F9: 25748.93 | G9: 3751.99 | H9: 21996.94 | I9: 281107.07
A10: 2026-08 | B10: 3927.21 | C10: 2178.42 | D10: 1748.79 | E10: 281592.96 | F10: 3927.21 | G10: 1334.88 | H10: 2592.33 | I10: 283699.4

Sheet Repasse
A1: mes | B1: repasse_pago_competencia | C1: entrada_vinculada_competencia | D1: diferenca | E1: criterio
A2: Critério | B2: Saída = PAGAR 2.6.04 e 3.2.07. Entrada tirada da receita = mesmo mês, mesmo departamento e mesmo valor em RECEBER de OUTRAS RECEITAS/REPASSE, mais qualquer RECEBER cuja descrição ou plano contenha REPASSE. OUTRAS RECEITAS sem esse vínculo permanece na receita, na aba Repasse_sem_vinculo.
A3: 2026-01 | B3: 31299.52 | C3: 22820.57 | D3: 8478.95 | E3: mês + departamento + valor, ou texto REPASSE
A4: 2026-02 | B4: 19103.78 | C4: 18789.77 | D4: 314.01 | E4: mês + departamento + valor, ou texto REPASSE
A5: 2026-03 | B5: 232934.97 | C5: 236752.69 | D5: -3817.72 | E5: mês + departamento + valor, ou texto REPASSE
A6: 2026-04 | B6: 213235 | C6: 183025 | D6: 30210 | E6: mês + departamento + valor, ou texto REPASSE
A7: 2026-05 | B7: 105937.03 | C7: 105173.03 | D7: 764 | E7: mês + departamento + valor, ou texto REPASSE
A8: 2026-06 | B8: 166779.38 | C8: 127214.34 | D8: 39565.04 | E8: mês + departamento + valor, ou texto REPASSE
A9: 2026-07 | B9: 176471.91 | C9: 150770.64 | D9: 25701.27 | E9: mês + departamento + valor, ou texto REPASSE
A10: 2026-08 | B10: 122613.72 | C10: 100320.9 | D10: 22292.82 | E10: mês + departamento + valor, ou texto REPASSE

Sheet Repasse_lancamentos
A1: lado | B1: ci_item | C1: mes | D1: departamento | E1: conta | F1: plano | G1: descricao | H1: valor_competencia | I1: ci_entrada_vinculada | J1: tratamento_receita
A2: PAGAR | B2: 6001 | C2: 2025-11 | D2: Distressed Deals | E2: 3.2.07.000 | F2: REPASSE DE OUTRAS RECEITAS | G2: REPASSE ACORDO CONSTRURBAN - PARCELA 15/15 | H2: 0 | J2: sem entrada vinculada
A3: PAGAR | B3: 17019 | C3: 2026-06 | D3: Insolvência | E3: 3.2.07.000 | F3: REPASSE DE OUTRAS RECEITAS | G3: REPASSE ACORDO CONSTRURBAN | H3: 191.7 | J3: sem entrada vinculada
A4: PAGAR | B4: 17833 | C4: 2026-07 | D4: Insolvência | E4: 3.2.07.000 | F4: REPASSE DE OUTRAS RECEITAS | G4: REPASSE ACORDO CONSTRURBAN | H4: 191.99 | J4: sem entrada vinculada
A5: PAGAR | B5: 18691 | C5: 2026-08 | D5: Insolvência | E5: 3.2.07.000 | F5: REPASSE DE OUTRAS RECEITAS | G5: REPASSE ACORDO CONSTRURBAN | H5: 192.27 | J5: sem entrada vinculada
A6: PAGAR | B6: 13358 | C6: 2026-03 | D6: Distressed Deals | E6: 3.2.07.000 | F6: REPASSE DE OUTRAS RECEITAS | G6: REPASSE ACORDO DECORWATTS X PENA CONSTRUÇÕES | H6: 302.49 | I6: 16023 | J6: entrada fora da receita
A7: PAGAR | B7: 13359 | C7: 2026-03 | D7: Distressed Deals | E7: 3.2.07.000 | F7: REPASSE DE OUTRAS RECEITAS | G7: REPASSE ACORDO DECORWATTS X KM 18 | H7: 312.41 | I7: 16018 | J7: entrada fora da receita
A8: PAGAR | B8: 12238 | C8: 2026-02 | D8: Conta Corrente Clientes | E8: 3.2.07.000 | F8: REPASSE DE OUTRAS RECEITAS | G8: MLE PROCESSO 1000140-12.2020.8.26.0650 | H8: 314.01 | J8: sem entrada vinculada
A9: PAGAR | B9: 17330 | C9: 2026-06 | D9: Recuperação de Crédito | E9: 3.2.07.000 | F9: REPASSE DE OUTRAS RECEITAS | G9: REPASSE LIBERAÇÃO JUDICIAL PROC. 000306587020258160014REJANE COSTA - R$ 7.917,00EUNICE RENNA - R$ 16.000,00FATIMA SAMÕES - R$ 10.500,00FELIPE RODRIGUES - R$ 516,92FELIPE RODRIGUES - R$ 1.000,00LILIAN VIEIRA - R$ 2.000,00 | H9: 516.92 | J9: sem entrada vinculada
A10: PAGAR | B10: 18480 | C10: 2026-07 | D10: Recuperação de Crédito | E10: 3.2.07.000 | F10: REPASSE DE OUTRAS RECEITAS | G10: REPASSE ACORDO FÁBIO IORGULO | H10: 686.63 | J10: sem entrada vinculada
A11: PAGAR | B11: 19041 | C11: 2026-08 | D11: Recuperação de Crédito | E11: 3.2.07.000 | F11: REPASSE DE OUTRAS RECEITAS | G11: REPASSE ACORDO FÁBIO IORGULO | H11: 686.63 | J11: sem entrada vinculada
A12: PAGAR | B12: 12900 | C12: 2026-03 | D12: Distressed Deals | E12: 3.2.07.000 | F12: REPASSE DE OUTRAS RECEITAS | G12: REPASSE ACORDO SBV SOLUÇÕES AMBIENTAIS | H12: 699.5 | I12: 12821 | J12: entrada fora da receita
A13: PAGAR | B13: 16657 | C13: 2026-05 | D13: Insolvência | E13: 3.2.07.000 | F13: REPASSE DE OUTRAS RECEITAS | G13: REPASSE ACORDO CONSTRURBAN - JANEIRO A ABRIL/2026 | H13: 764 | J13: sem entrada vinculada
A14: PAGAR | B14: 13085 | C14: 2026-02 | D14: Insolvência | E14: 3.2.07.000 | F14: REPASSE DE OUTRAS RECEITAS | G14: REPASSE PROCESSO 00029099420208260428 | H14: 864.12 | I14: 12927 | J14: entrada fora da receita
A15: PAGAR | B15: 17332 | C15: 2026-06 | D15: Recuperação de Crédito | E15: 3.2.07.000 | F15: REPASSE DE OUTRAS RECEITAS | G15: REPASSE LIBERAÇÃO JUDICIAL PROC. 000306587020258160014REJANE COSTA - R$ 7.917,00EUNICE RENNA - R$ 16.000,00FATIMA SAMÕES - R$ 10.500,00FELIPE RODRIGUES - R$ 516,92FELIPE RODRIGUES - R$ 1.000,00LILIAN VIEIRA - R$ 2.000,00 | H15: 1000 | J15: sem entrada vinculada
A16: PAGAR | B16: 11643 | C16: 2026-01 | D16: Insolvência | E16: 3.2.07.000 | F16: REPASSE DE OUTRAS RECEITAS | G16: REPASSE PROCESSO 10035085620188260114 - APOSENTADORIA | H16: 1107.98 | J16: sem entrada vinculada
A17: PAGAR | B17: 17995 | C17: 2026-07 | D17: Recuperação de Crédito | E17: 3.2.07.000 | F17: REPASSE DE OUTRAS RECEITAS | G17: REPASSE LIBERAÇÃO JUDICIAL - PROC. 1020087-64.2023.8.26.0224 | H17: 1147.45 | J17: sem entrada vinculada
A18: PAGAR | B18: 17378 | C18: 2026-06 | D18: Trabalhista | E18: 3.2.07.000 | F18: REPASSE DE OUTRAS RECEITAS | G18: REPASSE LIBERAÇÃO JUDICIAL PROC. 1000860-98.2025.5.02.0204 | H18: 1439.42 | J18: sem entrada vinculada
A19: PAGAR | B19: 18870 | C19: 2026-08 | D19: Recuperação de Crédito | E19: 3.2.07.000 | F19: REPASSE DE OUTRAS RECEITAS | G19: REPASSE ACORDO DENARDI | H19: 1512.21 | J19: sem entrada vinculada
A20: PAGAR | B20: 11829 | C20: 2026-01 | D20: Distressed Deals | E20: 3.2.07.000 | F20: REPASSE DE OUTRAS RECEITAS | G20: REPASSE ACORDO GS INDUSTRIAL | H20: 1875 | I20: 9339 | J20: entrada fora da receita
A21: PAGAR | B21: 13048 | C21: 2026-02 | D21: Distressed Deals | E21: 3.2.07.000 | F21: REPASSE DE OUTRAS RECEITAS | G21: REPASSE ACORDO GS INDUSTRIAL | H21: 1875 | I21: 9340 | J21: entrada fora da receita
A22: PAGAR | B22: 14913 | C22: 2026-04 | D22: Recuperação de Crédito | E22: 3.2.07.000 | F22: REPASSE DE OUTRAS RECEITAS | G22: REPASSE ACORDO GS INDUSTRIAL | H22: 1875 | I22: 9342 | J22: entrada fora da receita
A23: PAGAR | B23: 16656 | C23: 2026-05 | D23: Recuperação de Crédito | E23: 3.2.07.000 | F23: REPASSE DE OUTRAS RECEITAS | G23: REPASSE ACORDO GS INDUSTRIAL | H23: 1875 | I23: 9343 | J23: entrada fora da receita
A24: PAGAR | B24: 17401 | C24: 2026-06 | D24: Recuperação de Crédito | E24: 3.2.07.000 | F24: REPASSE DE OUTRAS RECEITAS | G24: REPASSE ACORDO GS INDUSTRIAL | H24: 1875 | I24: 9344 | J24: entrada fora da receita
A25: PAGAR | B25: 17996 | C25: 2026-07 | D25: Recuperação de Crédito | E25: 3.2.07.000 | F25: REPASSE DE OUTRAS RECEITAS | G25: REPASSE ACORDO GS INDUSTRIAL | H25: 1875 | I25: 9345 | J25: entrada fora da receita
A26: PAGAR | B26: 18869 | C26: 2026-08 | D26: Recuperação de Crédito | E26: 3.2.07.000 | F26: REPASSE DE OUTRAS RECEITAS | G26: REPASSE ACORDO GS INDUSTRIAL | H26: 1875 | I26: 9346 | J26: entrada fora da receita
A27: PAGAR | B27: 17331 | C27: 2026-06 | D27: Recuperação de Crédito | E27: 3.2.07.000 | F27: REPASSE DE OUTRAS RECEITAS | G27: REPASSE LIBERAÇÃO JUDICIAL PROC. 000306587020258160014REJANE COSTA - R$ 7.917,00EUNICE RENNA - R$ 16.000,00FATIMA SAMÕES - R$ 10.500,00FELIPE RODRIGUES - R$ 516,92FELIPE RODRIGUES - R$ 1.000,00LILIAN VIEIRA - R$ 2.000,00 | H27: 2000 | J27: sem entrada vinculada
A28: PAGAR | B28: 18187 | C28: 2026-07 | D28: Recuperação de Crédito | E28: 3.2.07.000 | F28: REPASSE DE OUTRAS RECEITAS | G28: REPASSE ACORDO DENARDI | H28: 2442.25 | I28: 18188 | J28: entrada fora da receita
A29: PAGAR | B29: 17358 | C29: 2026-06 | D29: Recuperação de Crédito | E29: 3.2.07.000 | F29: REPASSE DE OUTRAS RECEITAS | G29: REPASSE LIBERAÇÃO JUDICIAL PROC. 000306587020258160014REJANE COSTA - R$ 7.917,00EUNICE RENNA - R$ 16.000,00FATIMA SAMÕES - R$ 10.500,00FELIPE RODRIGUES - R$ 516,92FELIPE RODRIGUES - R$ 1.000,00LILIAN VIEIRA - R$ 2.000,00 | H29: 2939.44 | J29: sem entrada vinculada
A30: PAGAR | B30: 12433 | C30: 2026-02 | D30: Distressed Deals | E30: 3.2.07.000 | F30: REPASSE DE OUTRAS RECEITAS | G30: REPASSE ACORDO CONSÓRCIO SANTA BARBARA | H30: 4050.65 | I30: 12827 | J30: entrada fora da receita
A31: PAGAR | B31: 16093 | C31: 2026-03 | D31: Distressed Deals | E31: 3.2.07.000 | F31: REPASSE DE OUTRAS RECEITAS | G31: REPASSE ACORDO GUARA EMPREENDIMENTOS | H31: 7615.77 | I31: 16083 | J31: entrada fora da receita
A32: PAGAR | B32: 11833 | C32: 2026-01 | D32: Distressed Deals | E32: 3.2.07.000 | F32: REPASSE DE OUTRAS RECEITAS | G32: REPASSE PROC. 1061459-77.2023.8.26.0002 - DECORWATTS X SOBROSA | H32: 7670.57 | I32: 12366 | J32: entrada fora da receita
A33: PAGAR | B33: 17355 | C33: 2026-06 | D33: Recuperação de Crédito | E33: 3.2.07.000 | F33: REPASSE DE OUTRAS RECEITAS | G33: REPASSE LIBERAÇÃO JUDICIAL PROC. 000306587020258160014REJANE COSTA - R$ 7.917,00EUNICE RENNA - R$ 16.000,00FATIMA SAMÕES - R$ 10.500,00FELIPE RODRIGUES - R$ 516,92FELIPE RODRIGUES - R$ 1.000,00LILIAN VIEIRA - R$ 2.000,00 | H33: 7917 | J33: sem entrada vinculada
A34: PAGAR | B34: 18591 | C34: 2026-08 | D34: Trabalhista | E34: 3.2.07.000 | F34: REPASSE DE OUTRAS RECEITAS | G34: REPASSE PROC. 0011542-17.2025.5.15.0092 - PAULO X BRADESCO | H34: 8061.71 | J34: sem entrada vinculada
A35: PAGAR | B35: 18481 | C35: 2026-07 | D35: Recuperação de Crédito | E35: 3.2.07.000 | F35: REPASSE DE OUTRAS RECEITAS | G35: REPASSE LIBERAÇÃO JUDICIAL - PROC. 02520-91.2025.8.26.0248 | H35: 8365.24 | I35: 18225 | J35: entrada fora da receita
A36: PAGAR | B36: 11377 | C36: 2026-01 | D36: Distressed Deals | E36: 3.2.07.000 | F36: REPASSE DE OUTRAS RECEITAS | G36: REPASSE ACORDO ENCALSO | H36: 8645.97 | J36: sem entrada vinculada
A37: PAGAR | B37: 17356 | C37: 2026-06 | D37: Recuperação de Crédito | E37: 3.2.07.000 | F37: REPASSE DE OUTRAS RECEITAS | G37: REPASSE LIBERAÇÃO JUDICIAL PROC. 000306587020258160014REJANE COSTA - R$ 7.917,00EUNICE RENNA - R$ 16.000,00FATIMA SAMÕES - R$ 10.500,00FELIPE RODRIGUES - R$ 516,92FELIPE RODRIGUES - R$ 1.000,00LILIAN VIEIRA - R$ 2.000,00 | H37: 10500 | J37: sem entrada vinculada
A38: PAGAR | B38: 14912 | C38: 2026-03 | D38: Distressed Deals | E38: 3.2.07.000 | F38: REPASSE DE OUTRAS RECEITAS | G38: REPASSE ACORDO GS INDUSTRIAL | H38: 11250 | I38: 9341 | J38: entrada fora da receita
A39: PAGAR | B39: 18575 | C39: 2026-07 | D39: Cível | E39: 3.2.07.000 | F39: REPASSE DE OUTRAS RECEITAS | G39: GOLD LAND - SUGUITA | H39: 11835.2 | J39: sem entrada vinculada
A40: PAGAR | B40: 18581 | C40: 2026-07 | D40: Cível | E40: 3.2.07.000 | F40: REPASSE DE OUTRAS RECEITAS | G40: GOLD LAND - SUGUITA | H40: 11840 | J40: sem entrada vinculada
A41: PAGAR | B41: 19343 | C41: 2026-08 | D41: Cível | E41: 3.2.07.000 | F41: REPASSE DE OUTRAS RECEITAS | G41: GOLD LAND - SUGUITA | H41: 11840 | J41: sem entrada vinculada
A42: PAGAR | B42: 11553 | C42: 2026-01 | D42: Cível | E42: 3.2.07.000 | F42: REPASSE DE OUTRAS RECEITAS | G42: GOLD LAND - SUGUITA | H42: 12000 | I42: 12527 | J42: entrada fora da receita
A43: PAGAR | B43: 12320 | C43: 2026-02 | D43: Cível | E43: 3.2.07.000 | F43: REPASSE DE OUTRAS RECEITAS | G43: GOLD LAND - SUGUITA | H43: 12000 | I43: 12526 | J43: entrada fora da receita
A44: PAGAR | B44: 12610 | C44: 2026-03 | D44: Cível | E44: 3.2.07.000 | F44: REPASSE DE OUTRAS RECEITAS | G44: GOLD LAND - SUGUITA | H44: 12000 | I44: 12528 | J44: entrada fora da receita
A45: PAGAR | B45: 17314 | C45: 2026-04 | D45: Cível | E45: 3.2.07.000 | F45: REPASSE DE OUTRAS RECEITAS | G45: GOLD LAND - SUGUITA | H45: 12000 | I45: 12529 | J45: entrada fora da receita
A46: PAGAR | B46: 17323 | C46: 2026-05 | D46: Cível | E46: 3.2.07.000 | F46: REPASSE DE OUTRAS RECEITAS | G46: GOLD LAND - SUGUITA | H46: 12000 | I46: 12530 | J46: entrada fora da receita
A47: PAGAR | B47: 17791 | C47: 2026-06 | D47: Cível | E47: 3.2.07.000 | F47: REPASSE DE OUTRAS RECEITAS | G47: GOLD LAND - SUGUITA | H47: 12000 | I47: 12531 | J47: entrada fora da receita
A48: PAGAR | B48: 17517 | C48: 2026-06 | D48: Recuperação de Crédito | E48: 3.2.07.000 | F48: REPASSE DE OUTRAS RECEITAS | G48: REPASSE LIBERAÇÃO JUDICIAL PROC. 000306587020258160014REJANE COSTA - R$ 7.917,00EUNICE RENNA - R$ 16.000,00FATIMA SAMÕES - R$ 10.500,00FELIPE RODRIGUES - R$ 516,92FELIPE RODRIGUES - R$ 1.000,00LILIAN VIEIRA - R$ 2.000,00 | H48: 13060.56 | J48: sem entrada vinculada
A49: PAGAR | B49: 17172 | C49: 2026-06 | D49: Recuperação de Crédito | E49: 3.2.07.000 | F49: REPASSE DE OUTRAS RECEITAS | G49: REPASSE PROC. 1012237-27.2025.8.26.0114 - GPR X PROJETAR | H49: 22041.31 | I49: 17097 | J49: entrada fora da receita
A50: PAGAR | B50: 15855 | C50: 2026-04 | D50: Conta Corrente Clientes | E50: 3.2.07.000 | F50: REPASSE DE OUTRAS RECEITAS | G50: REPASSE OKNO CAPITAL | H50: 31960 | J50: sem entrada vinculada
A51: PAGAR | B51: 17994 | C51: 2026-07 | D51: Recuperação de Crédito | E51: 3.2.07.000 | F51: REPASSE DE OUTRAS RECEITAS | G51: REPASSE LIBERAÇÃO JUDICIAL PROC. 4011523-40.2026.8.26.0224 | H51: 46790.12 | I51: 17923 | J51: entrada fora da receita
A52: PAGAR | B52: 16664 | C52: 2026-05 | D52: Recuperação de Crédito | E52: 3.2.07.000 | F52: REPASSE DE OUTRAS RECEITAS | G52: REPASSE ACORDO ECOBULK | H52: 91298.03 | I52: 16900 | J52: entrada fora da receita
A53: PAGAR | B53: 17549 | C53: 2026-06 | D53: Recuperação de Crédito | E53: 3.2.07.000 | F53: REPASSE DE OUTRAS RECEITAS | G53: REPASSE ACORDO ECOBULK | H53: 91298.03 | I53: 16903 | J53: entrada fora da receita
A54: PAGAR | B54: 18178 | C54: 2026-07 | D54: Recuperação de Crédito | E54: 3.2.07.000 | F54: REPASSE DE OUTRAS RECEITAS | G54: REPASSE ACORDO ECOBULK | H54: 91298.03 | I54: 16906 | J54: entrada fora da receita
A55: PAGAR | B55: 18901 | C55: 2026-08 | D55: Recuperação de Crédito | E55: 3.2.07.000 | F55: REPASSE DE OUTRAS RECEITAS | G55: REPASSE ACORDO CONSORCIO CRA | H55: 98445.9 | I55: 18900 | J55: entrada fora da receita
A56: PAGAR | B56: 16481 | C56: 2026-04 | D56: Recuperação de Crédito | E56: 3.2.07.000 | F56: REPASSE DE OUTRAS RECEITAS | G56: REPASSE ACORDO ECOBULK | H56: 167400 | I56: 16231 | J56: entrada fora da receita
A57: PAGAR | B57: 14888 | C57: 2026-03 | D57: Conta Corrente Clientes | E57: 3.2.07.000 | F57: REPASSE DE OUTRAS RECEITAS | G57: REPASSE PROC. 00006294220248260451 | H57: 200754.8 | I57: 14886 | J57: entrada fora da receita
A58: RECEBER | B58: 12367 | C58: 2026-01 | D58: Conta Corrente Clientes | E58: 3.2.01.000 | F58: REEMBOLSO DE DESPESAS | G58: REEMBOLSO REPASSE INDEVIDO ACORDO JRA EMPREENDIMENTOS | H58: 1275 | J58: fora da receita por texto REPASSE
A59: RECEBER | B59: 16013 | C59: 2026-03 | D59: Facilities | E59: 3.2.10.000 | F59: PARCERIAS | G59: REPASSE - PARCERIA | H59: 1908.86 | J59: fora da receita por texto REPASSE
A60: RECEBER | B60: 16079 | C60: 2026-03 | D60: Facilities | E60: 3.2.10.000 | F60: PARCERIAS | G60: REPASSE - PARCERIA | H60: 1908.86 | J60: fora da receita por texto REPASSE
A61: RECEBER | B61: 16229 | C61: 2026-04 | D61: Facilities | E61: 3.2.10.000 | F61: PARCERIAS | G61: REPASSE - PARCERIA | H61: 1750 | J61: fora da receita por texto REPASSE

Sheet Repasse_sem_vinculo
A1: ci_item | B1: mes | C1: departamento | D1: conta | E1: plano | F1: descricao | G1: valor_competencia | H1: status
A2: 11932 | B2: 2026-01 | C2: Conta Corrente Clientes | D2: 3.2.06.000 | E2: OUTRAS RECEITAS | F2: HOUVE UM PAGAMENTO DE R$ 18.000,00 POR ENGANO E DEVOLVEMOS PARA O GUSTAVO | G2: 18000 | H2: permanece na receita até validação
A3: 11974 | B3: 2026-01 | C3: Distressed Deals | D3: 3.2.06.000 | E3: OUTRAS RECEITAS | F3: ACORDO GRUPO PAULO CURZIO | G3: 183.62 | H3: permanece na receita até validação
A4: 12242 | B4: 2026-02 | C4: Facilities | D4: 3.2.06.000 | E4: OUTRAS RECEITAS | F4: Teste Vios de boletos | G4: 12 | H4: permanece na receita até validação
A5: 12391 | B5: 2026-02 | C5: Distressed Deals | D5: 3.2.06.000 | E5: OUTRAS RECEITAS | F5: ACORDO GRUPO PAULO CURZIO | G5: 6.97 | H5: permanece na receita até validação
A6: 12392 | B6: 2026-02 | C6: Distressed Deals | D6: 3.2.06.000 | E6: OUTRAS RECEITAS | F6: ACORDO GRUPO PAULO CURZIO | G6: 183.89 | H6: permanece na receita até validação
A7: 12532 | B7: 2026-07 | C7: Cível | D7: 3.2.06.000 | E7: OUTRAS RECEITAS | F7: GOLD LAND | G7: 12000 | H7: permanece na receita até validação
A8: 12533 | B8: 2026-08 | C8: Cível | D8: 3.2.06.000 | E8: OUTRAS RECEITAS | F8: GOLD LAND | G8: 12000 | H8: permanece na receita até validação
A9: 12928 | B9: 2026-02 | C9: Insolvência | D9: 3.2.06.000 | E9: OUTRAS RECEITAS | F9: PROC. 10001401220208260650 - PERFILIX | G9: 314.01 | H9: permanece na receita até validação
A10: 13092 | B10: 2026-02 | C10: Facilities | D10: 3.2.06.000 | E10: OUTRAS RECEITAS | F10: TESTE EMISSÃO BOLETO PELO VIOS | G10: 10.04 | H10: permanece na receita até validação
A11: 13368 | B11: 2026-03 | C11: Distressed Deals | D11: 3.2.06.000 | E11: OUTRAS RECEITAS | F11: ACORDO GRUPO PAULO CURZIO | G11: 6.98 | H11: permanece na receita até validação
A12: 13369 | B12: 2026-03 | C12: Distressed Deals | D12: 3.2.06.000 | E12: OUTRAS RECEITAS | F12: ACORDO GRUPO PAULO CURZIO | G12: 184.16 | H12: permanece na receita até validação
A13: 14113 | B13: 2026-04 | C13: Distressed Deals | D13: 3.2.06.000 | E13: OUTRAS RECEITAS | F13: HONORÁRIOS DE ÊXITO REFERENTE À CESSÃO PARA STRATEGI | G13: 31960 | H13: permanece na receita até validação
... A43: 19192 | B43: 2026-08 | C43: Insolvência | D43: 3.2.06.000 | E43: OUTRAS RECEITAS | F43: ACORDO GRUPO PAULO CURZIO | G43: 7.03 | H43: permanece na receita até validação

Sheet Tributos_mensal
A1: conta | B1: plano | C1: mes | D1: valor_competencia | E1: valor_caixa | F1: flag
A2: 3.3.01.000 | B2: IMPOSTOS SOBRE SERVIÇOS - ISS | C2: 2026-01 | D2: 31.7 | E2: 31.7 | F2: composicao_pendente
A3: 3.3.01.000 | B3: IMPOSTOS SOBRE SERVIÇOS - ISS | C3: 2026-02 | D3: 37.25 | E3: 37.25 | F3: composicao_pendente
A4: 3.3.01.000 | B4: IMPOSTOS SOBRE SERVIÇOS - ISS | C4: 2026-03 | D4: 9.59 | E4: 9.59 | F4: composicao_pendente
A5: 3.3.01.000 | B5: IMPOSTOS SOBRE SERVIÇOS - ISS | C5: 2026-04 | D5: 9.59 | E5: 9.59 | F5: composicao_pendente
A6: 3.3.01.000 | B6: IMPOSTOS SOBRE SERVIÇOS - ISS | C6: 2026-05 | D6: 9.59 | E6: 9.59 | F6: composicao_pendente
A7: 3.3.01.000 | B7: IMPOSTOS SOBRE SERVIÇOS - ISS | C7: 2026-06 | D7: 28.12 | E7: 28.12 | F7: composicao_pendente
A8: 3.3.01.000 | B8: IMPOSTOS SOBRE SERVIÇOS - ISS | C8: 2026-07 | D8: 73.7 | E8: 73.7 | F8: composicao_pendente
A9: 3.3.01.000 | B9: IMPOSTOS SOBRE SERVIÇOS - ISS | C9: 2026-08 | D9: 9.59 | E9: 9.59 | F9: composicao_pendente
A10: 5.14.03.000 | B10: IMPOSTOS E TAXAS | C10: 2026-01 | D10: 75447.27 | E10: 75447.27 | F10: composicao_pendente
A11: 5.14.03.000 | B11: IMPOSTOS E TAXAS | C11: 2026-02 | D11: 40614.41 | E11: 40614.41 | F11: composicao_pendente
A12: 5.14.03.000 | B12: IMPOSTOS E TAXAS | C12: 2026-03 | D12: 46006.62 | E12: 46006.62 | F12: composicao_pendente
A13: 5.14.03.000 | B13: IMPOSTOS E TAXAS | C13: 2026-04 | D13: 63450.81 | E13: 63450.81 | F13: composicao_pendente
... A21: 2.2.06.000 | B21: Tributos | C21: 2026-01 a 2026-08 | D21: 0 | E21: 0 | F21: composicao_pendente; sem movimento no período

Sheet Socios_capital
A1: mes | B1: pro_labore_8_1_03 | C1: contas_nominais_socios | D1: distribuicao_de_lucros | E1: remuneracao_socios_de_capital
A2: Nota | B2: Linha abaixo do resultado operacional. Fora do OPEX. Associados 8.1.01 não entram aqui.
A3: 2026-01 | B3: 102000 | C3: 0 | D3: 100246.41 | E3: 202246.41
A4: 2026-02 | B4: 120000 | C4: 0 | D4: 158070.98 | E4: 278070.98
A5: 2026-03 | B5: 120000 | C5: 0 | D5: 227427.74 | E5: 347427.74
A6: 2026-04 | B6: 120000 | C6: 0 | D6: 282322.16 | E6: 402322.16
A7: 2026-05 | B7: 120000 | C7: 0 | D7: 277856.6 | E7: 397856.6
A8: 2026-06 | B8: 120000 | C8: 0 | D8: 244021.16 | E8: 364021.16
A9: 2026-07 | B9: 120000 | C9: 0 | D9: 250465.89 | E9: 370465.89
A10: 2026-08 | B10: 120000 | C10: 0 | D10: 286548.54 | E10: 406548.54

Sheet Provisao_13_ferias
A1: conta | B1: plano | C1: mes | D1: lancado_competencia | E1: provisao_sugerida_mensal | F1: ajuste_sugerido | G1: status
A2: 8.2.05.000 | B2: 13º SALÁRIO | C2: 2026-01 | D2: 0 | E2: 0 | F2: 0 | G2: sugerida
A3: 8.2.05.000 | B3: 13º SALÁRIO | C3: 2026-02 | D3: 0 | E3: 0 | F3: 0 | G3: sugerida
A4: 8.2.05.000 | B4: 13º SALÁRIO | C4: 2026-03 | D4: 0 | E4: 0 | F4: 0 | G4: sugerida
A5: 8.2.05.000 | B5: 13º SALÁRIO | C5: 2026-04 | D5: 0 | E5: 0 | F5: 0 | G5: sugerida
A6: 8.2.05.000 | B6: 13º SALÁRIO | C6: 2026-05 | D6: 0 | E6: 0 | F6: 0 | G6: sugerida
A7: 8.2.05.000 | B7: 13º SALÁRIO | C7: 2026-06 | D7: 0 | E7: 0 | F7: 0 | G7: sugerida
A8: 8.2.05.000 | B8: 13º SALÁRIO | C8: 2026-07 | D8: 0 | E8: 0 | F8: 0 | G8: sugerida
A9: 8.2.05.000 | B9: 13º SALÁRIO | C9: 2026-08 | D9: 0 | E9: 0 | F9: 0 | G9: sugerida
A10: 8.2.04.000 | B10: FÉRIAS | C10: 2026-01 | D10: 0 | E10: 577.87 | F10: 577.87 | G10: sugerida
A11: 8.2.04.000 | B11: FÉRIAS | C11: 2026-02 | D11: 2225.3 | E11: 577.87 | F11: -1647.43 | G11: sugerida
A12: 8.2.04.000 | B12: FÉRIAS | C12: 2026-03 | D12: 420.89 | E12: 577.87 | F12: 156.98 | G12: sugerida
A13: 8.2.04.000 | B13: FÉRIAS | C13: 2026-04 | D13: 0 | E13: 577.87 | F13: 577.87 | G13: sugerida
... A25: 8.7.06.000 | B25: SALDO DE FÉRIAS ASSOCIADOS | C25: 2026-08 | D25: 0 | E25: 2766.98 | F25: 2766.98 | G25: sugerida
A26: Nota | B26: Provisão mensal = soma de competência jan–ago / 8. Não há custo por pessoa para calcular 1/12 da folha.

Sheet Alerta_outros
A1: grupo_gerencial | B1: valor_competencia | C1: pct_opex
A2: Pessoas | B2: 3030022.9 | C2: 0.68268409
A3: Ocupação/Facilities | B3: 389048.18 | C3: 0.087655115
A4: Serviços Terceirizados | B4: 303790.27 | C4: 0.068445947
A5: Comissões | B5: 302414.44 | C5: 0.068135963
A6: Tecnologia e Sistemas | B6: 215542.89 | C6: 0.048563232
A7: Marketing e Desenvolvimento de Negócios | B7: 128184.12 | C7: 0.028880726
A8: Administrativo Geral | B8: 32457.96 | C8: 0.007312992
A9: Despesas Processuais | B9: 19024.49 | C9: 0.0042863428
A10: Administrativo e Financeiro | B10: 10384.85 | C10: 0.002339775
A11: Viagens e Deslocamentos | B11: 7526.7 | C11: 0.001695815
A12: Outros dentro de 5% do OPEX | B12: 0 | C12: 0

Sheet Referencia_2026
A1: nome | B1: nota | C1: ano | D1: mes | E1: grupo_conta | F1: plano_contas | G1: conta_numero | H1: departamento | I1: descricao | J1: valor
A2: Referência 2026 | B2: referência montada em jul/2026 a partir do realizado até ago | C2: 2026 | D2: 7 | E2: BENEFÍCIOS | F2: VALE TRANSPORTE | G2: 8.4.02.000 | H2: Facilities | I2: Caju - Beneficios | J2: 4000
A3: Referência 2026 | B3: referência montada em jul/2026 a partir do realizado até ago | C3: 2026 | D3: 4 | E3: DESPESAS DE INFRAESTRUTURA | F3: INTERNET | G3: 5.12.03.000 | H3: Facilities | I3: Vogel Soluções em Telecomunicações e Informática S/A | J3: 709.99
A4: Referência 2026 | B4: referência montada em jul/2026 a partir do realizado até ago | C4: 2026 | D4: 7 | E4: DESPESAS DE INFRAESTRUTURA | F4: ENERGIA ELÉTRICA | G4: 5.12.02.000 | H4: Facilities | I4: CPFL ENERGIA S.A | J4: 2100
A5: Referência 2026 | B5: referência montada em jul/2026 a partir do realizado até ago | C5: 2026 | D5: 7 | E5: TREINAMENTO/DESENVOLVIMENTO/CULTURA | F5: EVENTOS | G5: 8.5.04.000 | H5: Facilities | I5: CAFÉ COM CULTURA · Casa Olivetto Eventos | J5: 4500
A6: Referência 2026 | B6: referência montada em jul/2026 a partir do realizado até ago | C6: 2026 | D6: 2 | E6: IMPOSTOS, TAXAS E SEGUROS | F6: IMPOSTOS E TAXAS | G6: 5.14.03.000 | H6: Facilities | I6: PARCELAMENTO PGFN · MINISTERIO DA ECONOMIA | J6: 600
A7: Referência 2026 | B7: referência montada em jul/2026 a partir do realizado até ago | C7: 2026 | D7: 6 | E7: ENCARGOS SOCIAIS | F7: FGTS | G7: 8.3.01.000 | H7: Facilities | I7: FGTS | J7: 2225
A8: Referência 2026 | B8: referência montada em jul/2026 a partir do realizado até ago | C8: 2026 | D8: 2 | E8: COMISSÕES SOBRE VENDAS | F8: COMISSÕES INTERNAS | G8: 4.1.02.000 | H8: Cível | I8: ADRIANA CAVALCANTE · Renato Rossetti Vallim de Castro | J8: 100.2
A9: Referência 2026 | B9: referência montada em jul/2026 a partir do realizado até ago | C9: 2026 | D9: 6 | E9: TECNOLOGIA E SISTEMAS | F9: SISTEMAS DE GESTÃO E OPERAÇãO | G9: 9.1.05.000 | H9: T.I. | I9: Vios Tecnologia | J9: 10000
A10: Referência 2026 | B10: referência montada em jul/2026 a partir do realizado até ago | C10: 2026 | D10: 3 | E10: DESPESAS COM SERVIÇOS DE TERCEIROS | F10: LIMPEZA | H10: Facilities | I10: LIMPEZA DE CARPETE, TAPETES, VIDROS · FORNECEDOR NÃO CADASTRADO | J10: 756
A11: Referência 2026 | B11: referência montada em jul/2026 a partir do realizado até ago | C11: 2026 | D11: 7 | E11: BENEFÍCIOS | F11: AUXÍLIO EDUCACIONAL | G11: 8.4.05.000 | H11: Cível | I11: PÓS GRADUAÇÃO GIANCARLO ZOTINI · Fundacao Getulio Vargas | J11: 1053.1
A12: Referência 2026 | B12: referência montada em jul/2026 a partir do realizado até ago | C12: 2026 | D12: 8 | E12: BENEFÍCIOS | F12: ASSISTÊNCIA MÉDICA E ODONTOLÓGICA | G12: 8.4.03.000 | H12: Operações Legais | I12: FELIPE SOARES DE CAMARGO · Qualicorp Administradora de Beneficios S.a. | J12: 1476.31
A13: Referência 2026 | B13: referência montada em jul/2026 a partir do realizado até ago | C13: 2026 | D13: 8 | E13: DESPESAS DE INFRAESTRUTURA | F13: TELEFONIA MÓVEL | G13: 5.12.07.000 | H13: Facilities | I13: CLARO S.A. | J13: 60
A14: Referência 2026 | B14: referência montada em jul/2026 a partir do realizado até ago | C14: 2026 | D14: 1 | E14: BENEFÍCIOS | F14: VALE TRANSPORTE | G14: 8.4.02.000 | H14: Facilities | I14: Caju - Beneficios | J14: 4000
A15: Referência 2026 | B15: referência montada em jul/2026 a partir do realizado até ago | C15: 2026 | D15: 5 | E15: DESPESAS DE MANUTENÇãO | F15: MANUTENÇãO PREDIAL | H15: Facilities | I15: FORNECEDOR NÃO CADASTRADO | J15: 2014
A16: Referência 2026 | B16: referência montada em jul/2026 a partir do realizado até ago | C16: 2026 | D16: 3 | E16: DESPESAS DE INFRAESTRUTURA | F16: TELEFONIA MÓVEL | G16: 5.12.07.000 | H16: Facilities | I16: CLARO S.A. | J16: 85.84
A17: Referência 2026 | B17: referência montada em jul/2026 a partir do realizado até ago | C17: 2026 | D17: 1 | E17: TECNOLOGIA E SISTEMAS | F17: SISTEMAS DE GESTÃO E OPERAÇãO | G17: 9.1.05.000 | H17: T.I. | I17: Kurier Tecnologia Em Informacao Ltda | J17: 592.32
A18: Referência 2026 | B18: referência montada em jul/2026 a partir do realizado até ago | C18: 2026 | D18: 1 | E18: DESPESAS FINANCEIRAS | F18: DESPESAS BANCÁRIAS | G18: 5.18.01.000 | H18: Facilities | I18: TARIFA CONTA CERTA · ITAU UNIBANCO S.A. | J18: 179
A19: Referência 2026 | B19: referência montada em jul/2026 a partir do realizado até ago | C19: 2026 | D19: 7 | E19: DESPESAS DE INFRAESTRUTURA | F19: INTERNET | G19: 5.12.03.000 | H19: Facilities | I19: IP DEDICADO · Vivo S.a Telefônica Brasil S.a | J19: 1000
A20: Referência 2026 | B20: referência montada em jul/2026 a partir do realizado até ago | C20: 2026 | D20: 2 | E20: DESPESAS DE MANUTENÇãO | F20: PAISAGISMO | G20: 5.9.07.000 | H20: Facilities | I20: Mateus dos Santos | J20: 900
A21: Referência 2026 | B21: referência montada em jul/2026 a partir do realizado até ago | C21: 2026 | D21: 4 | E21: DESPESAS DE INFRAESTRUTURA | F21: TELEFONIA MÓVEL | G21: 5.12.07.000 | H21: Facilities | I21: CLARO S.A. | J21: 85.84
A22: Referência 2026 | B22: referência montada em jul/2026 a partir do realizado até ago | C22: 2026 | D22: 6 | E22: REMUNERAÇãO FIXA | F22: PRÓ-LABORE | G22: 8.1.03.000 | H22: Gustavo Bismarchi Motta | I22: Gustavo Bismarchi Motta | J22: 60000
A23: Referência 2026 | B23: referência montada em jul/2026 a partir do realizado até ago | C23: 2026 | D23: 8 | E23: TECNOLOGIA E SISTEMAS | F23: SISTEMAS DE GESTÃO E OPERAÇãO | G23: 9.1.05.000 | H23: T.I. | I23: FEEDZ · Solucoes Em Software e Servicos Tts Ltda | J23: 1137.2
A24: Referência 2026 | B24: referência montada em jul/2026 a partir do realizado até ago | C24: 2026 | D24: 2 | E24: IMPOSTOS SOBRE SERVIÇOS | F24: IMPOSTOS SOBRE SERVIÇOS - ISS | G24: 3.3.01.000 | H24: Facilities | I24: MUNICIPIO DE CAMPINAS | J24: 10
A25: Referência 2026 | B25: referência montada em jul/2026 a partir do realizado até ago | C25: 2026 | D25: 6 | E25: COMISSÕES SOBRE VENDAS | F25: COMISSÕES INTERNAS | G25: 4.1.02.000 | H25: Cível | I25: BEATRIZ BALDO · Felipe Soares de Camargo | J25: 100
A26: Referência 2026 | B26: referência montada em jul/2026 a partir do realizado até ago | C26: 2026 | D26: 8 | E26: DESPESAS COM SERVIÇOS DE TERCEIROS | F26: SERVIÇOS DE INFORMÁTICA | G26: 5.8.02.000 | H26: T.I. | I26: Cleber R Felix Informatica | J26: 3006.07
A27: Referência 2026 | B27: referência montada em jul/2026 a partir do realizado até ago | C27: 2026 | D27: 8 | E27: COMISSÕES SOBRE VENDAS | F27: COMISSÕES INTERNAS | G27: 4.1.02.000 | H27: Insolvência | I27: FAVIFER, LATASA · Leonardo Loureiro Basso | J27: 2000
... A45: Referência 2026 | B45: referência montada em jul/2026 a partir do realizado até ago | C45: 2026 | D45: 2 | E45: IMPOSTOS, TAXAS E SEGUROS | F45: SEGUROS | G45: 5.14.05.000 | H45: Facilities | I45: SEGURO RESPONSABILIDADE CIVIL · TOKIO MARINE SEGURADORA S.A. | J45: 1436.4
A46: Referência 2026 | B46: referência montada em jul/2026 a partir do realizado até ago | C46: 2026 | D46: 5 | E46: TECNOLOGIA E SISTEMAS | F46: DOMÍNIOS E HOSPEDAGEM | H46: T.I. | I46: DOMÍNIO BIBLIOTECA · FORNECEDOR NÃO CADASTRADO | J46: 44.9
A47: Referência 2026 | B47: referência montada em jul/2026 a partir do realizado até ago | C47: 2026 | D47: 4 | E47: DESPESAS FINANCEIRAS | F47: DESPESAS BANCÁRIAS | G47: 5.18.01.000 | H47: Facilities | I47: TARIFA PACOTE DE SERVIÇOS · Banco do Brasil Sa | J47: 124.9
A48: Referência 2026 | B48: referência montada em jul/2026 a partir do realizado até ago | C48: 2026 | D48: 6 | E48: DESPESAS COM SERVIÇOS DE TERCEIROS | F48: CONSULTORIA | G48: 5.8.20.000 | H48: Facilities | I48: Mais Humanidade Ltda | J48: 4000
A49: Referência 2026 | B49: referência montada em jul/2026 a partir do realizado até ago | C49: 2026 | D49: 1 | E49: TECNOLOGIA E SISTEMAS | F49: MARKETING E COMERCIAL | G49: 9.1.03.000 | H49: T.I. | I49: RD MARKETING · Rd Gestao e Sistemas S.a. | J49: 1121
A50: Referência 2026 | B50: referência montada em jul/2026 a partir do realizado até ago | C50: 2026 | D50: 7 | E50: DESPESAS COM SERVIÇOS DE TERCEIROS | F50: LIMPEZA | H50: Facilities | I50: LIMPEZA DE CARPETE, TAPETES, VIDROS · FORNECEDOR NÃO CADASTRADO | J50: 756
A51: Referência 2026 | B51: referência montada em jul/2026 a partir do realizado até ago | C51: 2026 | D51: 6 | E51: TECNOLOGIA E SISTEMAS | F51: SISTEMAS DE GESTÃO E OPERAÇãO | G51: 9.1.05.000 | H51: Insolvência | I51: Credvalue Ltda | J51: 1000
A52: Referência 2026 | B52: referência montada em jul/2026 a partir do realizado até ago | C52: 2026 | D52: 6 | E52: DESPESAS DE INFRAESTRUTURA | F52: INTERNET | G52: 5.12.03.000 | H52: Facilities | I52: Vogel Soluções em Telecomunicações e Informática S/A | J52: 709.99
A53: Referência 2026 | B53: referência montada em jul/2026 a partir do realizado até ago | C53: 2026 | D53: 8 | E53: TECNOLOGIA E SISTEMAS | F53: SISTEMAS DE GESTÃO E OPERAÇãO | G53: 9.1.05.000 | H53: T.I. | I53: Adobe Systems Brasil Ltda. | J53: 275
A54: Referência 2026 | B54: referência montada em jul/2026 a partir do realizado até ago | C54: 2026 | D54: 6 | E54: DESPESAS FINANCEIRAS | F54: IOF | G54: 5.18.02.000 | H54: Facilities | I54: IOF ADICIONAL SOBRE PARCELAMENTO NO CARTÃO DE CRÉDITO - REGULARIZAÇÃO OAB · Banco Bradesco S.a. | J54: 10
A55: Referência 2026 | B55: referência montada em jul/2026 a partir do realizado até ago | C55: 2026 | D55: 1 | E55: IMPOSTOS, TAXAS E SEGUROS | F55: IMPOSTOS E TAXAS | G55: 5.14.03.000 | H55: Gustavo Bismarchi Motta | I55: GUSTAVO - REGULARIZAÇÃO REF. 2021, 2022, 2023 E 2024 · Ordem dos Advogados do Brasil Al | J55: 880
A56: Referência 2026 | B56: referência montada em jul/2026 a partir do realizado até ago | C56: 2026 | D56: 7 | E56: BENEFÍCIOS | F56: ESTACIONAMENTO | G56: 8.4.06.000 | H56: Cível | I56: Quickpark Estacionamento Ltda | J56: 3300
A57: Referência 2026 | B57: referência montada em jul/2026 a partir do realizado até ago | C57: 2026 | D57: 7 | E57: TECNOLOGIA E SISTEMAS | F57: SISTEMAS DE GESTÃO E OPERAÇãO | G57: 9.1.05.000 | H57: Insolvência | I57: Credvalue Ltda | J57: 1000
A58: Referência 2026 | B58: referência montada em jul/2026 a partir do realizado até ago | C58: 2026 | D58: 3 | E58: DESPESAS FINANCEIRAS | F58: DESPESAS BANCÁRIAS | G58: 5.18.01.000 | H58: Facilities | I58: TARIFA PACOTE DE SERVIÇOS · Banco do Brasil Sa | J58: 124.9
A59: Referência 2026 | B59: referência montada em jul/2026 a partir do realizado até ago | C59: 2026 | D59: 7 | E59: DESPESAS DE MANUTENÇãO | F59: MANUTENÇãO PURIFICADORES DE ÁGUA | G59: 5.9.08.000 | H59: Facilities | I59: MANUTENÇÃO PURIFICADORES · Whirlpool S.a | J59: 234.64
A60: Referência 2026 | B60: referência montada em jul/2026 a partir do realizado até ago | C60: 2026 | D60: 7 | E60: COMISSÕES SOBRE VENDAS | F60: COMISSÕES INTERNAS | G60: 4.1.02.000 | H60: Insolvência | I60: CRISTAL & CORES, SELETIVA · Ligia Gilberti Lopes | J60: 1500
A61: Referência 2026 | B61: referência montada em jul/2026 a partir do realizado até ago | C61: 2026 | D61: 4 | E61: DESPESAS COM SERVIÇOS DE TERCEIROS | F61: CONSULTORIA | G61: 5.8.20.000 | H61: Facilities | I61: Antunes Galvao Consultoria Em Gestao Empresarial | J61: 11062.4
A62: Referência 2026 | B62: referência montada em jul/2026 a partir do realizado até ago | C62: 2026 | D62: 4 | E62: REMUNERAÇãO FIXA | F62: PRÓ-LABORE | G62: 8.1.03.000 | H62: Gustavo Bismarchi Motta | I62: Gustavo Bismarchi Motta | J62: 60000
... A65: Referência 2026 | B65: referência montada em jul/2026 a partir do realizado até ago | C65: 2026 | D65: 5 | E65: DESPESAS DE INFRAESTRUTURA | F65: ÁGUA E ESGOTO | G65: 5.12.01.000 | H65: Facilities | I65: SOCIEDADE DE ABASTECIMENTO DE ÁGUA E SANEAMENTO S/A (SANASA) | J65: 1700
A66: Referência 2026 | B66: referência montada em jul/2026 a partir do realizado até ago | C66: 2026 | D66: 5 | E66: DESPESAS COM SERVIÇOS DE TERCEIROS | F66: LIMPEZA | H66: Facilities | I66: LIMPEZA DE CARPETE, TAPETES, VIDROS · FORNECEDOR NÃO CADASTRADO | J66: 756
A67: Referência 2026 | B67: referência montada em jul/2026 a partir do realizado até ago | C67: 2026 | D67: 5 | E67: TECNOLOGIA E SISTEMAS | F67: AUTOMAÇãO, DADOS E IA | G67: 9.1.01.000 | H67: Insolvência | I67: LEONARDO, JORGE E LIGIA · Fellow.ai | J67: 390
A68: Referência 2026 | B68: referência montada em jul/2026 a partir do realizado até ago | C68: 2026 | D68: 2 | E68: TECNOLOGIA E SISTEMAS | F68: SISTEMAS DE GESTÃO E OPERAÇãO | G68: 9.1.05.000 | H68: T.I. | I68: Guarda Site e Hospedagem | J68: 109.8
A69: Referência 2026 | B69: referência montada em jul/2026 a partir do realizado até ago | C69: 2026 | D69: 5 | E69: TECNOLOGIA E SISTEMAS | F69: SISTEMAS DE GESTÃO E OPERAÇãO | G69: 9.1.05.000 | H69: T.I. | I69: FEEDZ · Solucoes Em Software e Servicos Tts Ltda | J69: 1137.2
A70: Referência 2026 | B70: referência montada em jul/2026 a partir do realizado até ago | C70: 2026 | D70: 2 | E70: DESPESAS DE INFRAESTRUTURA | F70: ENERGIA ELÉTRICA | G70: 5.12.02.000 | H70: Facilities | I70: CPFL ENERGIA S.A | J70: 2100
A71: Referência 2026 | B71: referência montada em jul/2026 a partir do realizado até ago | C71: 2026 | D71: 2 | E71: REMUNERAÇãO FIXA | F71: SALÁRIOS | H71: Facilities | J71: 20000
A72: Referência 2026 | B72: referência montada em jul/2026 a partir do realizado até ago | C72: 2026 | D72: 2 | E72: DESPESAS DE INFRAESTRUTURA | F72: INTERNET | G72: 5.12.03.000 | H72: Facilities | I72: IP DEDICADO · Vivo S.a Telefônica Brasil S.a | J72: 1000
A73: Referência 2026 | B73: referência montada em jul/2026 a partir do realizado até ago | C73: 2026 | D73: 6 | E73: TECNOLOGIA E SISTEMAS | F73: SISTEMAS DE GESTÃO E OPERAÇãO | G73: 9.1.05.000 | H73: Cível | I73: Credvalue Ltda | J73: 1000
A74: Referência 2026 | B74: referência montada em jul/2026 a partir do realizado até ago | C74: 2026 | D74: 6 | E74: IMPOSTOS, TAXAS E SEGUROS | F74: IMPOSTOS E TAXAS | G74: 5.14.03.000 | H74: Facilities | I74: DAS - SIMPLES NACIONAL · MINISTERIO DA ECONOMIA | J74: 40000
A75: Referência 2026 | B75: referência montada em jul/2026 a partir do realizado até ago | C75: 2026 | D75: 2 | E75: DESPESAS DE INFRAESTRUTURA | F75: INTERNET | H75: Facilities | I75: MONITORA DADOS · Vivo S.a Telefônica Brasil S.a | J75: 50
A76: Referência 2026 | B76: referência montada em jul/2026 a partir do realizado até ago | C76: 2026 | D76: 4 | E76: TECNOLOGIA E SISTEMAS | F76: SISTEMAS DE GESTÃO E OPERAÇãO | G76: 9.1.05.000 | H76: T.I. | I76: LICENÇA TEAMS PREMIUM · Scansource Brasil Distribuidora de Tecnologias Ltda | J76: 343.25
A77: Referência 2026 | B77: referência montada em jul/2026 a partir do realizado até ago | C77: 2026 | D77: 4 | E77: COMISSÕES SOBRE VENDAS | F77: COMISSÕES INTERNAS | G77: 4.1.02.000 | H77: Cível | I77: BEATRIZ BALDO · Felipe Soares de Camargo | J77: 100
A78: Referência 2026 | B78: referência montada em jul/2026 a partir do realizado até ago | C78: 2026 | D78: 7 | E78: IMPOSTOS SOBRE SERVIÇOS | F78: IMPOSTOS SOBRE SERVIÇOS - ISS | G78: 3.3.01.000 | H78: Facilities | I78: MUNICIPIO DE CAMPINAS | J78: 10
A79: Referência 2026 | B79: referência montada em jul/2026 a partir do realizado até ago | C79: 2026 | D79: 4 | E79: TECNOLOGIA E SISTEMAS | F79: MARKETING E COMERCIAL | G79: 9.1.03.000 | H79: Marketing | I79: Alemweb Com Servicos de Informacao - Migalhas | J79: 1000
A80: Referência 2026 | B80: referência montada em jul/2026 a partir do realizado até ago | C80: 2026 | D80: 8 | E80: DESPESAS COM SERVIÇOS DE TERCEIROS | F80: CONSULTORIA | G80: 5.8.20.000 | H80: Facilities | I80: Antunes Galvao Consultoria Em Gestao Empresarial | J80: 11062.4
A81: Referência 2026 | B81: referência montada em jul/2026 a partir do realizado até ago | C81: 2026 | D81: 5 | E81: DESPESAS DE INFRAESTRUTURA | F81: ALARME E MONITORAMENTO | G81: 5.12.06.000 | H81: Facilities | I81: Verisure Brasil Monitoramento de Alarmes S.a. | J81: 217.74
A82: Referência 2026 | B82: referência montada em jul/2026 a partir do realizado até ago | C82: 2026 | D82: 8 | E82: DESPESAS COM SERVIÇOS DE TERCEIROS | F82: CONSULTORIA | G82: 5.8.20.000 | H82: Facilities | I82: Mais Humanidade Ltda | J82: 4000
A83: Referência 2026 | B83: referência montada em jul/2026 a partir do realizado até ago | C83: 2026 | D83: 6 | E83: TECNOLOGIA E SISTEMAS | F83: DOMÍNIOS E HOSPEDAGEM | H83: T.I. | I83: DOMÍNIO SITE · FORNECEDOR NÃO CADASTRADO | J83: 74.9
A84: Referência 2026 | B84: referência montada em jul/2026 a partir do realizado até ago | C84: 2026 | D84: 5 | E84: TECNOLOGIA E SISTEMAS | F84: AUTOMAÇãO, DADOS E IA | G84: 9.1.01.000 | H84: T.I. | I84: Openai, L.l.c. | J84: 56.6
A85: Referência 2026 | B85: referência montada em jul/2026 a partir do realizado até ago | C85: 2026 | D85: 1 | E85: TECNOLOGIA E SISTEMAS | F85: AUTOMAÇãO, DADOS E IA | G85: 9.1.01.000 | H85: Operações Legais | I85: SAMUEL · Fellow.ai | J85: 130
A86: Referência 2026 | B86: referência montada em jul/2026 a partir do realizado até ago | C86: 2026 | D86: 8 | E86: TREINAMENTO/DESENVOLVIMENTO/CULTURA | F86: DATAS COMEMORATIVAS | H86: Facilities | I86: DIA DOS PAIS · FORNECEDOR NÃO CADASTRADO | J86: 1716
A87: Referência 2026 | B87: referência montada em jul/2026 a partir do realizado até ago | C87: 2026 | D87: 2 | E87: DESPESAS DE INFRAESTRUTURA | F87: TELEFONIA MÓVEL | G87: 5.12.07.000 | H87: Facilities | I87: CLARO S.A. | J87: 85.84
A88: Referência 2026 | B88: referência montada em jul/2026 a partir do realizado até ago | C88: 2026 | D88: 3 | E88: IMPOSTOS SOBRE SERVIÇOS | F88: IMPOSTOS SOBRE SERVIÇOS - ISS | G88: 3.3.01.000 | H88: Facilities | I88: MUNICIPIO DE CAMPINAS | J88: 10
A89: Referência 2026 | B89: referência montada em jul/2026 a partir do realizado até ago | C89: 2026 | D89: 7 | E89: TECNOLOGIA E SISTEMAS | F89: MARKETING E COMERCIAL | G89: 9.1.03.000 | H89: T.I. | I89: RD CRM · Rd Gestao e Sistemas S.a. | J89: 1350
A90: Referência 2026 | B90: referência montada em jul/2026 a partir do realizado até ago | C90: 2026 | D90: 6 | E90: TECNOLOGIA E SISTEMAS | F90: MARKETING E COMERCIAL | G90: 9.1.03.000 | H90: T.I. | I90: RD MARKETING · Rd Gestao e Sistemas S.a. | J90: 1121
A91: Referência 2026 | B91: referência montada em jul/2026 a partir do realizado até ago | C91: 2026 | D91: 5 | E91: TECNOLOGIA E SISTEMAS | F91: AUTOMAÇãO, DADOS E IA | G91: 9.1.01.000 | H91: Ricardo Viscardi Pires | I91: RICARDO · Fellow.ai | J91: 130
A92: Referência 2026 | B92: referência montada em jul/2026 a partir do realizado até ago | C92: 2026 | D92: 3 | E92: REMUNERAÇãO FIXA | F92: PRÓ-LABORE | G92: 8.1.03.000 | H92: Ricardo Viscardi Pires | I92: Ricardo Viscardi Pires | J92: 60000
A93: Referência 2026 | B93: referência montada em jul/2026 a partir do realizado até ago | C93: 2026 | D93: 6 | E93: DESPESAS DE MANUTENÇãO | F93: MANUTENÇãO PREDIAL | H93: Facilities | I93: FORNECEDOR NÃO CADASTRADO | J93: 2014
A94: Referência 2026 | B94: referência montada em jul/2026 a partir do realizado até ago | C94: 2026 | D94: 2 | E94: COMISSÕES SOBRE VENDAS | F94: COMISSÕES INTERNAS | G94: 4.1.02.000 | H94: Insolvência | I94: FAVIFER, LATASA · Leonardo Loureiro Basso | J94: 2000
A95: Referência 2026 | B95: referência montada em jul/2026 a partir do realizado até ago | C95: 2026 | D95: 1 | E95: REMUNERAÇãO FIXA | F95: PRÓ-LABORE | G95: 8.1.03.000 | H95: Ricardo Viscardi Pires | I95: Ricardo Viscardi Pires | J95: 60000
A96: Referência 2026 | B96: referência montada em jul/2026 a partir do realizado até ago | C96: 2026 | D96: 8 | E96: COMISSÕES SOBRE VENDAS | F96: COMISSÕES INTERNAS | G96: 4.1.02.000 | H96: Cível | I96: ADRIANA CAVALCANTE · Renato Rossetti Vallim de Castro | J96: 100.2
A97: Referência 2026 | B97: referência montada em jul/2026 a partir do realizado até ago | C97: 2026 | D97: 3 | E97: OUTRAS DESPESAS | F97: CARTÃO DE CRÉDITO | G97: 5.16.03.000 | H97: Facilities | I97: ANUIDADE · BANCO BRADESCO CARTOES S.A. | J97: 46
A98: Referência 2026 | B98: referência montada em jul/2026 a partir do realizado até ago | C98: 2026 | D98: 1 | E98: REMUNERAÇãO FIXA | F98: PRÓ-LABORE | G98: 8.1.03.000 | H98: Gustavo Bismarchi Motta | I98: Gustavo Bismarchi Motta | J98: 60000
A99: Referência 2026 | B99: referência montada em jul/2026 a partir do realizado até ago | C99: 2026 | D99: 8 | E99: DESPESAS FINANCEIRAS | F99: DESPESAS BANCÁRIAS | G99: 5.18.01.000 | H99: Facilities | I99: TARIFA CONTA CERTA · ITAU UNIBANCO S.A. | J99: 179
A100: Referência 2026 | B100: referência montada em jul/2026 a partir do realizado até ago | C100: 2026 | D100: 5 | E100: IMPOSTOS, TAXAS E SEGUROS | F100: IMPOSTOS E TAXAS | G100: 5.14.03.000 | H100: Gustavo Bismarchi Motta | I100: GUSTAVO - REGULARIZAÇÃO REF. 2021, 2022, 2023 E 2024 · Ordem dos Advogados do Brasil Al | J100: 880
A101: Referência 2026 | B101: referência montada em jul/2026 a partir do realizado até ago | C101: 2026 | D101: 8 | E101: ENCARGOS SOCIAIS | F101: FGTS | G101: 8.3.01.000 | H101: Facilities | I101: FGTS | J101: 2225
A102: Referência 2026 | B102: referência montada em jul/2026 a partir do realizado até ago | C102: 2026 | D102: 3 | E102: IMPOSTOS, TAXAS E SEGUROS | F102: IMPOSTOS E TAXAS | G102: 5.14.03.000 | H102: Gustavo Bismarchi Motta | I102: GUSTAVO - REGULARIZAÇÃO REF. 2021, 2022, 2023 E 2024 · Ordem dos Advogados do Brasil Df | J102: 440.01
A103: Referência 2026 | B103: referência montada em jul/2026 a partir do realizado até ago | C103: 2026 | D103: 3 | E103: TECNOLOGIA E SISTEMAS | F103: SISTEMAS DE GESTÃO E OPERAÇãO | G103: 9.1.05.000 | H103: T.I. | I103: OFFICE 365 · Vivo S.a Telefônica Brasil S.a | J103: 4300
A104: Referência 2026 | B104: referência montada em jul/2026 a partir do realizado até ago | C104: 2026 | D104: 7 | E104: TECNOLOGIA E SISTEMAS | F104: SISTEMAS DE GESTÃO E OPERAÇãO | G104: 9.1.05.000 | H104: T.I. | I104: LICENÇA TEAMS PREMIUM · Scansource Brasil Distribuidora de Tecnologias Ltda | J104: 343.25
A105: Referência 2026 | B105: referência montada em jul/2026 a partir do realizado até ago | C105: 2026 | D105: 4 | E105: DESPESAS COM SERVIÇOS DE TERCEIROS | F105: HONORÁRIOS CONTÁBEIS | G105: 5.8.19.000 | H105: Facilities | I105: Selores Contabilidade Ss Ltda | J105: 2544.15
... A129: Referência 2026 | B129: referência montada em jul/2026 a partir do realizado até ago | C129: 2026 | D129: 3 | E129: DESPESAS DE MANUTENÇãO | F129: MANUTENÇãO PURIFICADORES DE ÁGUA | G129: 5.9.08.000 | H129: Facilities | I129: MANUTENÇÃO PURIFICADORES · Whirlpool S.a | J129: 234.64
A130: Referência 2026 | B130: referência montada em jul/2026 a partir do realizado até ago | C130: 2026 | D130: 5 | E130: TREINAMENTO/DESENVOLVIMENTO/CULTURA | F130: DATAS COMEMORATIVAS | H130: Facilities | I130: DIA DAS MÃES · FORNECEDOR NÃO CADASTRADO | J130: 1400
A131: Referência 2026 | B131: referência montada em jul/2026 a partir do realizado até ago | C131: 2026 | D131: 4 | E131: TECNOLOGIA E SISTEMAS | F131: AUTOMAÇãO, DADOS E IA | G131: 9.1.01.000 | H131: Operações Legais | I131: SAMUEL · Fellow.ai | J131: 130
A132: Referência 2026 | B132: referência montada em jul/2026 a partir do realizado até ago | C132: 2026 | D132: 4 | E132: ENCARGOS SOCIAIS | F132: INSS | G132: 8.3.02.000 | H132: Facilities | I132: Receita Federal | J132: 15000
A133: Referência 2026 | B133: referência montada em jul/2026 a partir do realizado até ago | C133: 2026 | D133: 2 | E133: DESPESAS DE INFRAESTRUTURA | F133: ALARME E MONITORAMENTO | G133: 5.12.06.000 | H133: Facilities | I133: Verisure Brasil Monitoramento de Alarmes S.a. | J133: 217.74
A134: Referência 2026 | B134: referência montada em jul/2026 a partir do realizado até ago | C134: 2026 | D134: 8 | E134: TREINAMENTO/DESENVOLVIMENTO/CULTURA | F134: EVENTOS | G134: 8.5.04.000 | H134: Facilities | I134: CAFÉ COM CULTURA · Casa Olivetto Eventos | J134: 4500
A135: Referência 2026 | B135: referência montada em jul/2026 a partir do realizado até ago | C135: 2026 | D135: 2 | E135: TECNOLOGIA E SISTEMAS | F135: AUTOMAÇãO, DADOS E IA | G135: 9.1.01.000 | H135: Operações Legais | I135: SAMUEL · Fellow.ai | J135: 130
A136: Referência 2026 | B136: referência montada em jul/2026 a partir do realizado até ago | C136: 2026 | D136: 6 | E136: TECNOLOGIA E SISTEMAS | F136: MARKETING E COMERCIAL | G136: 9.1.03.000 | H136: T.I. | I136: RD CRM · Rd Gestao e Sistemas S.a. | J136: 1350
A137: Referência 2026 | B137: referência montada em jul/2026 a partir do realizado até ago | C137: 2026 | D137: 3 | E137: BENEFÍCIOS | F137: VALE TRANSPORTE | G137: 8.4.02.000 | H137: Facilities | I137: Caju - Beneficios | J137: 4000
A138: Referência 2026 | B138: referência montada em jul/2026 a partir do realizado até ago | C138: 2026 | D138: 1 | E138: DESPESAS COM SERVIÇOS DE TERCEIROS | F138: HONORÁRIOS CONTÁBEIS | G138: 5.8.19.000 | H138: Facilities | I138: Selores Contabilidade Ss Ltda | J138: 2544.15
A139: Referência 2026 | B139: referência montada em jul/2026 a partir do realizado até ago | C139: 2026 | D139: 5 | E139: DESPESAS COM SERVIÇOS DE TERCEIROS | F139: CONSULTORIA | G139: 5.8.20.000 | H139: Facilities | I139: Mais Humanidade Ltda | J139: 4000
A140: Referência 2026 | B140: referência montada em jul/2026 a partir do realizado até ago | C140: 2026 | D140: 8 | E140: DESPESAS DE INFRAESTRUTURA | F140: INTERNET | G140: 5.12.03.000 | H140: Facilities | I140: Vogel Soluções em Telecomunicações e Informática S/A | J140: 709.99
A141: Referência 2026 | B141: referência montada em jul/2026 a partir do realizado até ago | C141: 2026 | D141: 8 | E141: TECNOLOGIA E SISTEMAS | F141: AUTOMAÇãO, DADOS E IA | G141: 9.1.01.000 | H141: Insolvência | I141: LEONARDO, JORGE E LIGIA · Fellow.ai | J141: 390
A142: Referência 2026 | B142: referência montada em jul/2026 a partir do realizado até ago | C142: 2026 | D142: 6 | E142: BENEFÍCIOS | F142: ASSISTÊNCIA MÉDICA E ODONTOLÓGICA | G142: 8.4.03.000 | H142: Cível | I142: SUL AMERICA COMPANHIA DE SEGURO SAUDE | J142: 4766.3
...

Sheet Pessoas_fte
A1: cargo | B1: ativos | C1: peso_fte | D1: fte | E1: nota
A2: Advogado Júnior | B2: 11 | C2: 1 | D2: 11 | E2: cadastro atual, não é headcount histórico
A3: Advogado Pleno | B3: 11 | C3: 1 | D3: 11 | E3: cadastro atual, não é headcount histórico
A4: Estagiário | B4: 7 | C4: 0.75 | D4: 5.25 | E4: peso_fte_estagiario da Configuracao
A5: Sócio de Área | B5: 4 | C5: 1 | D5: 4 | E5: cadastro atual, não é headcount histórico
A6: Coordenador | B6: 4 | C6: 1 | D6: 4 | E6: cadastro atual, não é headcount histórico
A7: Supervisor | B7: 3 | C7: 1 | D7: 3 | E7: cadastro atual, não é headcount histórico
A8: Gerente | B8: 2 | C8: 1 | D8: 2 | E8: cadastro atual, não é headcount histórico
A9: Assistente Administrativo | B9: 2 | C9: 1 | D9: 2 | E9: cadastro atual, não é headcount histórico
A10: Sócio | B10: 2 | C10: 1 | D10: 2 | E10: cadastro atual, não é headcount histórico
A11: Analista Financeiro | B11: 1 | C11: 1 | D11: 1 | E11: cadastro atual, não é headcount histórico
A12: Coordenador Comercial | B12: 1 | C12: 1 | D12: 1 | E12: cadastro atual, não é headcount histórico
A13: Analista Júnior | B13: 1 | C13: 1 | D13: 1 | E13: cadastro atual, não é headcount histórico
... A23: Advogado | B23: 1 | C23: 1 | D23: 1 | E23: cadastro atual, não é headcount histórico
